Workbook

Sheet 00_COE
A1: CHI PHÍ VỐN CSH (COE) — MÔ HÌNH CAPM
A3: Tham số | B3: Giá trị
A4: Rf — Lãi suất phi rủi ro | B4: 0.045
A5: β — Hệ số Beta | B5: 0.8
A6: ERP — Phần bù rủi ro vốn | B6: 0.07
A7: α — Phần bù rủi ro đặc thù (Frontier/Bank) | B7: 0.02
A9: COE = Rf + β × ERP + α | B9: =B4+B5*B6+B7

Sheet 01_Cover
B2: PHÂN TÍCH CỔ PHIẾU NGÂN HÀNG: VIB
B3: Ngân hàng VIB
B5: Giá hiện tại (VND): | C5: ='02_Assumptions'!B2
B6: Giá mục tiêu (VND): | C6: ='07_Valuation'!B21
B7: Upside: | C7: ='07_Valuation'!B23
B8: Khuyến nghị: | C8: =IF('07_Valuation'!B23>0.15,"MUA",IF('07_Valuation'!B23<-0.05,"BÁN","THEO DÕI"))

Sheet 02_Assumptions
A1: Chỉ tiêu | B1: 2021 | C1: 2022 | D1: 2023 | E1: 2024 | F1: 2025 | G1: 2026F | H1: 2027F | I1: 2028F
A2: Giá cổ phiếu (VND) | B2: 16150
A3: Số lượng CP lưu hành | B3: 3404200300
A4: Tín dụng tăng trưởng (%) | G4: 0.14 | H4: 0.13 | I4: 0.12
A5: Huy động tăng trưởng (%) | G5: 0.12 | H5: 0.11 | I5: 0.1
A6: NIM (%) | B6: 0.0396 | C6: 0.0474 | D6: 0.0504 | E6: 0.0378 | F6: 0.0312 | G6: 0.0328 | H6: 0.0337 | I6: 0.0343
A7: CIR (%) | B7: 0.3547 | C7: 0.3432 | D7: 0.2983 | E7: 0.3506 | F7: 0.3716 | G7: 0.33 | H7: 0.32 | I7: 0.32
A8: CoC - Credit Cost (%) | B8: 0.008 | C8: 0.006 | D8: 0.0197 | E8: 0.015 | F8: 0.01 | G8: 0.0095 | H8: 0.009 | I8: 0.0085
A9: NPL ratio (%) | B9: 0.0235 | C9: 0.0248 | D9: 0.032 | E9: 0.0357 | F9: 0.0301 | G9: 0.0286 | H9: 0.0271 | I9: 0.0256
A10: CASA ratio (%) | B10: 0.1611 | C10: 0.1364 | D10: 0.132 | E10: 0.1395 | F10: 0.1439 | G10: 0.1539 | H10: 0.1639 | I10: 0.1739
A11: Tăng trưởng non-TOI (%) | G11: 0.15 | H11: 0.15 | I11: 0.14
A12: Chi phí vốn CSH (COE) | G12: 0.121 | H12: 0.121 | I12: 0.121
A13: Tăng trưởng dài hạn (g) | I13: 0.03
A14: Thuế suất (%) | G14: 0.2 | H14: 0.2 | I14: 0.2
A15: P/B mục tiêu (x) | G15: 1.4807642 | H15: 1.4807642 | I15: 1.4807642

Sheet 03_Income_Model
A1: Chỉ tiêu | B1: 2021 | C1: 2022 | D1: 2023 | E1: 2024 | F1: 2025 | G1: 2026F | H1: 2027F | I1: 2028F
A2: IEA bình quân (tỷ) | B2: 298251.02 | C2: 315494.68 | D2: 366949.06 | E2: 443478.57 | F2: 515510.92 | G2: 580664.08 | H2: 653069.89 | I2: 727988.1
A3: IEA tăng trưởng (%) | C3: 0.1156 | D3: 0.2056 | E3: 0.211 | F3: 0.1223 | G3: 0.13 | H3: 0.12 | I3: 0.11
A4: NIM (%) | B4: 0.0396 | C4: 0.0474 | D4: 0.0504 | E4: 0.0378 | F4: 0.0312 | G4: 0.0328 | H4: 0.0337 | I4: 0.0343
A5: NII (tỷ) | B5: 11816.147 | C5: 14962.555 | D5: 18484.071 | E5: 16750.412 | F5: 16092.16 | G5: =G2*'02_Assumptions'!G6 | H5: =H2*'02_Assumptions'!H6 | I5: =I2*'02_Assumptions'!I6
A6: Thu nhập dịch vụ | B6: 2741.952 | C6: 3188.381 | D6: 2203.263 | E6: 1765.459 | F6: 2105.341
A7: Thu nhập ngoại hối | B7: -86.748 | C7: -275.032 | D7: 548.47 | E7: 500.968 | F7: -154.292
A8: Thu nhập CK đầu tư | B8: 196.796 | C8: -175.843 | D8: 129.73 | E8: 247.967 | F8: 79.774
A9: Thu nhập khác | B9: 220.99 | C9: 354.882 | D9: 791.614 | E9: 1300.5 | F9: 1880.913
A10: Tổng thu nhập ngoài lãi | B10: 3074.756 | C10: 3095.283 | D10: 3676.422 | E10: 3818.64 | F10: 3914.481 | G10: 4501.6531 | H10: 5176.9011 | I10: 5901.6673
A11: Tổng thu nhập HĐ - TOI | B11: 14890.903 | C11: 18057.838 | D11: 22160.493 | E11: 20569.052 | F11: 20006.641 | G11: =G5+G10 | H11: =H5+H10 | I11: =I5+I10
A12: NII/TOI (%) | B12: 79.35 | C12: 82.86 | D12: 83.41 | E12: 81.44 | F12: 80.43
A13: Chi phí HĐ - OPEX | B13: 5281.843 | C13: 6197.114 | D13: 6610.743 | E13: 7211.292 | F13: 7435.006 | G13: =G11*'02_Assumptions'!G7 | H13: =H11*'02_Assumptions'!H7 | I13: =I11*'02_Assumptions'!I7
A14: PPOP - LN trước dự phòng | B14: 9609.06 | C14: 11860.724 | D14: 15549.75 | E14: 13357.76 | F14: 12571.635 | G14: =G11-G13 | H14: =H11-H13 | I14: =I11-I13
A15: PPOP/TOI (%) | B15: 64.53 | C15: 65.68 | D15: 70.17 | E15: 64.94 | F15: 62.84
A16: Dự phòng tín dụng | B16: 1598.048 | C16: 1279.609 | D16: 4845.805 | E16: 4353.458 | F16: 3467.019 | G16: =(('05_Balance_Sheet'!F3+'05_Balance_Sheet'!G3)/2)*'02_Assumptions'!G8 | H16: =(('05_Balance_Sheet'!G3+'05_Balance_Sheet'!H3)/2)*'02_Assumptions'!H8 | I16: =(('05_Balance_Sheet'!H3+'05_Balance_Sheet'!I3)/2)*'02_Assumptions'!I8
A17: LN trước thuế - PBT | B17: 8011.012 | C17: 10581.115 | D17: 10703.945 | E17: 9004.302 | F17: 9104.616 | G17: =G14-G16 | H17: =H14-H16 | I17: =I14-I16

Sheet 04_PnL_Quarterly
A1: Chỉ tiêu | B1: Q2/2023 | C1: Q3/2023 | D1: Q4/2023 | E1: Q1/2024 | F1: Q2/2024 | G1: Q3/2024 | H1: Q4/2024 | I1: Q1/2025 | J1: Q2/2025 | K1: Q3/2025 | L1: Q4/2025 | M1: Q1/2026
A2: Thu nhập lãi thuần - NII | B2: 4401.862 | C2: 4673.187 | D2: 4333.289 | E2: 4357.794 | F2: 4316.913 | G2: 4159.34 | H2: 3916.365 | I2: 3737.109 | J2: 3968.694 | K2: 4172.726 | L2: 4213.631 | M2: 4038.566
A3: Thu nhập ngoài lãi | B3: 962.042 | C3: 1351.309 | D3: 1509.204 | E3: 960.716 | F3: 722.277 | G3: 776.64 | H3: 1359.007 | I3: 864.046 | J3: 1148.124 | K3: 834.306 | L3: 1068.005 | M3: 1821.77
A4: Tổng thu nhập HĐ - TOI | B4: 5363.904 | C4: 6024.496 | D4: 5842.493 | E4: 5318.51 | F4: 5039.19 | G4: 4935.98 | H4: 5275.372 | I4: 4601.155 | J4: 5116.818 | K4: 5007.032 | L4: 5281.636 | M4: 5860.336
A5: Chi phí hoạt động - OPEX | B5: 1555.747 | C5: 1716.919 | D5: 1770.567 | E5: 1871.092 | F5: 1806.19 | G5: 1782.264 | H5: 1751.746 | I5: 1759.035 | J5: 1885.615 | K5: 1819.16 | L5: 1971.196 | M5: 1852.742
A6: LN trước dự phòng - PPOP | B6: 3808.157 | C6: 4307.577 | D6: 4071.926 | E6: 3447.418 | F6: 3233 | G6: 3153.716 | H6: 3523.626 | I6: 2842.12 | J6: 3231.203 | K6: 3187.872 | L6: 3310.44 | M6: 4007.594
A7: Dự phòng tín dụng | B7: 860.152 | C7: 1624.784 | D7: 1693.469 | E7: 945.488 | F7: 1129.885 | G7: 1155.569 | H7: 1122.516 | I7: 421.332 | J7: 635.637 | K7: 1157.888 | L7: 1252.162 | M7: 1204.926
A8: LN trước thuế - PBT | B8: 2948.005 | C8: 2682.793 | D8: 2378.457 | E8: 2501.93 | F8: 2103.115 | G8: 1998.147 | H8: 2401.11 | I8: 2420.788 | J8: 2595.566 | K8: 2029.984 | L8: 2058.278 | M8: 2802.668
A9: LN sau thuế - NPAT | B9: 2358.4 | C9: 2146.903 | D9: 1902.006 | E9: 2001.143 | F9: 1682.962 | G9: 1599.173 | H9: 1921.192 | I9: 1936.464 | J9: 2076.469 | K9: 1624.513 | L9: 1647.984 | M9: 2241.191

Sheet 04_PnL
A1: Chỉ tiêu | B1: 2021 | C1: 2022 | D1: 2023 | E1: 2024 | F1: 2025 | G1: 2026F | H1: 2027F | I1: 2028F
A2: Thu nhập lãi thuần (NII) | B2: 11816.147 | C2: 14962.555 | D2: 18484.071 | E2: 16750.412 | F2: 16092.16 | G2: ='03_Income_Model'!G5 | H2: ='03_Income_Model'!H5 | I2: ='03_Income_Model'!I5
A3: Tổng thu nhập hoạt động (TOI) | B3: 14890.903 | C3: 18057.838 | D3: 22160.493 | E3: 20569.052 | F3: 20006.641 | G3: =SUM(G2+'03_Income_Model'!G10) | H3: =SUM(H2+'03_Income_Model'!H10) | I3: =SUM(I2+'03_Income_Model'!I10)
A4: Lợi nhuận trước dự phòng (PPOP) | B4: 9609.06 | C4: 11860.724 | D4: 15549.75 | E4: 13357.76 | F4: 12571.635 | G4: ='03_Income_Model'!G14 | H4: ='03_Income_Model'!H14 | I4: ='03_Income_Model'!I14
A5: LNST (NPAT) | B5: 6409.75 | C5: 8468.767 | D5: 8563.053 | E5: 7204.47 | F5: 7285.43 | G5: =('03_Income_Model'!G17)-MAX(('03_Income_Model'!G17)*'02_Assumptions'!G14,0) | H5: =('03_Income_Model'!H17)-MAX(('03_Income_Model'!H17)*'02_Assumptions'!H14,0) | I5: =('03_Income_Model'!I17)-MAX(('03_Income_Model'!I17)*'02_Assumptions'!I14,0)
A6: EPS (VND) | B6: 1882.8945 | C6: 2487.7405 | D6: 2515.4375 | E6: 2116.3473 | F6: 2140.1297 | G6: =G5*1000000000/'02_Assumptions'!$B$3 | H6: =H5*1000000000/'02_Assumptions'!$B$3 | I6: =I5*1000000000/'02_Assumptions'!$B$3

Sheet 05_Balance_Sheet_Quarterly
A1: Chỉ tiêu | B1: Q2/2023 | C1: Q3/2023 | D1: Q4/2023 | E1: Q1/2024 | F1: Q2/2024 | G1: Q3/2024 | H1: Q4/2024 | I1: Q1/2025 | J1: Q2/2025 | K1: Q3/2025 | L1: Q4/2025 | M1: Q1/2026
A2: Tổng tài sản | B2: 378662.84 | C2: 384419.1 | D2: 409880.58 | E2: 413887.82 | F2: 430962.08 | G2: 445377.59 | H2: 493158.37 | I2: 495727.38 | J2: 530909.02 | K2: 543559.67 | L2: 556098.44 | M2: 564145.94
A3: Tiền mặt & NHNN | B3: 1315.853 | C3: 1545.792 | D3: 1681.071 | E3: 1715.126 | F3: 1703.868 | G3: 1625.047 | H3: 1639.368 | I3: 1646.956 | J3: 1843.449 | K3: 1934.668 | L3: 3552.574 | M3: 1876.239
A4: TG các TCTD khác | B4: 79806.086 | C4: 74707.078 | D4: 68197.574 | E4: 92771.841 | F4: 114455.66 | G4: 82657.125 | H4: 105588.52 | I4: 102269.01 | J4: 97946.353 | K4: 104756.56 | L4: 104411.12 | M4: 114132.18
A5: Cho vay khách hàng | B5: 231347 | C5: 241890.74 | D5: 262074.23 | E5: 262910.84 | F5: 273996.2 | G5: 292146.17 | H5: 318316.08 | I5: 329264.07 | J5: 351360.11 | K5: 367863.42 | L5: 377113.2 | M5: 381361.99
A6: CK đầu tư | B6: 50259.444 | C6: 52384.561 | D6: 60988.364 | E6: 44298.356 | F6: 28742.093 | G6: 57909.577 | H6: 50344.312 | I6: 49438.602 | J6: 67210.426 | K6: 53170.066 | L6: 51149.531 | M6: 49089.083
A7: Tiền gửi khách hàng | B7: 205302.77 | C7: 213533.76 | D7: 236577.27 | E7: 234210.79 | F7: 247629.78 | G7: 255632.64 | H7: 276308.32 | I7: 282298.04 | J7: 304392.95 | K7: 307929.16 | L7: 294577.66 | M7: 316373.84
A8: Vốn chủ sở hữu | B8: 33909.846 | C8: 36039.756 | D8: 37938.955 | E8: 38415.725 | F8: 38350.429 | G8: 39942.085 | H8: 41861.809 | I8: 43643.267 | J8: 43627.741 | K8: 45259.765 | L8: 46904.739 | M8: 49144.071

Sheet 05_Balance_Sheet
A1: Chỉ tiêu | B1: 2021 | C1: 2022 | D1: 2023 | E1: 2024 | F1: 2025 | G1: 2026F | H1: 2027F | I1: 2028F
A2: Tổng tài sản | B2: 309517.13 | C2: 342798.92 | D2: 409881.37 | E2: 493158.37 | F2: 556098.44 | G2: =SUM(G3:G6)+G7-G8-G9+G10 | H2: =SUM(H3:H6)+H7-H8-H9+H10 | I2: =SUM(I3:I6)+I7-I8-I9+I10
A3: Cho vay khách hàng (Gross) | B3: 199116.43 | C3: 228879.24 | D3: 262075.02 | E3: 318316.08 | F3: 377113.2 | G3: =F3*(1+'02_Assumptions'!G4) | H3: =G3*(1+'02_Assumptions'!H4) | I3: =H3*(1+'02_Assumptions'!I4)
A4: Trái phiếu doanh nghiệp | B4: 21702.85 | C4: 18345.796 | D4: 15123.396 | E4: 20244.697 | F4: 43794.655 | G4: =F4*(1+'02_Assumptions'!G4) | H4: =G4*(1+'02_Assumptions'!H4) | I4: =H4*(1+'02_Assumptions'!I4)
A5: Tiền gửi khách hàng | B5: 173564.89 | C5: 200123.94 | D5: 236577.27 | E5: 276308.32 | F5: 294577.66 | G5: =F5*(1+'02_Assumptions'!G5) | H5: =G5*(1+'02_Assumptions'!H5) | I5: =H5*(1+'02_Assumptions'!I5)
A6: Giấy tờ có giá phát hành (Bonds) | B6: 42298.182 | C6: 31774.818 | D6: 23896.936 | E6: 23262.579 | F6: 35070.7 | G6: =F6*1.02 | H6: =G6*1.02 | I6: =H6*1.02
A7: Tiền gửi Kho bạc Nhà nước | B7: 10430.709 | C7: 9164.688 | D7: 7720.366 | E7: 24250.175 | F7: 20931.899 | G7: =F7*(1+'02_Assumptions'!G5) | H7: =G7*(1+'02_Assumptions'!H5) | I7: =H7*(1+'02_Assumptions'!I5)
A8: Tiền gửi ký quỹ (trừ đi) | B8: 9221.084 | C8: 8120.838 | D8: 9883.707 | E8: 17666.375 | F8: 22152.864 | G8: =F8*(1+'02_Assumptions'!G5) | H8: =G8*(1+'02_Assumptions'!H5) | I8: =H8*(1+'02_Assumptions'!I5)
A9: Vốn chuyên dùng (trừ đi) | B9: 8.648 | C9: 8.092 | D9: 6.93 | E9: 5.368 | F9: 3.306 | G9: =F9*1.02 | H9: =G9*1.02 | I9: =H9*1.02
A10: Vốn chủ sở hữu (VCSH) | B10: 24290.74 | C10: 32651.042 | D10: 37939.587 | E10: 41861.809 | F10: 46904.739 | G10: =F10+'04_PnL'!G5*0.7 | H10: =G10+'04_PnL'!H5*0.7 | I10: =H10+'04_PnL'!I5*0.7

Sheet 06_Ratios_Quarterly
A1: Chỉ tiêu | B1: Q2/2023 | C1: Q3/2023 | D1: Q4/2023 | E1: Q1/2024 | F1: Q2/2024 | G1: Q3/2024 | H1: Q4/2024 | I1: Q1/2025 | J1: Q2/2025 | K1: Q3/2025 | L1: Q4/2025 | M1: Q1/2026
A2: NIM — năm hóa (%) | B2: =('04_PnL_Quarterly'!B2*4/'05_Balance_Sheet_Quarterly'!B4)*100 | C2: =('04_PnL_Quarterly'!C2*4/'05_Balance_Sheet_Quarterly'!C4)*100 | D2: =('04_PnL_Quarterly'!D2*4/'05_Balance_Sheet_Quarterly'!D4)*100 | E2: =('04_PnL_Quarterly'!E2*4/'05_Balance_Sheet_Quarterly'!E4)*100 | F2: =('04_PnL_Quarterly'!F2*4/'05_Balance_Sheet_Quarterly'!F4)*100 | G2: =('04_PnL_Quarterly'!G2*4/'05_Balance_Sheet_Quarterly'!G4)*100 | H2: =('04_PnL_Quarterly'!H2*4/'05_Balance_Sheet_Quarterly'!H4)*100 | I2: =('04_PnL_Quarterly'!I2*4/'05_Balance_Sheet_Quarterly'!I4)*100 | ... M2: =('04_PnL_Quarterly'!M2*4/'05_Balance_Sheet_Quarterly'!M4)*100
A3: ROE — năm hóa (%) | B3: =('04_PnL_Quarterly'!B8*4/'05_Balance_Sheet_Quarterly'!B7)*100 | C3: =('04_PnL_Quarterly'!C8*4/'05_Balance_Sheet_Quarterly'!C7)*100 | D3: =('04_PnL_Quarterly'!D8*4/'05_Balance_Sheet_Quarterly'!D7)*100 | E3: =('04_PnL_Quarterly'!E8*4/'05_Balance_Sheet_Quarterly'!E7)*100 | F3: =('04_PnL_Quarterly'!F8*4/'05_Balance_Sheet_Quarterly'!F7)*100 | G3: =('04_PnL_Quarterly'!G8*4/'05_Balance_Sheet_Quarterly'!G7)*100 | H3: =('04_PnL_Quarterly'!H8*4/'05_Balance_Sheet_Quarterly'!H7)*100 | I3: =('04_PnL_Quarterly'!I8*4/'05_Balance_Sheet_Quarterly'!I7)*100 | ... M3: =('04_PnL_Quarterly'!M8*4/'05_Balance_Sheet_Quarterly'!M7)*100
A4: LDR (%) | B4: =('05_Balance_Sheet_Quarterly'!B4/'05_Balance_Sheet_Quarterly'!B6)*100 | C4: =('05_Balance_Sheet_Quarterly'!C4/'05_Balance_Sheet_Quarterly'!C6)*100 | D4: =('05_Balance_Sheet_Quarterly'!D4/'05_Balance_Sheet_Quarterly'!D6)*100 | E4: =('05_Balance_Sheet_Quarterly'!E4/'05_Balance_Sheet_Quarterly'!E6)*100 | F4: =('05_Balance_Sheet_Quarterly'!F4/'05_Balance_Sheet_Quarterly'!F6)*100 | G4: =('05_Balance_Sheet_Quarterly'!G4/'05_Balance_Sheet_Quarterly'!G6)*100 | H4: =('05_Balance_Sheet_Quarterly'!H4/'05_Balance_Sheet_Quarterly'!H6)*100 | I4: =('05_Balance_Sheet_Quarterly'!I4/'05_Balance_Sheet_Quarterly'!I6)*100 | ... M4: =('05_Balance_Sheet_Quarterly'!M4/'05_Balance_Sheet_Quarterly'!M6)*100

Sheet 06_Ratios
A1: Chỉ tiêu | B1: 2021 | C1: 2022 | D1: 2023 | E1: 2024 | F1: 2025 | G1: 2026F | H1: 2027F | I1: 2028F
A2: NIM (%) | B2: 0.0396 | C2: 0.0474 | D2: 0.0504 | E2: 0.0378 | F2: 0.0312 | G2: 0.0328 | H2: 0.0337 | I2: 0.0343
A3: CIR (%) | B3: 0.3547 | C3: 0.3432 | D3: 0.2983 | E3: 0.3506 | F3: 0.3716 | G3: 0.33 | H3: 0.32 | I3: 0.32
A4: ROE (%) | B4: 0.2639 | C4: 0.2975 | D4: 0.2426 | E4: 0.1806 | F4: 0.1641 | G4: ='04_PnL'!G5/AVERAGE('05_Balance_Sheet'!F10,'05_Balance_Sheet'!G10) | H4: ='04_PnL'!H5/AVERAGE('05_Balance_Sheet'!G10,'05_Balance_Sheet'!H10) | I4: ='04_PnL'!I5/AVERAGE('05_Balance_Sheet'!H10,'05_Balance_Sheet'!I10)
A5: ROA (%) | B5: 0.0207 | C5: 0.0247 | D5: 0.0209 | E5: 0.0146 | F5: 0.0131 | G5: ='04_PnL'!G5/AVERAGE('05_Balance_Sheet'!F2,'05_Balance_Sheet'!G2) | H5: ='04_PnL'!H5/AVERAGE('05_Balance_Sheet'!G2,'05_Balance_Sheet'!H2) | I5: ='04_PnL'!I5/AVERAGE('05_Balance_Sheet'!H2,'05_Balance_Sheet'!I2)
A6: LDR — điều chỉnh (%) | B6: =SUM('05_Balance_Sheet'!B3:B4)/(SUM('05_Balance_Sheet'!B5:B6)+'05_Balance_Sheet'!B7*0.0-'05_Balance_Sheet'!B8-'05_Balance_Sheet'!B9) | C6: =SUM('05_Balance_Sheet'!C3:C4)/(SUM('05_Balance_Sheet'!C5:C6)+'05_Balance_Sheet'!C7*0.0-'05_Balance_Sheet'!C8-'05_Balance_Sheet'!C9) | D6: =SUM('05_Balance_Sheet'!D3:D4)/(SUM('05_Balance_Sheet'!D5:D6)+'05_Balance_Sheet'!D7*0.35-'05_Balance_Sheet'!D8-'05_Balance_Sheet'!D9) | E6: =SUM('05_Balance_Sheet'!E3:E4)/(SUM('05_Balance_Sheet'!E5:E6)+'05_Balance_Sheet'!E7*0.5-'05_Balance_Sheet'!E8-'05_Balance_Sheet'!E9) | F6: =SUM('05_Balance_Sheet'!F3:F4)/(SUM('05_Balance_Sheet'!F5:F6)+'05_Balance_Sheet'!F7*0.6-'05_Balance_Sheet'!F8-'05_Balance_Sheet'!F9) | G6: =SUM('05_Balance_Sheet'!G3:G4)/(SUM('05_Balance_Sheet'!G5:G6)+'05_Balance_Sheet'!G7*0.8-'05_Balance_Sheet'!G8-'05_Balance_Sheet'!G9) | H6: =SUM('05_Balance_Sheet'!H3:H4)/(SUM('05_Balance_Sheet'!H5:H6)+'05_Balance_Sheet'!H7*0.8-'05_Balance_Sheet'!H8-'05_Balance_Sheet'!H9) | I6: =SUM('05_Balance_Sheet'!I3:I4)/(SUM('05_Balance_Sheet'!I5:I6)+'05_Balance_Sheet'!I7*0.8-'05_Balance_Sheet'!I8-'05_Balance_Sheet'!I9)
A7: NPL (%) | B7: 0.0235 | C7: 0.0248 | D7: 0.032 | E7: 0.0357 | F7: 0.0301 | G7: 0.0286 | H7: 0.0271 | I7: 0.0256
A8: CoC — Credit Cost (%) | B8: 0.008 | C8: 0.006 | D8: 0.0197 | E8: 0.015 | F8: 0.01 | G8: 0.0095 | H8: 0.009 | I8: 0.0085
A9: CASA ratio (%) | B9: 0.1611 | C9: 0.1364 | D9: 0.132 | E9: 0.1395 | F9: 0.1439 | G9: 0.1539 | H9: 0.1639 | I9: 0.1739

Sheet 07_Valuation
A1: PHƯƠNG PHÁP ĐỊNH GIÁ
A2: Chi phí vốn CSH (COE) | B2: ='00_COE'!B9
A3: Tăng trưởng dài hạn (g) | B3: 0.03
A5: RESIDUAL INCOME MODEL
A6: BV/share hiện tại (VND) | B6: ='05_Balance_Sheet'!F10*1000000000/'02_Assumptions'!$B$3
A7: PV của RI 3 năm (VND) | B7: =SUM(B31:D31)
A8: PV của Continuing Value (VND) | B8: =((D29*(1+B3)/(B2-B3))*D30)*0.5
A9: GIÁ TRỊ RI (VND) | B9: =B6+B7+B8
A11: P/B MULTIPLE — 3 mức phân phối lịch sử
A12: P/B hiện tại (x) | B12: ='02_Assumptions'!B2/B6
A13: P/B hấp dẫn (x) — MUA | B13: =PERCENTILE('13_PE_PB_History'!C22:C33, 0.25) | C13: Median P/B nửa dưới (vùng mua hấp dẫn)
A14: P/B median all-time (x) — FAIR VALUE | B14: =MEDIAN('13_PE_PB_History'!C22:C33) | C14: Median PB toàn bộ lịch sử
A15: P/B chốt lời (x) — BÁN / CHỐT LỜI | B15: =PERCENTILE('13_PE_PB_History'!C22:C33, 0.75) | C15: Median P/B nửa trên (vùng chốt lời)
A16: BV/share tương lai (2026F) | B16: =B6+B26
A17: GIÁ TRỊ P/B (VND) | B17: =B14*B16
A19: WEIGHTED TARGET PRICE
A20: Trong số: 50% RI + 50% P/B
A21: Target Price (VND) | B21: =B9*0.5+B17*0.5
A22: Giá hiện tại (VND) | B22: ='02_Assumptions'!B2
A23: UPSIDE (%) | B23: =B21/B22-1
A25: --- RI DETAIL ---
A26: EPS (VND) | B26: ='04_PnL'!G6 | C26: ='04_PnL'!H6 | D26: ='04_PnL'!I6
A27: BVPS đầu kỳ (VND) | B27: =B6 | C27: =B27+B26 | D27: =C27+C26
A28: Capital Charge (VND) | B28: =B27*'07_Valuation'!$B$2 | C28: =C27*'07_Valuation'!$B$2 | D28: =D27*'07_Valuation'!$B$2
A29: Residual Income (VND) | B29: =B26-B28 | C29: =C26-C28 | D29: =D26-D28
A30: Discount Factor | B30: =1/(1+'07_Valuation'!$B$2)^1 | C30: =1/(1+'07_Valuation'!$B$2)^2 | D30: =1/(1+'07_Valuation'!$B$2)^3
A31: PV of RI | B31: =B29*B30 | C31: =C29*C30 | D31: =D29*D30

Sheet 08_Sensitivity
A1: Độ nhạy: Giá trị RI theo COE × g (5×5)
A2: COE \ g | B2: 0.01 | C2: 0.02 | D2: 0.03 | E2: 0.04 | F2: 0.05
A3: 0.08 | B3: 25719.779 | C3: 27239.975 | D3: 29368.25 | E3: 32560.662 | F3: 37881.348
A4: 0.1 | B4: 23344.08 | C4: 24198.908 | D4: 25297.972 | E4: 26763.391 | F4: 28814.977
A5: 0.12 | B5: 21814.658 | C5: 22354.377 | D5: 23014.033 | E5: 23838.604 | F5: 24898.766
A6: 0.14 | B6: 20742.263 | C6: 21109.598 | D6: 21543.721 | E6: 22064.669 | F6: 22701.383
A7: 0.16 | B7: 19945.127 | C7: 20208.676 | D7: 20512.77 | E7: 20867.548 | F7: 21286.83

Sheet 09_PESTLE
A1: Nhân tố | B1: Nội dung | C1: Tác động | D1: Mức độ
A2: Chính trị (Political) | B2: Môi trường chính trị ổn định, NHNN điều hành linh hoạt hỗ trợ tăng trưởng tín dụng. | C2: Tích cực | D2: Cao
A3: Kinh tế (Economic) | B3: GDP tăng trưởng 6–7%, nhu cầu vốn sản xuất–tiêu dùng cao, lãi suất huy động giảm dần. | C3: Tích cực | D3: Cao
A4: Xã hội (Social) | B4: Tầng lớp trung lưu mở rộng, thanh toán không tiền mặt tăng mạnh thúc đẩy CASA và phí dịch vụ. | C4: Tích cực | D4: Trung bình
A5: Công nghệ (Technological) | B5: Chuyển đổi số banking (mobile/open banking) giảm CIR, tăng CASA và cross-sell sản phẩm. | C5: Tích cực | D5: Cao
A6: Pháp lý (Legal) | B6: Thông tư 06/2024 siết TPDN, Basel II/III nâng chuẩn CAR — cần theo dõi áp lực pháp lý. | C6: Trung tính | D6: Trung bình
A7: Môi trường (Environmental) | B7: ESG lending ngày càng được yêu cầu; rủi ro tín dụng BĐS liên quan biến đổi khí hậu tăng. | C7: Tiêu cực | D7: Thấp

Sheet 10_Leading_Indicators
A1: Chỉ số | B1: Ngưỡng tích cực | C1: Giá trị hiện tại | D1: Trạng thái
A2: NPL ratio (%) | B2: < 1.5% | C2: 3.01% | D2: Đạt
A3: CASA ratio (%) | B3: > 20% | C3: 14.39% | D3: Tốt
A4: NIM (%) | B4: > 3.0% | C4: 3.12% | D4: Tốt

Sheet 11_Investment_Thesis
A1: Luận điểm chính | B1: Chi tiết nhận định
A2: Lợi thế CASA vượt trội | B2: Hệ sinh thái số hóa giúp huy động dòng vốn rẻ dồi dào, ổn định biên lãi NIM.
A3: Hiệu quả sinh lời cao | B3: Chỉ số ROE và ROA luôn nằm trong nhóm dẫn đầu hệ thống ngân hàng TMCP.

Sheet 12_Summary_Snapshot
A1: Chỉ tiêu | B1: 2021 | C1: 2022 | D1: 2023 | E1: 2024 | F1: 2025 | G1: 2026F | H1: 2027F | I1: 2028F
A2: Thu nhập lãi thuần (NII) | B2: 11816.147 | C2: 14962.555 | D2: 18484.071 | E2: 16750.412 | F2: 16092.16 | G2: 19045.782 | H2: 22008.455 | I2: 24969.992
A3: Tổng thu nhập hoạt động (TOI) | B3: 14890.903 | C3: 18057.838 | D3: 22160.493 | E3: 20569.052 | F3: 20006.641 | G3: 23547.435 | H3: 27185.356 | I3: 30871.659
A4: Lợi nhuận trước dự phòng (PPOP) | B4: 9609.06 | C4: 11860.724 | D4: 15549.75 | E4: 13357.76 | F4: 12571.635 | G4: 15776.781 | H4: 18486.042 | I4: 20992.728
A5: LNST (NPAT) | B5: 6409.75 | C5: 8468.767 | D5: 8563.053 | E5: 7204.47 | F5: 7285.43 | G5: 9554.7406 | H5: 11492.291 | I5: 13292.556
A6: EPS (VND) | B6: 1882.8945 | C6: 2487.7405 | D6: 2515.4375 | E6: 2116.3473 | F6: 2140.1297 | G6: 2806.7504 | H6: 3375.9152 | I6: 3904.7515
A7: Tổng tài sản | B7: 309517.13 | C7: 342798.92 | D7: 409881.37 | E7: 493158.37 | F7: 556098.44
A8: Cho vay khách hàng (Gross) | B8: 199116.43 | C8: 228879.24 | D8: 262075.02 | E8: 318316.08 | F8: 377113.2 | G8: 429909.04 | H8: 485797.22 | I8: 544092.88
A9: Trái phiếu doanh nghiệp | B9: 21702.85 | C9: 18345.796 | D9: 15123.396 | E9: 20244.697 | F9: 43794.655
A10: Tiền gửi khách hàng | B10: 173564.89 | C10: 200123.94 | D10: 236577.27 | E10: 276308.32 | F10: 294577.66 | G10: 329926.98 | H10: 366218.95 | I10: 402840.84
A11: Giấy tờ có giá phát hành (Bonds) | B11: 42298.182 | C11: 31774.818 | D11: 23896.936 | E11: 23262.579 | F11: 35070.7
A12: Tiền gửi Kho bạc Nhà nước | B12: 10430.709 | C12: 9164.688 | D12: 7720.366 | E12: 24250.175 | F12: 20931.899
A13: Tiền gửi ký quỹ (trừ đi) | B13: 9221.084 | C13: 8120.838 | D13: 9883.707 | E13: 17666.375 | F13: 22152.864
A14: Vốn chuyên dùng (trừ đi) | B14: 8.648 | C14: 8.092 | D14: 6.93 | E14: 5.368 | F14: 3.306
A15: Vốn chủ sở hữu (VCSH) | B15: 24290.74 | C15: 32651.042 | D15: 37939.587 | E15: 41861.809 | F15: 46904.739

Sheet 13_PE_PB_History
A1: Quỳ | B1: P/E (x) | C1: P/B (x) | D1: EV/EBITDA (x) | E1: Giá
A2: Q2/18 | B2: 10.840407 | C2: 1.709906
A3: Q3/18 | B3: 8.6097538 | C3: 1.5164805
A4: Q4/18 | B4: 6.7369146 | C4: 1.3271303
A5: Q1/19 | B5: 6.7946988 | C5: 1.3404628
A6: Q2/19 | B6: 5.6456249 | C6: 1.2713375
A7: Q3/19 | B7: 5.9902458 | C7: 1.4456984
A8: Q4/19 | B8: 5.0098 | C8: 1.2954824
A9: Q1/20 | B9: 4.2397969 | C9: 1.0312173
A10: Q2/20 | B10: 5.1957878 | C10: 1.2754079
A11: Q3/20 | B11: 8.3521689 | C11: 2.0286368
A12: Q4/20 | B12: 9.1080981 | C12: 2.2855458
A13: Q1/21 | B13: 13.095666 | C13: 3.3823903
... A35: MEDIAN ALL-TIME | B35: 7.4729375 | C35: 1.4267657
