Workbook

Sheet 00_COE
A1: CHI PHÍ VỐN CSH (COE) — MÔ HÌNH CAPM
A3: Tham số | B3: Giá trị
A4: Rf — Lãi suất phi rủi ro | B4: 0.045
A5: β — Hệ số Beta | B5: 0.98
A6: ERP — Phần bù rủi ro vốn | B6: 0.07
A7: α — Phần bù rủi ro đặc thù (Frontier/Bank) | B7: 0.02
A9: COE = Rf + β × ERP + α | B9: =B4+B5*B6+B7

Sheet 01_Cover
B2: PHÂN TÍCH CỔ PHIẾU NGÂN HÀNG: TCB
B3: Ngân hàng TCB
B5: Giá hiện tại (VND): | C5: ='02_Assumptions'!B2
B6: Giá mục tiêu (VND): | C6: ='07_Valuation'!B21
B7: Upside: | C7: ='07_Valuation'!B23
B8: Khuyến nghị: | C8: =IF('07_Valuation'!B23>0.15,"MUA",IF('07_Valuation'!B23<-0.05,"BÁN","THEO DÕI"))

Sheet 02_Assumptions
A1: Chỉ tiêu | B1: 2021 | C1: 2022 | D1: 2023 | E1: 2024 | F1: 2025 | G1: 2026F | H1: 2027F | I1: 2028F
A2: Giá cổ phiếu (VND) | B2: 33400
A3: Số lượng CP lưu hành | B3: 7862636600
A4: Tín dụng tăng trưởng (%) | G4: 0.14 | H4: 0.13 | I4: 0.12
A5: Huy động tăng trưởng (%) | G5: 0.12 | H5: 0.11 | I5: 0.1
A6: NIM (%) | B6: 0.0513 | C6: 0.0532 | D6: 0.0404 | E6: 0.0426 | F6: 0.0378 | G6: 0.0397 | H6: 0.0408 | I6: 0.0416
A7: CIR (%) | B7: 0.3014 | C7: 0.3213 | D7: 0.3308 | E7: 0.3271 | F7: 0.3078 | G7: 0.33 | H7: 0.32 | I7: 0.32
A8: CoC - Credit Cost (%) | B8: 0.0078 | C8: 0.0051 | D8: 0.0084 | E8: 0.0072 | F8: 0.0064 | G8: 0.0061 | H8: 0.0058 | I8: 0.0054
A9: NPL ratio (%) | B9: 0.0067 | C9: 0.0073 | D9: 0.0117 | E9: 0.0114 | F9: 0.0108 | G9: 0.0103 | H9: 0.0097 | I9: 0.0092
A10: CASA ratio (%) | B10: 0.4698 | C10: 0.3434 | D10: 0.38 | E10: 0.3594 | F10: 0.3448 | G10: 0.3548 | H10: 0.3648 | I10: 0.3748
A11: Tăng trưởng non-TOI (%) | G11: 0.15 | H11: 0.15 | I11: 0.14
A12: Chi phí vốn CSH (COE) | G12: 0.1336 | H12: 0.1336 | I12: 0.1336
A13: Tăng trưởng dài hạn (g) | I13: 0.03
A14: Thuế suất (%) | G14: 0.2 | H14: 0.2 | I14: 0.2
A15: P/B mục tiêu (x) | G15: 1.4563578 | H15: 1.4563578 | I15: 1.4563578

Sheet 03_Income_Model
A1: Chỉ tiêu | B1: 2021 | C1: 2022 | D1: 2023 | E1: 2024 | F1: 2025 | G1: 2026F | H1: 2027F | I1: 2028F
A2: IEA bình quân (tỷ) | B2: 520194.1 | C2: 569081.67 | D2: 685155.23 | E2: 833463.76 | F2: 1009356.7 | G2: 1175895.3 | H2: 1322523.4 | I2: 1474239.3
A3: IEA tăng trưởng (%) | C3: 0.188 | D3: 0.2174 | E3: 0.2157 | F3: 0.2072 | G3: 0.13 | H3: 0.12 | I3: 0.11
A4: NIM (%) | B4: 0.0513 | C4: 0.0532 | D4: 0.0404 | E4: 0.0426 | F4: 0.0378 | G4: 0.0397 | H4: 0.0408 | I4: 0.0416
A5: NII (tỷ) | B5: 26698.613 | C5: 30289.775 | D5: 27691.12 | E5: 35507.963 | F5: 38155.091 | G5: =G2*'02_Assumptions'!G6 | H5: =H2*'02_Assumptions'!H6 | I5: =I2*'02_Assumptions'!I6
A6: Thu nhập dịch vụ | B6: 6382.24 | C6: 8152.605 | D6: 8714.897 | E6: 8042.248 | F6: 8771.995
A7: Thu nhập ngoại hối | B7: 231.416 | C7: -275.063 | D7: 195.75 | E7: 592.556 | F7: 1642.201
A8: Thu nhập CK đầu tư | B8: 1956.713 | C8: 183.708 | D8: 990.453 | E8: 2440.358 | F8: 2898.295
A9: Thu nhập khác | B9: 1803.246 | C9: 2167.375 | D9: 2434.116 | E9: 342.711 | F9: 1884.342
A10: Tổng thu nhập ngoài lãi | B10: 10377.678 | C10: 10237.416 | D10: 12369.972 | E10: 11482.434 | F10: 15236.034 | G10: 17521.439 | H10: 20149.655 | I10: 22970.607
A11: Tổng thu nhập HĐ - TOI | B11: 37076.291 | C11: 40527.191 | D11: 40061.092 | E11: 46990.397 | F11: 53391.125 | G11: =G5+G10 | H11: =H5+H10 | I11: =I5+I10
A12: NII/TOI (%) | B12: 72.01 | C12: 74.74 | D12: 69.12 | E12: 75.56 | F12: 71.46
A13: Chi phí HĐ - OPEX | B13: 11173.395 | C13: 13023.129 | D13: 13251.796 | E13: 15369.735 | F13: 16432.434 | G13: =G11*'02_Assumptions'!G7 | H13: =H11*'02_Assumptions'!H7 | I13: =I11*'02_Assumptions'!I7
A14: PPOP - LN trước dự phòng | B14: 25902.896 | C14: 27504.062 | D14: 26809.296 | E14: 31620.662 | F14: 36958.691 | G14: =G11-G13 | H14: =H11-H13 | I14: =I11-I13
A15: PPOP/TOI (%) | B15: 69.86 | C15: 67.87 | D15: 66.92 | E15: 67.29 | F15: 69.22
A16: Dự phòng tín dụng | B16: 2664.603 | C16: 1936.294 | D16: 3921.068 | E16: 4082.294 | F16: 4420.625 | G16: =(('05_Balance_Sheet'!F3+'05_Balance_Sheet'!G3)/2)*'02_Assumptions'!G8 | H16: =(('05_Balance_Sheet'!G3+'05_Balance_Sheet'!H3)/2)*'02_Assumptions'!H8 | I16: =(('05_Balance_Sheet'!H3+'05_Balance_Sheet'!I3)/2)*'02_Assumptions'!I8
A17: LN trước thuế - PBT | B17: 23238.293 | C17: 25567.768 | D17: 22888.228 | E17: 27538.368 | F17: 32538.066 | G17: =G14-G16 | H17: =H14-H16 | I17: =I14-I16

Sheet 04_PnL_Quarterly
A1: Chỉ tiêu | B1: Q2/2023 | C1: Q3/2023 | D1: Q4/2023 | E1: Q1/2024 | F1: Q2/2024 | G1: Q3/2024 | H1: Q4/2024 | I1: Q1/2025 | J1: Q2/2025 | K1: Q3/2025 | L1: Q4/2025 | M1: Q1/2026
A2: Thu nhập lãi thuần - NII | B2: 6294.877 | C2: 7272.16 | D2: 7597.203 | E2: 8499.544 | F2: 9477.926 | G2: 8928.676 | H2: 8601.817 | I2: 8305.393 | J2: 9137.076 | K2: 9924.643 | L2: 10787.979 | M2: 9522.053
A3: Thu nhập ngoài lãi | B3: 3030.294 | C3: 3146.333 | D3: 3420.251 | E3: 3762.223 | F3: 3941.77 | G3: 2825.659 | H3: 952.782 | I3: 3305.805 | J3: 3605.955 | K3: 4317.48 | L3: 4006.794 | M3: 4152.221
A4: Tổng thu nhập HĐ - TOI | B4: 9325.171 | C4: 10418.493 | D4: 11017.454 | E4: 12261.767 | F4: 13419.696 | G4: 11754.335 | H4: 9554.599 | I4: 11611.198 | J4: 12743.031 | K4: 14242.123 | L4: 14794.773 | M4: 13674.274
A5: Chi phí hoạt động - OPEX | B5: 2868.89 | C5: 3630.731 | D5: 3610.089 | E5: 3249.136 | F5: 3948.974 | G5: 3430.902 | H5: 4740.723 | I5: 3284.915 | J5: 3830.693 | K5: 4492.851 | L5: 4823.975 | M5: 3869.012
A6: LN trước dự phòng - PPOP | B6: 6456.281 | C6: 6787.762 | D6: 7407.365 | E6: 9012.631 | F6: 9470.722 | G6: 8323.433 | H6: 4813.876 | I6: 8326.283 | J6: 8912.338 | K6: 9749.272 | L6: 9970.798 | M6: 9805.262
A7: Dự phòng tín dụng | B7: 807.271 | C7: 944.972 | D7: 1634.295 | E7: 1210.972 | F7: 1644.213 | G7: 1109.265 | H7: 117.844 | I7: 1090.055 | J7: 1013.75 | K7: 1499.256 | L7: 817.564 | M7: 935.292
A8: LN trước thuế - PBT | B8: 5649.01 | C8: 5842.79 | D8: 5773.07 | E8: 7801.659 | F8: 7826.509 | G8: 7214.168 | H8: 4696.032 | I8: 7236.228 | J8: 7898.588 | K8: 8250.016 | L8: 9153.234 | M8: 8869.97
A9: LN sau thuế - NPAT | B9: 4503.449 | C9: 4668.705 | D9: 4481.615 | E9: 6277.003 | F9: 6269.968 | G9: 5793.022 | H9: 3420.111 | I9: 6013.511 | J9: 6347.61 | K9: 6613.525 | L9: 6979.826 | M9: 6950.28

Sheet 04_PnL
A1: Chỉ tiêu | B1: 2021 | C1: 2022 | D1: 2023 | E1: 2024 | F1: 2025 | G1: 2026F | H1: 2027F | I1: 2028F
A2: Thu nhập lãi thuần (NII) | B2: 26698.613 | C2: 30289.775 | D2: 27691.12 | E2: 35507.963 | F2: 38155.091 | G2: ='03_Income_Model'!G5 | H2: ='03_Income_Model'!H5 | I2: ='03_Income_Model'!I5
A3: Tổng thu nhập hoạt động (TOI) | B3: 37076.291 | C3: 40527.191 | D3: 40061.092 | E3: 46990.397 | F3: 53391.125 | G3: =SUM(G2+'03_Income_Model'!G10) | H3: =SUM(H2+'03_Income_Model'!H10) | I3: =SUM(I2+'03_Income_Model'!I10)
A4: Lợi nhuận trước dự phòng (PPOP) | B4: 25902.896 | C4: 27504.062 | D4: 26809.296 | E4: 31620.662 | F4: 36958.691 | G4: ='03_Income_Model'!G14 | H4: ='03_Income_Model'!H14 | I4: ='03_Income_Model'!I14
A5: LNST (NPAT) | B5: 18415.382 | C5: 20436.426 | D5: 18190.866 | E5: 21760.104 | F5: 25954.472 | G5: =('03_Income_Model'!G17)-MAX(('03_Income_Model'!G17)*'02_Assumptions'!G14,0) | H5: =('03_Income_Model'!H17)-MAX(('03_Income_Model'!H17)*'02_Assumptions'!H14,0) | I5: =('03_Income_Model'!I17)-MAX(('03_Income_Model'!I17)*'02_Assumptions'!I14,0)
A6: EPS (VND) | B6: 2342.1383 | C6: 2599.1823 | D6: 2313.5835 | E6: 2767.5327 | F6: 3300.9884 | G6: =G5*1000000000/'02_Assumptions'!$B$3 | H6: =H5*1000000000/'02_Assumptions'!$B$3 | I6: =I5*1000000000/'02_Assumptions'!$B$3

Sheet 05_Balance_Sheet_Quarterly
A1: Chỉ tiêu | B1: Q2/2023 | C1: Q3/2023 | D1: Q4/2023 | E1: Q1/2024 | F1: Q2/2024 | G1: Q3/2024 | H1: Q4/2024 | I1: Q1/2025 | J1: Q2/2025 | K1: Q3/2025 | L1: Q4/2025 | M1: Q1/2026
A2: Tổng tài sản | B2: 732470.17 | C2: 781278.67 | D2: 849482.01 | E2: 885653.46 | F2: 908306.7 | G2: 927053.34 | H2: 978798.55 | I2: 989215.99 | J2: 1037645.4 | K2: 1129570.5 | L2: 1192344.1 | M2: 1190453.8
A3: Tiền mặt & NHNN | B3: 3112.603 | C3: 3505.804 | D3: 3620.695 | E3: 3665.067 | F3: 3638.265 | G3: 3608.503 | H3: 3384.77 | I3: 3789.947 | J3: 3666.435 | K3: 4045.689 | L3: 4360.821 | M3: 5467.7
A4: TG các TCTD khác | B4: 71193.282 | C4: 69386.021 | D4: 104072.32 | E4: 89074.54 | F4: 88903.726 | G4: 90014.293 | H4: 84590.474 | I4: 81883.43 | J4: 80845.693 | K4: 92999.089 | L4: 114958.31 | M4: 87777.341
A5: Cho vay khách hàng | B5: 460753.04 | C5: 469588.52 | D5: 512513.67 | E5: 552577.12 | F5: 584713.48 | G5: 617924.57 | H5: 623634.27 | I5: 655007.21 | J5: 700801.93 | K5: 756078 | L5: 757118.75 | M5: 785612.53
A6: CK đầu tư | B6: 107847.62 | C6: 121243.2 | D6: 104993.95 | E6: 131188.84 | F6: 113677.24 | G6: 102135.24 | H6: 148623.64 | I6: 124378.66 | J6: 146985.6 | K6: 139296.46 | L6: 145526.4 | M6: 141063.97
A7: Tiền gửi khách hàng | B7: 381946.52 | C7: 409044.57 | D7: 454660.78 | E7: 458040.69 | F7: 481860.24 | G7: 494954.02 | H7: 533392.35 | I7: 531583.05 | J7: 545078.84 | K7: 595086.94 | L7: 618911.54 | M7: 599808.24
A8: Vốn chủ sở hữu | B8: 122464.97 | C8: 127129.79 | D8: 131628.07 | E8: 137872.73 | F8: 138551.66 | G8: 144367.98 | H8: 147939.62 | I8: 153952.67 | J8: 161827.23 | K8: 179430.59 | L8: 179501.44 | M8: 186682.77

Sheet 05_Balance_Sheet
A1: Chỉ tiêu | B1: 2021 | C1: 2022 | D1: 2023 | E1: 2024 | F1: 2025 | G1: 2026F | H1: 2027F | I1: 2028F
A2: Tổng tài sản | B2: 568728.95 | C2: 699032.54 | D2: 849482.01 | E2: 978798.55 | F2: 1192344.1 | G2: =SUM(G3:G6)+G7-G8-G9+G10 | H2: =SUM(H3:H6)+H7-H8-H9+H10 | I2: =SUM(I3:I6)+I7-I8-I9+I10
A3: Cho vay khách hàng (Gross) | B3: 343605.58 | C3: 415752.26 | D3: 512513.67 | E3: 623634.27 | F3: 757118.75 | G3: =F3*(1+'02_Assumptions'!G4) | H3: =G3*(1+'02_Assumptions'!H4) | I3: =H3*(1+'02_Assumptions'!I4)
A4: Trái phiếu doanh nghiệp | B4: 200 | C4: 0 | D4: 0 | E4: 6900 | F4: 0 | G4: =F4*(1+'02_Assumptions'!G4) | H4: =G4*(1+'02_Assumptions'!H4) | I4: =H4*(1+'02_Assumptions'!I4)
A5: Tiền gửi khách hàng | B5: 314752.53 | C5: 358403.78 | D5: 454660.78 | E5: 533392.35 | F5: 618911.54 | G5: =F5*(1+'02_Assumptions'!G5) | H5: =G5*(1+'02_Assumptions'!H5) | I5: =H5*(1+'02_Assumptions'!I5)
A6: Giấy tờ có giá phát hành (Bonds) | B6: 33679.824 | C6: 34006.619 | D6: 84703.3 | E6: 140422.32 | F6: 215330.13 | G6: =F6*1.02 | H6: =G6*1.02 | I6: =H6*1.02
A7: Tiền gửi Kho bạc Nhà nước | B7: 34711.477 | C7: 70525.051 | D7: 80543.555 | E7: 39512.096 | F7: 72324.964 | G7: =F7*(1+'02_Assumptions'!G5) | H7: =G7*(1+'02_Assumptions'!H5) | I7: =H7*(1+'02_Assumptions'!I5)
A8: Tiền gửi ký quỹ (trừ đi) | B8: 11956.065 | C8: 13303.703 | D8: 13948.273 | E8: 20192.422 | F8: 23104.566 | G8: =F8*(1+'02_Assumptions'!G5) | H8: =G8*(1+'02_Assumptions'!H5) | I8: =H8*(1+'02_Assumptions'!I5)
A9: Vốn chuyên dùng (trừ đi) | B9: 0 | C9: 0 | D9: 0 | E9: 0 | F9: 0 | G9: =F9*1.02 | H9: =G9*1.02 | I9: =H9*1.02
A10: Vốn chủ sở hữu (VCSH) | B10: 93041.472 | C10: 113424.97 | D10: 131616.07 | E10: 147939.62 | F10: 179501.44 | G10: =F10+'04_PnL'!G5*0.7 | H10: =G10+'04_PnL'!H5*0.7 | I10: =H10+'04_PnL'!I5*0.7

Sheet 06_Ratios_Quarterly
A1: Chỉ tiêu | B1: Q2/2023 | C1: Q3/2023 | D1: Q4/2023 | E1: Q1/2024 | F1: Q2/2024 | G1: Q3/2024 | H1: Q4/2024 | I1: Q1/2025 | J1: Q2/2025 | K1: Q3/2025 | L1: Q4/2025 | M1: Q1/2026
A2: NIM — năm hóa (%) | B2: =('04_PnL_Quarterly'!B2*4/'05_Balance_Sheet_Quarterly'!B4)*100 | C2: =('04_PnL_Quarterly'!C2*4/'05_Balance_Sheet_Quarterly'!C4)*100 | D2: =('04_PnL_Quarterly'!D2*4/'05_Balance_Sheet_Quarterly'!D4)*100 | E2: =('04_PnL_Quarterly'!E2*4/'05_Balance_Sheet_Quarterly'!E4)*100 | F2: =('04_PnL_Quarterly'!F2*4/'05_Balance_Sheet_Quarterly'!F4)*100 | G2: =('04_PnL_Quarterly'!G2*4/'05_Balance_Sheet_Quarterly'!G4)*100 | H2: =('04_PnL_Quarterly'!H2*4/'05_Balance_Sheet_Quarterly'!H4)*100 | I2: =('04_PnL_Quarterly'!I2*4/'05_Balance_Sheet_Quarterly'!I4)*100 | ... M2: =('04_PnL_Quarterly'!M2*4/'05_Balance_Sheet_Quarterly'!M4)*100
A3: ROE — năm hóa (%) | B3: =('04_PnL_Quarterly'!B8*4/'05_Balance_Sheet_Quarterly'!B7)*100 | C3: =('04_PnL_Quarterly'!C8*4/'05_Balance_Sheet_Quarterly'!C7)*100 | D3: =('04_PnL_Quarterly'!D8*4/'05_Balance_Sheet_Quarterly'!D7)*100 | E3: =('04_PnL_Quarterly'!E8*4/'05_Balance_Sheet_Quarterly'!E7)*100 | F3: =('04_PnL_Quarterly'!F8*4/'05_Balance_Sheet_Quarterly'!F7)*100 | G3: =('04_PnL_Quarterly'!G8*4/'05_Balance_Sheet_Quarterly'!G7)*100 | H3: =('04_PnL_Quarterly'!H8*4/'05_Balance_Sheet_Quarterly'!H7)*100 | I3: =('04_PnL_Quarterly'!I8*4/'05_Balance_Sheet_Quarterly'!I7)*100 | ... M3: =('04_PnL_Quarterly'!M8*4/'05_Balance_Sheet_Quarterly'!M7)*100
A4: LDR (%) | B4: =('05_Balance_Sheet_Quarterly'!B4/'05_Balance_Sheet_Quarterly'!B6)*100 | C4: =('05_Balance_Sheet_Quarterly'!C4/'05_Balance_Sheet_Quarterly'!C6)*100 | D4: =('05_Balance_Sheet_Quarterly'!D4/'05_Balance_Sheet_Quarterly'!D6)*100 | E4: =('05_Balance_Sheet_Quarterly'!E4/'05_Balance_Sheet_Quarterly'!E6)*100 | F4: =('05_Balance_Sheet_Quarterly'!F4/'05_Balance_Sheet_Quarterly'!F6)*100 | G4: =('05_Balance_Sheet_Quarterly'!G4/'05_Balance_Sheet_Quarterly'!G6)*100 | H4: =('05_Balance_Sheet_Quarterly'!H4/'05_Balance_Sheet_Quarterly'!H6)*100 | I4: =('05_Balance_Sheet_Quarterly'!I4/'05_Balance_Sheet_Quarterly'!I6)*100 | ... M4: =('05_Balance_Sheet_Quarterly'!M4/'05_Balance_Sheet_Quarterly'!M6)*100

Sheet 06_Ratios
A1: Chỉ tiêu | B1: 2021 | C1: 2022 | D1: 2023 | E1: 2024 | F1: 2025 | G1: 2026F | H1: 2027F | I1: 2028F
A2: NIM (%) | B2: 0.0513 | C2: 0.0532 | D2: 0.0404 | E2: 0.0426 | F2: 0.0378 | G2: 0.0397 | H2: 0.0408 | I2: 0.0416
A3: CIR (%) | B3: 0.3014 | C3: 0.3213 | D3: 0.3308 | E3: 0.3271 | F3: 0.3078 | G3: 0.33 | H3: 0.32 | I3: 0.32
A4: ROE (%) | B4: 0.1979 | C4: 0.198 | D4: 0.1485 | E4: 0.1557 | F4: 0.1585 | G4: ='04_PnL'!G5/AVERAGE('05_Balance_Sheet'!F10,'05_Balance_Sheet'!G10) | H4: ='04_PnL'!H5/AVERAGE('05_Balance_Sheet'!G10,'05_Balance_Sheet'!H10) | I4: ='04_PnL'!I5/AVERAGE('05_Balance_Sheet'!H10,'05_Balance_Sheet'!I10)
A5: ROA (%) | B5: 0.0324 | C5: 0.0292 | D5: 0.0214 | E5: 0.0222 | F5: 0.0218 | G5: ='04_PnL'!G5/AVERAGE('05_Balance_Sheet'!F2,'05_Balance_Sheet'!G2) | H5: ='04_PnL'!H5/AVERAGE('05_Balance_Sheet'!G2,'05_Balance_Sheet'!H2) | I5: ='04_PnL'!I5/AVERAGE('05_Balance_Sheet'!H2,'05_Balance_Sheet'!I2)
A6: LDR — điều chỉnh (%) | B6: =SUM('05_Balance_Sheet'!B3:B4)/(SUM('05_Balance_Sheet'!B5:B6)+'05_Balance_Sheet'!B7*0.0-'05_Balance_Sheet'!B8-'05_Balance_Sheet'!B9) | C6: =SUM('05_Balance_Sheet'!C3:C4)/(SUM('05_Balance_Sheet'!C5:C6)+'05_Balance_Sheet'!C7*0.0-'05_Balance_Sheet'!C8-'05_Balance_Sheet'!C9) | D6: =SUM('05_Balance_Sheet'!D3:D4)/(SUM('05_Balance_Sheet'!D5:D6)+'05_Balance_Sheet'!D7*0.35-'05_Balance_Sheet'!D8-'05_Balance_Sheet'!D9) | E6: =SUM('05_Balance_Sheet'!E3:E4)/(SUM('05_Balance_Sheet'!E5:E6)+'05_Balance_Sheet'!E7*0.5-'05_Balance_Sheet'!E8-'05_Balance_Sheet'!E9) | F6: =SUM('05_Balance_Sheet'!F3:F4)/(SUM('05_Balance_Sheet'!F5:F6)+'05_Balance_Sheet'!F7*0.6-'05_Balance_Sheet'!F8-'05_Balance_Sheet'!F9) | G6: =SUM('05_Balance_Sheet'!G3:G4)/(SUM('05_Balance_Sheet'!G5:G6)+'05_Balance_Sheet'!G7*0.8-'05_Balance_Sheet'!G8-'05_Balance_Sheet'!G9) | H6: =SUM('05_Balance_Sheet'!H3:H4)/(SUM('05_Balance_Sheet'!H5:H6)+'05_Balance_Sheet'!H7*0.8-'05_Balance_Sheet'!H8-'05_Balance_Sheet'!H9) | I6: =SUM('05_Balance_Sheet'!I3:I4)/(SUM('05_Balance_Sheet'!I5:I6)+'05_Balance_Sheet'!I7*0.8-'05_Balance_Sheet'!I8-'05_Balance_Sheet'!I9)
A7: NPL (%) | B7: 0.0067 | C7: 0.0073 | D7: 0.0117 | E7: 0.0114 | F7: 0.0108 | G7: 0.0103 | H7: 0.0097 | I7: 0.0092
A8: CoC — Credit Cost (%) | B8: 0.0078 | C8: 0.0051 | D8: 0.0084 | E8: 0.0072 | F8: 0.0064 | G8: 0.0061 | H8: 0.0058 | I8: 0.0054
A9: CASA ratio (%) | B9: 0.4698 | C9: 0.3434 | D9: 0.38 | E9: 0.3594 | F9: 0.3448 | G9: 0.3548 | H9: 0.3648 | I9: 0.3748

Sheet 07_Valuation
A1: PHƯƠNG PHÁP ĐỊNH GIÁ
A2: Chi phí vốn CSH (COE) | B2: ='00_COE'!B9
A3: Tăng trưởng dài hạn (g) | B3: 0.03
A5: RESIDUAL INCOME MODEL
A6: BV/share hiện tại (VND) | B6: ='05_Balance_Sheet'!F10*1000000000/'02_Assumptions'!$B$3
A7: PV của RI 3 năm (VND) | B7: =SUM(B31:D31)
A8: PV của Continuing Value (VND) | B8: =((D29*(1+B3)/(B2-B3))*D30)*0.5
A9: GIÁ TRỊ RI (VND) | B9: =B6+B7+B8
A11: P/B MULTIPLE — 3 mức phân phối lịch sử
A12: P/B hiện tại (x) | B12: ='02_Assumptions'!B2/B6
A13: P/B hấp dẫn (x) — MUA | B13: =PERCENTILE('13_PE_PB_History'!C21:C32, 0.25) | C13: Median P/B nửa dưới (vùng mua hấp dẫn)
A14: P/B median all-time (x) — FAIR VALUE | B14: =MEDIAN('13_PE_PB_History'!C21:C32) | C14: Median PB toàn bộ lịch sử
A15: P/B chốt lời (x) — BÁN / CHỐT LỜI | B15: =PERCENTILE('13_PE_PB_History'!C21:C32, 0.75) | C15: Median P/B nửa trên (vùng chốt lời)
A16: BV/share tương lai (2026F) | B16: =B6+B26
A17: GIÁ TRỊ P/B (VND) | B17: =B14*B16
A19: WEIGHTED TARGET PRICE
A20: Trong số: 50% RI + 50% P/B
A21: Target Price (VND) | B21: =B9*0.5+B17*0.5
A22: Giá hiện tại (VND) | B22: ='02_Assumptions'!B2
A23: UPSIDE (%) | B23: =B21/B22-1
A25: --- RI DETAIL ---
A26: EPS (VND) | B26: ='04_PnL'!G6 | C26: ='04_PnL'!H6 | D26: ='04_PnL'!I6
A27: BVPS đầu kỳ (VND) | B27: =B6 | C27: =B27+B26 | D27: =C27+C26
A28: Capital Charge (VND) | B28: =B27*'07_Valuation'!$B$2 | C28: =C27*'07_Valuation'!$B$2 | D28: =D27*'07_Valuation'!$B$2
A29: Residual Income (VND) | B29: =B26-B28 | C29: =C26-C28 | D29: =D26-D28
A30: Discount Factor | B30: =1/(1+'07_Valuation'!$B$2)^1 | C30: =1/(1+'07_Valuation'!$B$2)^2 | D30: =1/(1+'07_Valuation'!$B$2)^3
A31: PV of RI | B31: =B29*B30 | C31: =C29*C30 | D31: =D29*D30

Sheet 08_Sensitivity
A1: Độ nhạy: Giá trị RI theo COE × g (5×5)
A2: COE \ g | B2: 0.01 | C2: 0.02 | D2: 0.03 | E2: 0.04 | F2: 0.05
A3: 0.08 | B3: 31535.188 | C3: 32641.849 | D3: 34191.175 | E3: 36515.163 | F3: 40388.477
A4: 0.1 | B4: 29805.199 | C4: 30427.49 | D4: 31227.579 | E4: 32294.363 | F4: 33787.862
A5: 0.12 | B5: 28691.307 | C5: 29084.207 | D5: 29564.419 | E5: 30164.684 | F5: 30936.453
A6: 0.14 | B6: 27910.147 | C6: 28177.556 | D6: 28493.586 | E6: 28872.822 | F6: 29336.332
A7: 0.16 | B7: 27329.393 | C7: 27521.25 | D7: 27742.622 | E7: 28000.89 | F7: 28306.116

Sheet 09_PESTLE
A1: Nhân tố | B1: Nội dung | C1: Tác động | D1: Mức độ
A2: Chính trị (Political) | B2: Môi trường chính trị ổn định, NHNN điều hành linh hoạt hỗ trợ tăng trưởng tín dụng. | C2: Tích cực | D2: Cao
A3: Kinh tế (Economic) | B3: GDP tăng trưởng 6–7%, nhu cầu vốn sản xuất–tiêu dùng cao, lãi suất huy động giảm dần. | C3: Tích cực | D3: Cao
A4: Xã hội (Social) | B4: Tầng lớp trung lưu mở rộng, thanh toán không tiền mặt tăng mạnh thúc đẩy CASA và phí dịch vụ. | C4: Tích cực | D4: Trung bình
A5: Công nghệ (Technological) | B5: Chuyển đổi số banking (mobile/open banking) giảm CIR, tăng CASA và cross-sell sản phẩm. | C5: Tích cực | D5: Cao
A6: Pháp lý (Legal) | B6: Thông tư 06/2024 siết TPDN, Basel II/III nâng chuẩn CAR — cần theo dõi áp lực pháp lý. | C6: Trung tính | D6: Trung bình
A7: Môi trường (Environmental) | B7: ESG lending ngày càng được yêu cầu; rủi ro tín dụng BĐS liên quan biến đổi khí hậu tăng. | C7: Tiêu cực | D7: Thấp

Sheet 10_Leading_Indicators
A1: Chỉ số | B1: Ngưỡng tích cực | C1: Giá trị hiện tại | D1: Trạng thái
A2: NPL ratio (%) | B2: < 1.5% | C2: 1.08% | D2: Đạt
A3: CASA ratio (%) | B3: > 20% | C3: 34.48% | D3: Tốt
A4: NIM (%) | B4: > 3.0% | C4: 3.78% | D4: Tốt

Sheet 11_Investment_Thesis
A1: Luận điểm chính | B1: Chi tiết nhận định
A2: Lợi thế CASA vượt trội | B2: Hệ sinh thái số hóa giúp huy động dòng vốn rẻ dồi dào, ổn định biên lãi NIM.
A3: Hiệu quả sinh lời cao | B3: Chỉ số ROE và ROA luôn nằm trong nhóm dẫn đầu hệ thống ngân hàng TMCP.

Sheet 12_Summary_Snapshot
A1: Chỉ tiêu | B1: 2021 | C1: 2022 | D1: 2023 | E1: 2024 | F1: 2025 | G1: 2026F | H1: 2027F | I1: 2028F
A2: Thu nhập lãi thuần (NII) | B2: 26698.613 | C2: 30289.775 | D2: 27691.12 | E2: 35507.963 | F2: 38155.091 | G2: 46683.044 | H2: 53958.954 | I2: 61328.354
A3: Tổng thu nhập hoạt động (TOI) | B3: 37076.291 | C3: 40527.191 | D3: 40061.092 | E3: 46990.397 | F3: 53391.125 | G3: 64204.483 | H3: 74108.609 | I3: 84298.961
A4: Lợi nhuận trước dự phòng (PPOP) | B4: 25902.896 | C4: 27504.062 | D4: 26809.296 | E4: 31620.662 | F4: 36958.691 | G4: 43017.004 | H4: 50393.854 | I4: 57323.293
A5: LNST (NPAT) | B5: 18415.382 | C5: 20436.426 | D5: 18190.866 | E5: 21760.104 | F5: 25954.472 | G5: 30460.232 | H5: 36049.913 | I5: 41392.448
A6: EPS (VND) | B6: 2342.1383 | C6: 2599.1823 | D6: 2313.5835 | E6: 2767.5327 | F6: 3300.9884 | G6: 3874.048 | H6: 4584.9649 | I6: 5264.4488
A7: Tổng tài sản | B7: 568728.95 | C7: 699032.54 | D7: 849482.01 | E7: 978798.55 | F7: 1192344.1
A8: Cho vay khách hàng (Gross) | B8: 343605.58 | C8: 415752.26 | D8: 512513.67 | E8: 623634.27 | F8: 757118.75 | G8: 863115.38 | H8: 975320.38 | I8: 1092358.8
A9: Trái phiếu doanh nghiệp | B9: 200 | C9: 0 | D9: 0 | E9: 6900 | F9: 0
A10: Tiền gửi khách hàng | B10: 314752.53 | C10: 358403.78 | D10: 454660.78 | E10: 533392.35 | F10: 618911.54 | G10: 693180.92 | H10: 769430.82 | I10: 846373.9
A11: Giấy tờ có giá phát hành (Bonds) | B11: 33679.824 | C11: 34006.619 | D11: 84703.3 | E11: 140422.32 | F11: 215330.13
A12: Tiền gửi Kho bạc Nhà nước | B12: 34711.477 | C12: 70525.051 | D12: 80543.555 | E12: 39512.096 | F12: 72324.964
A13: Tiền gửi ký quỹ (trừ đi) | B13: 11956.065 | C13: 13303.703 | D13: 13948.273 | E13: 20192.422 | F13: 23104.566
A14: Vốn chuyên dùng (trừ đi) | B14: 0 | C14: 0 | D14: 0 | E14: 0 | F14: 0
A15: Vốn chủ sở hữu (VCSH) | B15: 93041.472 | C15: 113424.97 | D15: 131616.07 | E15: 147939.62 | F15: 179501.44

Sheet 13_PE_PB_History
A1: Quỳ | B1: P/E (x) | C1: P/B (x) | D1: EV/EBITDA (x) | E1: Giá
A2: Q3/18 | B2: 10.848603 | C2: 2.049471
A3: Q4/18 | B3: 10.20653 | C3: 1.8832315
A4: Q1/19 | B4: 10.060768 | C4: 1.6464212
A5: Q2/19 | B5: 8.5457101 | C5: 1.3519338
A6: Q3/19 | B6: 9.4717886 | C6: 1.4846297
A7: Q4/19 | B7: 8.7821251 | C7: 1.3913663
A8: Q1/20 | B8: 5.9406023 | C8: 0.96876684
A9: Q2/20 | B9: 6.5290253 | C9: 1.0622946
A10: Q3/20 | B10: 7.5261695 | C10: 1.2188484
A11: Q4/20 | B11: 10.286093 | C11: 1.6737237
A12: Q1/21 | B12: 11.218552 | C12: 1.8651941
A13: Q2/21 | B13: 13.131655 | C13: 2.3877964
... A34: MEDIAN ALL-TIME | B34: 8.7083436 | C34: 1.2722808

Sheet 14_Credit_Funding_Growth
A1: Quý | B1: Tổng Tín dụng (tỷ VND) | C1: Tổng Huy động (tỷ VND) | D1: Tăng trưởng Tín dụng QoQ (%) | E1: Tăng trưởng Huy động QoQ (%)
A2: Q2/18 | B2: 168352.17 | C2: 205187.51 | D2: 0.0032 | E2: 0.0185
A3: Q3/18 | B3: 180268.21 | C3: 210823.2 | D3: 0.0708 | E3: 0.0275
A4: Q4/18 | B4: 177793.13 | C4: 214649.3 | D4: -0.0137 | E4: 0.0181
A5: Q1/19 | B5: 177078.68 | C5: 220844.22 | D5: -0.004 | E5: 0.0289
A6: Q2/19 | B6: 197293.49 | C6: 232904.78 | D6: 0.1142 | E6: 0.0546
A7: Q3/19 | B7: 211168.21 | C7: 233143.29 | D7: 0.0703 | E7: 0.001
A8: Q4/19 | B8: 228087.29 | C8: 248757.39 | D8: 0.0801 | E8: 0.067
A9: Q1/20 | B9: 229737.64 | C9: 252570.89 | D9: 0.0072 | E9: 0.0153
A10: Q2/20 | B10: 230085.47 | C10: 273261.75 | D10: 0.0015 | E10: 0.0819
A11: Q3/20 | B11: 228867.89 | C11: 275357.33 | D11: -0.0053 | E11: 0.0077
A12: Q4/20 | B12: 275510.37 | C12: 305358.29 | D12: 0.2038 | E12: 0.109
A13: Q1/21 | B13: 293999.39 | C13: 313481.37 | D13: 0.0671 | E13: 0.0266
... A33: Q1/26 | B33: 785612.53 | C33: 867468.7 | D33: 0.0376 | E33: -0.0087

Sheet 15_Peer_Benchmark
A1: Ngân hàng | B1: NPL (%) | C1: NIM (%) | D1: CASA (%) | E1: ROE (%) | F1: CIR (%) | G1: P/B (x) | H1: Tăng trưởng tín dụng (%) | I1: Vốn hóa (tỷ VND)
A2: Trung bình ngành | B2: 2 | C2: 3.5 | D2: 20 | E2: 15 | F2: 35 | G2: 1 | H2: 12 | I2: -
A3: VCB — Vietcombank | B3: 0.02 | C3: 0.035 | D3: 0.2 | E3: 0.15 | F3: 0.35 | G3: 1 | H3: 0.12 | I3: 50000
A4: BID — BIDV | B4: 0.02 | C4: 0.035 | D4: 0.2 | E4: 0.15 | F4: 0.35 | G4: 1 | H4: 0.12 | I4: 50000
A5: CTG — VietinBank | B5: 0.02 | C5: 0.035 | D5: 0.2 | E5: 0.15 | F5: 0.35 | G5: 1 | H5: 0.12 | I5: 50000
A6: TCB — Techcombank | B6: 0.02 | C6: 0.035 | D6: 0.2 | E6: 0.15 | F6: 0.35 | G6: 1 | H6: 0.12 | I6: 50000
A7: MBB — MBBank | B7: 0.02 | C7: 0.035 | D7: 0.2 | E7: 0.15 | F7: 0.35 | G7: 1 | H7: 0.12 | I7: 50000
A8: ACB — ACB | B8: 0.02 | C8: 0.035 | D8: 0.2 | E8: 0.15 | F8: 0.35 | G8: 1 | H8: 0.12 | I8: 50000
A9: VIB — VIB | B9: 0.02 | C9: 0.035 | D9: 0.2 | E9: 0.15 | F9: 0.35 | G9: 1 | H9: 0.12 | I9: 50000
A10: HDB — HDBank | B10: 0.02 | C10: 0.035 | D10: 0.2 | E10: 0.15 | F10: 0.35 | G10: 1 | H10: 0.12 | I10: 50000
A11: STB — Sacombank | B11: 0.02 | C11: 0.035 | D11: 0.2 | E11: 0.15 | F11: 0.35 | G11: 1 | H11: 0.12 | I11: 50000
A12: VPB — VPBank | B12: 0.02 | C12: 0.035 | D12: 0.2 | E12: 0.15 | F12: 0.35 | G12: 1 | H12: 0.12 | I12: 50000
A13: TPB — TPBank | B13: 0.02 | C13: 0.035 | D13: 0.2 | E13: 0.15 | F13: 0.35 | G13: 1 | H13: 0.12 | I13: 50000
A14: MSB — MSB | B14: 0.02 | C14: 0.035 | D14: 0.2 | E14: 0.15 | F14: 0.35 | G14: 1 | H14: 0.12 | I14: 50000
... A20: NAB — NamABank | B20: 0.02 | C20: 0.035 | D20: 0.2 | E20: 0.15 | F20: 0.35 | G20: 1 | H20: 0.12 | I20: 50000
