Workbook

Sheet 01_Trang bìa
B2: PHÂN TÍCH ĐẦU TƯ CỔ PHIẾU DHC
B3: Công ty Cổ phần Đông Hải Bến Tre | HOSE: DHC | Ngành Giấy & Bao bì
B4: CHỈ TIÊU CHÍNH 2025A/2026E
B5: Ngày phân tích | C5: 17/06/2026 | E5: EPS 2025A (VNĐ/CP) | F5: 3,988
B6: Sàn niêm yết | C6: HOSE | E6: EPS 2026E (VNĐ/CP) | F6: ~4,400
B7: Khuyến nghị | C7: MUA / TÍCH LŨY | E7: P/E Forward | F7: 8.3x
B8: Giá mục tiêu | C8: 47,000 VNĐ/CP | E8: EV/EBITDA 2025A | F8: 5.2x
B9: Giá thị trường | C9: 36,600 VNĐ/CP | E9: ROE 2025A | F9: 20.6%
B10: Vốn hóa thị trường | C10: 3,535 tỷ VNĐ | E10: BVPS 2025A (VNĐ/CP) | F10: 22,893
B11: Giá cao 52 tuần | C11: 45,000 VNĐ | E11: Net Cash (tỷ VNĐ) | F11: 253
B12: Giá thấp 52 tuần | C12: 29,500 VNĐ | E12: Cổ tức (VNĐ/CP) | F12: 2,000
B13: Phân tích viên | C13: Chuyên gia DHC
B16: Lưu ý: Mô hình chỉ mang tính tham khảo, không phải khuyến nghị đầu tư chính thức.

Sheet 02_Giả định
B1: GIẢ ĐỊNH & THÔNG SỐ MÔ HÌNH
B2: Tham số | C2: 2024A | D2: 2025A | E2: 2026E | F2: 2027E | G2: Ghi chú
B3: A. DOANH THU — PHÂN MẢU VOLUME × GIÁ
B4: Sản lượng giấy cuộn (nghìn tấn) | C4: 305 | D4: 313 | E4: 320 | F4: 330 | G4: Giao Long 2 full công suất
B5: ASP giấy cuộn (triệu VNĐ/tấn) | C5: 10.37 | D5: 9.28 | E5: 10.4 | F5: 11 | G5: Kỳ vọng phục hồi giá giấy toàn cầu
B6: Doanh thu bao bì (tỷ VNĐ) | C6: 434 | D6: 726 | E6: 871 | F6: 1000 | G6: Tăng trưởng mảng bao bì carton
B7: B. BIÊN LỢI NHUẬN & CHI PHÍ
B8: Biên lợi nhuận gộp (%) | C8: 0.11843203 | D8: 0.16166345 | E8: 0.165 | F8: 0.17 | G8: Biên phục hồi nhờ giá giấy & hiệu quả SX
B9: Chi phí SGA / Doanh thu (%) | C9: 0.0457 | D9: 0.0343 | E9: 0.045 | F9: 0.043 | G9: Kiểm soát chi phí ổn định
B10: Khấu hao & phân bổ D&A (tỷ VNĐ) | C10: 105 | D10: 111 | E10: 115 | F10: 120 | G10: Tăng nhẹ theo CAPEX đầu tư
B11: Lãi tài chính thuần (tỷ VNĐ) | C11: 6 | D11: 33 | E11: 45 | F11: 50 | G11: Lãi tiền gửi & đầu tư TC ngắn hạn
B12: Thuế suất TNDN (%) | C12: 0.13261649 | D12: 0.14004376 | E12: 0.2 | F12: 0.2 | G12: Thuế suất chuẩn 20%
B13: C. ĐỊNH GIÁ — HỆ SỐ MỤC TIÊU
B14: Phương pháp | C14: Bear | D14: Base | E14: Bull
B15: P/E mục tiêu (lần) | C15: 7 | D15: 10 | E15: 13 | F15: 7 | G15: 10
B16: EV/EBITDA mục tiêu (lần) | C16: 6 | D16: 8 | E16: 10 | F16: 6 | G16: 8
B17: D. THÔNG SỐ DCF
B18: WACC (%) | E18: 0.12 | G18: = Chi phí vốn bình quân gia quyền
B19: Tốc độ tăng trưởng vĩnh viễn g (%) | E19: 0.03 | G19: = Dài hạn theo GDP danh nghĩa
B20: CAPEX 2026E (tỷ VNĐ) | E20: 350 | G20: Đầu tư Giao Long 3 phase 1
B21: CAPEX 2027E (tỷ VNĐ) | E21: 400 | G21: Tiếp tục đầu tư Giao Long 3
B22: Net Cash 2025A (tỷ VNĐ) | E22: 253 | G22: = 408+763-918 = 253 tỷ

Sheet 03_Doanh thu
B1: MÔ HÌNH DOANH THU — VOLUME × GIÁ BÁN
B2: Chỉ tiêu | C2: 2022A | D2: 2023A | E2: 2024A | F2: 2025A | G2: 2026E | H2: 2027E
B3: I. GIẤY CUỘN CÔNG NGHIỆP (Kraft Liner / Testliner / Fluting)
B4: Sản lượng (nghìn tấn) | C4: 297 | D4: 295 | E4: 305 | F4: 313 | G4: 320 | H4: 330
B5: ASP bình quân (triệu VNĐ/tấn) | C5: 11.42 | D5: 10.07 | E5: 10.37 | F5: 9.28 | G5: 10.4 | H5: 11
B6: Doanh thu giấy cuộn (tỷ VNĐ) | C6: 3392 | D6: 2971 | E6: 3163 | F6: 2905 | G6: =G4*G5 -> 3328 | H6: =H4*H5 -> 3630
B7: Tăng trưởng DT giấy cuộn (YoY%) | C7: - | D7: -0.12415162 | E7: 0.064699645 | F7: -0.081638396 | G7: =(G6-F6)/F6 -> 0.14561102 | H7: =(H6-G6)/G6 -> 0.090745192
B8: II. BAO BÌ CARTON
B9: Doanh thu bao bì (tỷ VNĐ) | C9: 340 | D9: 286 | E9: 434 | F9: 726 | G9: 871 | H9: 1000
B10: Tăng trưởng bao bì (YoY%) | C10: - | D10: -0.15882353 | E10: 0.51748252 | F10: 0.67281106 | G10: =(G9-F9)/F9 -> 0.19972452 | H10: =(H9-G9)/G9 -> 0.14810563
B11: III. TỔNG HỢP DOANH THU
B12: TỔNG DOANH THU (tỷ VNĐ) | C12: 3732 | D12: 3257 | E12: 3597 | F12: 3631 | G12: =G6+G9 -> 4199 | H12: =H6+H9 -> 4630
B13: Tăng trưởng DT tổng (YoY%) | C13: - | D13: -0.1272776 | E13: 0.10439054 | F13: 0.0094523214 | G13: =(G12-F12)/F12 -> 0.15643074 | H13: =(H12-G12)/G12 -> 0.10264349
B14: Tỷ trọng bao bì / Tổng DT (%) | C14: 0.091103966 | D14: 0.087810869 | E14: 0.1206561 | F14: 0.19994492 | G14: =G9/G12 -> 0.20743034 | H14: =H9/H12 -> 0.21598272

Sheet 04_KQKD
B1: KẾT QUẢ KINH DOANH (Tỷ VNĐ) — 2021–2027E
B2: Chỉ tiêu | C2: 2021A | D2: 2022A | E2: 2023A | F2: 2024A | G2: 2025A | H2: 2026E | I2: 2027E
B3: Doanh thu thuần (tỷ VNĐ) | C3: 4164 | D3: 3935 | E3: 3259 | F3: 3597 | G3: 3631 | H3: ='03_Doanh thu'!G12 -> 4199 | I3: ='03_Doanh thu'!H12 -> 4630
B4: Giá vốn hàng bán (COGS) | C4: 3492 | D4: 3324 | E4: 2755 | F4: 3170 | G4: 3044 | H4: =H3*(1-'02_Giả định'!E8) -> 3506.165 | I4: =I3*(1-'02_Giả định'!F8) -> 3842.9
B5: Lợi nhuận gộp | C5: 672 | D5: 611 | E5: 504 | F5: 426 | G5: 587 | H5: =H3-H4 -> 692.835 | I5: =I3-I4 -> 787.1
B6: Biên lợi nhuận gộp (%) | C6: 0.16138329 | D6: 0.15527319 | E6: 0.15464867 | F6: 0.11843203 | G6: 0.16166345 | H6: =H5/H3 -> 0.165 | I6: =I5/I3 -> 0.17
B7: Chi phí bán hàng & quản lý (SGA) | C7: 161 | D7: 158 | E7: 146 | F7: 153 | G7: 163 | H7: =H3*'02_Giả định'!E9 -> 188.955 | I7: =I3*'02_Giả định'!F9 -> 199.09
B8: EBIT | C8: 511 | D8: 453 | E8: 358 | F8: 274 | G8: 424 | H8: =H5-H7 -> 503.88 | I8: =I5-I7 -> 588.01
B9: Biên EBIT (%) | C9: 0.12271854 | D9: 0.11512071 | E9: 0.10984965 | F9: 0.07617459 | G9: 0.11677224 | H9: =H8/H3 -> 0.12 | I9: =I8/I3 -> 0.127
B10: Khấu hao & phân bổ (D&A) | C10: 103 | D10: 101 | E10: 102 | F10: 105 | G10: 111 | H10: ='02_Giả định'!E10 -> 115 | I10: ='02_Giả định'!F10 -> 120
B11: EBITDA | C11: 613 | D11: 554 | E11: 460 | F11: 379 | G11: 535 | H11: =H8+H10 -> 618.88 | I11: =I8+I10 -> 708.01
B12: Biên EBITDA (%) | C12: 0.14721422 | D12: 0.1407878 | E12: 0.14114759 | F12: 0.10536558 | G12: 0.14734233 | H12: =H11/H3 -> 0.14738747 | I12: =I11/I3 -> 0.15291793
B13: Lãi/(lỗ) tài chính thuần | C13: 1 | D13: -16 | E13: 0 | F13: 6 | G13: 33 | H13: ='02_Giả định'!E11 -> 45 | I13: ='02_Giả định'!F11 -> 50
B14: Lợi nhuận trước thuế (LNTT) | C14: 512 | D14: 437 | E14: 358 | F14: 279 | G14: 457 | H14: =H8+H13 -> 548.88 | I14: =I8+I13 -> 638.01
B15: Thuế TNDN | C15: 31 | D15: 57 | E15: 48 | F15: 37 | G15: 64 | H15: =H14*'02_Giả định'!E12 -> 109.776 | I15: =I14*'02_Giả định'!F12 -> 127.602
B16: LNST (cổ đông CTM) | C16: 481 | D16: 379 | E16: 309 | F16: 242 | G16: 393 | H16: =H14-H15 -> 439.104 | I16: =I14-I15 -> 510.408
B17: Biên lợi nhuận ròng (%) | C17: 0.11551393 | D17: 0.096315121 | E17: 0.09481436 | F17: 0.067278287 | G17: 0.10823465 | H17: =H16/H3 -> 0.10457347 | I17: =I16/I3 -> 0.11023931
B18: Tăng trưởng LNST (YoY%) | C18: - | D18: -0.21205821 | E18: -0.18469657 | F18: -0.21682848 | G18: 0.62396694 | H18: =(H16-G16)/G16 -> 0.11731298 | I18: =(I16-H16)/H16 -> 0.16238522
B19: Số CP lưu hành (triệu) | C19: 96.59 | D19: 96.59 | E19: 96.59 | F19: 96.59 | G19: 96.59 | H19: 96.59 | I19: 96.59
B20: EPS (VNĐ/CP) | C20: 4884 | D20: 3850 | E20: 3107 | F20: 2460 | G20: 3988 | H20: =H16/H19*1000 -> 4546.0607 | I20: =I16/I19*1000 -> 5284.2737

Sheet 05_CĐKT
B1: BẢNG CÂN ĐỐI KẾ TOÁN (Tỷ VNĐ)
B2: Chỉ tiêu | C2: 2023A | D2: 2024A | E2: 2025A | F2: 2026E | G2: 2027E
B3: A. TÀI SẢN NGẮN HẠN
B4: Tiền & tương đương tiền | C4: 247 | D4: 571 | E4: 408 | F4: =E4*1.05 -> 428.4 | G4: =F4*1.05 -> 449.82
B5: Đầu tư tài chính ngắn hạn | C5: 101 | D5: 337 | E5: 763 | F5: =E5*1.05 -> 801.15 | G5: =F5*1.05 -> 841.2075
B6: Phải thu khách hàng (AR) | C6: 626 | D6: 696 | E6: 751 | F6: =E6*1.05 -> 788.55 | G6: =F6*1.05 -> 827.9775
B7: Hàng tồn kho | C7: 504 | D7: 524 | E7: 492 | F7: =E7*1.05 -> 516.6 | G7: =F7*1.05 -> 542.43
B8: Tài sản ngắn hạn khác | C8: 100 | D8: 113 | E8: 165 | F8: =E8*1.05 -> 173.25 | G8: =F8*1.05 -> 181.9125
B9: TỔNG TÀI SẢN NGẮN HẠN | C9: 1578 | D9: 2241 | E9: 2579 | F9: =SUM(F4:F8) -> 2707.95 | G9: =SUM(G4:G8) -> 2843.3475
B10: B. TÀI SẢN DÀI HẠN
B11: Tài sản cố định (PPE thuần) | C11: 1087 | D11: 1010 | E11: 993 | F11: =E11+'02_Giả định'!E20-'02_Giả định'!E10 -> 1228 | G11: =F11+'02_Giả định'!E21-'02_Giả định'!F10 -> 1508
B12: Tài sản dài hạn khác | C12: 250 | D12: -6 | E12: 7 | F12: =E12 -> 7 | G12: =F12 -> 7
B13: TỔNG TÀI SẢN | C13: 2915 | D13: 3245 | E13: 3579 | F13: =F9+F11+F12 -> 3942.95 | G13: =G9+G11+G12 -> 4358.3475
B14: C. NỢ PHẢI TRẢ
B15: Vay & nợ thuê tài chính ngắn hạn | C15: 702 | D15: 761 | E15: 918 | F15: =E15*1.03 -> 945.54 | G15: =F15*1.03 -> 973.9062
B16: Phải trả người bán & PTNB ngắn hạn | C16: 361 | D16: 481 | E16: 450 | F16: =E16*1.03 -> 463.5 | G16: =F16*1.03 -> 477.405
B17: Nợ ngắn hạn khác | C17: 0 | D17: 0 | E17: 0 | F17: =0 -> 0 | G17: =0 -> 0
B18: TỔNG NỢ PHẢI TRẢ | C18: 1063 | D18: 1242 | E18: 1368 | F18: =SUM(F15:F17) -> 1409.04 | G18: =SUM(G15:G17) -> 1451.3112
B19: D. VỐN CHỦ SỞ HỮU
B20: Vốn cổ phần | C20: 966 | D20: 966 | E20: 966 | F20: =E20 -> 966 | G20: =F20 -> 966
B21: Lợi nhuận giữ lại & thặng dư | C21: 883 | D21: 1035 | E21: 1245 | F21: =E21+'04_KQKD'!H16 -> 1684.104 | G21: =F21+'04_KQKD'!I16 -> 2194.512
B22: VCSH (cổ đông CTM) | C22: 1849 | D22: 2001 | E22: 2211 | F22: =F20+F21 -> 2650.104 | G22: =G20+G21 -> 3160.512
B23: E. CHỈ TIÊU BỔ SUNG
B24: Net Cash = Tiền + ĐTTC NH - Vay NH | C24: -354 | D24: 147 | E24: 253 | F24: =F4+F5-F15 -> 284.01 | G24: =G4+G5-G15 -> 317.1213
B25: BVPS (VNĐ/CP) | C25: 19143 | D25: 20716 | E25: 22891 | F25: =F22/96.59*1000 -> 27436.629 | G25: =G22/96.59*1000 -> 32720.903

Sheet 06_LCTT
B1: LƯU CHUYỂN TIỀN TỆ (Tỷ VNĐ)
B2: Chỉ tiêu | C2: 2023A | D2: 2024A | E2: 2025A | F2: 2026E | G2: 2027E
B3: A. HOẠT ĐỘNG KINH DOANH (CFO)
B4: LNST | C4: 309 | D4: 242 | E4: 393 | F4: ='04_KQKD'!H16 -> 439.104 | G4: ='04_KQKD'!I16 -> 510.408
B5: Điều chỉnh D&A | C5: 102 | D5: 105 | E5: 111 | F5: ='04_KQKD'!H10 -> 115 | G5: ='04_KQKD'!I10 -> 120
B6: Thay đổi vốn lưu động & khác | C6: -170 | D6: 309 | E6: -39 | F6: =-50 -> -50 | G6: =-60 -> -60
B7: CFO (Lưu chuyển tiền thuần HĐKD) | C7: 241 | D7: 656 | E7: 465 | F7: =SUM(F4:F6) -> 504.104 | G7: =SUM(G4:G6) -> 570.408
B8: B. HOẠT ĐỘNG ĐẦU TƯ (CFI)
B9: CAPEX (đầu tư TSCĐ) | C9: -88 | D9: -71 | E9: -183 | F9: =-'02_Giả định'!E20 -> -350 | G9: =-'02_Giả định'!E21 -> -400
B10: CFI (Lưu chuyển tiền HĐĐT) | C10: -88 | D10: -71 | E10: -183 | F10: =F9 -> -350 | G10: =G9 -> -400
B11: C. HOẠT ĐỘNG TÀI CHÍNH (CFF)
B12: Vay ròng (phát hành - trả nợ) | C12: 0 | D12: 0 | E12: 0 | F12: =50 -> 50 | G12: =50 -> 50
B13: Cổ tức đã trả | C13: -193 | D13: -193 | E13: -193 | F13: =-193 -> -193 | G13: =-193 -> -193
B14: CFF (Lưu chuyển tiền HĐTC) | C14: -193 | D14: -193 | E14: -193 | F14: =F12+F13 -> -143 | G14: =G12+G13 -> -143
B15: D. TỔNG HỢP & FCF
B16: THAY ĐỔI TIỀN THUẦN | C16: -40 | D16: 392 | E16: 89 | F16: =F7+F10+F14 -> 11.104 | G16: =G7+G10+G14 -> 27.408
B17: FCF = CFO - CAPEX | C17: 153 | D17: 586 | E17: 282 | F17: =F7+F9 -> 154.104 | G17: =G7+G9 -> 170.408
B18: FCF trên mỗi cổ phiếu (VNĐ/CP) | C18: 1584 | D18: 6067 | E18: 2920 | F18: =F17/96.59*1000 -> 1595.4447 | G18: =G17/96.59*1000 -> 1764.2406

Sheet 07_Định giá
B1: ĐỊNH GIÁ CỔ PHIẾU DHC
B2: THÔNG SỐ ĐẦU VÀO
B3: Giá thị trường hiện tại (VNĐ/CP) | C3: 36600
B4: Net Cash 2025A (tỷ VNĐ) | C4: ='02_Giả định'!E22 -> 253
B5: Số cổ phiếu lưu hành (triệu CP) | C5: 96.59
B6: PHƯƠNG PHÁP 1: P/E FORWARD
B7: Chỉ tiêu | C7: Bear | D7: Base | E7: Bull
B8: P/E mục tiêu (lần) | C8: ='02_Giả định'!C15 -> 7 | D8: ='02_Giả định'!D15 -> 10 | E8: ='02_Giả định'!E15 -> 13
B9: EPS 2026E (VNĐ/CP) | C9: ='04_KQKD'!H20 -> 4546.0607 | D9: ='04_KQKD'!H20 -> 4546.0607 | E9: ='04_KQKD'!H20 -> 4546.0607
B10: Giá mục tiêu P/E (VNĐ/CP) | C10: =C8*C9 -> 31822.425 | D10: =D8*D9 -> 45460.607 | E10: =E8*E9 -> 59098.789
B11: PHƯƠNG PHÁP 2: EV/EBITDA FORWARD
B12: Chỉ tiêu | C12: Bear | D12: Base | E12: Bull
B13: EV/EBITDA mục tiêu (lần) | C13: ='02_Giả định'!C16 -> 6 | D13: ='02_Giả định'!D16 -> 8 | E13: ='02_Giả định'!E16 -> 10
B14: EBITDA 2026E (tỷ VNĐ) | C14: ='04_KQKD'!H11 -> 618.88 | D14: ='04_KQKD'!H11 -> 618.88 | E14: ='04_KQKD'!H11 -> 618.88
B15: EV mục tiêu (tỷ VNĐ) | C15: =C13*C14 -> 3713.28 | D15: =D13*D14 -> 4951.04 | E15: =E13*E14 -> 6188.8
B16: Equity Value = EV + Net Cash (tỷ VNĐ) | C16: =C15+C4 -> 3966.28 | D16: =D15+D4 -> 4951.04 | E16: =E15+E4 -> 6188.8
B17: Giá mục tiêu EV/EBITDA (VNĐ/CP) | C17: =C16/$C$5*1000 -> 41063.05 | D17: =D16/$C$5*1000 -> 51258.308 | E17: =E16/$C$5*1000 -> 64072.885
B18: TỔNG HỢP BLENDED (P/E 50% + EV/EBITDA 50%)
B19: Chỉ tiêu | C19: Bear | D19: Base | E19: Bull
B20: Giá blended (VNĐ/CP) | C20: =(C10+C17)/2 -> 36442.737 | D20: =(D10+D17)/2 -> 48359.458 | E20: =(E10+E17)/2 -> 61585.837
B21: Upside / (Downside) vs giá hiện tại | C21: =(C20-$C$3)/$C$3 -> -0.0042967939 | D21: =(D20-$C$3)/$C$3 -> 0.32129665 | E21: =(E20-$C$3)/$C$3 -> 0.68267314
B22: KHUYẾN NGHỊ | C22: TRÁNH / CHỜ | D22: MUA / TÍCH LŨY | E22: MUA MẠNH

Sheet 08_DCF
B1: PHÂN TÍCH DCF — DÒNG TIỀN CHIẾT KHẤU
B2: THÔNG SỐ DCF
B3: WACC (%) | C3: ='02_Giả định'!E18 -> 0.12
B4: Tốc độ tăng trưởng vĩnh viễn g (%) | C4: ='02_Giả định'!E19 -> 0.03
B5: Net Cash (tỷ VNĐ) | C5: ='02_Giả định'!E22 -> 253
B6: DỰ BÁO FCFF 2026E–2030E
B7: Chỉ tiêu | C7: 2026E | D7: 2027E | E7: 2028E | F7: 2029E | G7: 2030E
B8: EBIT (tỷ VNĐ) | C8: ='04_KQKD'!H8 -> 503.88 | D8: ='04_KQKD'!I8 -> 588.01 | E8: =D8*1.06 -> 623.2906 | F8: =E8*1.06 -> 660.68804 | G8: =F8*1.06 -> 700.32932
B9: NOPAT = EBIT×(1−20%) | C9: =C8*0.8 -> 403.104 | D9: =D8*0.8 -> 470.408 | E9: =E8*0.8 -> 498.63248 | F9: =F8*0.8 -> 528.55043 | G9: =G8*0.8 -> 560.26345
B10: (+) D&A (tỷ VNĐ) | C10: ='04_KQKD'!H10 -> 115 | D10: ='04_KQKD'!I10 -> 120 | E10: 125 | F10: 130 | G10: 135
B11: (−) CAPEX (tỷ VNĐ) | C11: ='02_Giả định'!E20 -> 350 | D11: ='02_Giả định'!E21 -> 400 | E11: 200 | F11: 200 | G11: 200
B12: (−) Thay đổi NWC (tỷ VNĐ) | C12: 50 | D12: 50 | E12: 50 | F12: 50 | G12: 50
B13: FCFF (tỷ VNĐ) | C13: =C9+C10-C11-C12 -> 118.104 | D13: =D9+D10-D11-D12 -> 140.408 | E13: =E9+E10-E11-E12 -> 373.63248 | F13: =F9+F10-F11-F12 -> 408.55043 | G13: =G9+G10-G11-G12 -> 445.26345
B14: Hệ số chiết khấu | C14: =1/(1+$C$3)^1 -> 0.89285714 | D14: =1/(1+$C$3)^2 -> 0.79719388 | E14: =1/(1+$C$3)^3 -> 0.71178025 | F14: =1/(1+$C$3)^4 -> 0.63551808 | G14: =1/(1+$C$3)^5 -> 0.56742686
B15: PV(FCFF) (tỷ VNĐ) | C15: =C13*C14 -> 105.45 | D15: =D13*D14 -> 111.9324 | E15: =E13*E14 -> 265.94422 | F15: =F13*F14 -> 259.64118 | G15: =G13*G14 -> 252.65444
B16: TÍNH TOÁN GIÁ TRỊ
B17: Tổng PV(FCFF) 2026–2030 (tỷ VNĐ) | C17: =SUM(C15:G15) -> 995.62224
B18: Terminal Value (tỷ VNĐ) | C18: =G13*(1+C4)/(C3-C4) -> 5095.7929
B19: PV(Terminal Value) (tỷ VNĐ) | C19: =C18/(1+C3)^5 -> 2891.4897
B20: Enterprise Value (tỷ VNĐ) | C20: =C17+C19 -> 3887.112
B21: (+) Net Cash (tỷ VNĐ) | C21: =C5 -> 253
B22: Equity Value (tỷ VNĐ) | C22: =C20+C21 -> 4140.112
B23: Giá trị nội tại DCF/CP (VNĐ/CP) | C23: =C22/96.59*1000 -> 42862.739

Sheet 09_Nhạy cảm
B1: PHÂN TÍCH ĐỘ NHẠY
B2: BẢNG 1: ĐỊNH GIÁ THEO P/E × EPS 2026E
B3: P/E \ EPS (VNĐ) | C3: 3400 | D3: 3700 | E3: 4000 | F3: 4300 | G3: 4600 | H3: 4900
B4: 7x | C4: 23800 | D4: 25900 | E4: 28000 | F4: 30100 | G4: 32200 | H4: 34300
B5: 8x | C5: 27200 | D5: 29600 | E5: 32000 | F5: 34400 | G5: 36800 | H5: 39200
B6: 9x | C6: 30600 | D6: 33300 | E6: 36000 | F6: 38700 | G6: 41400 | H6: 44100
B7: 10x | C7: 34000 | D7: 37000 | E7: 40000 | F7: 43000 | G7: 46000 | H7: 49000
B8: 11x | C8: 37400 | D8: 40700 | E8: 44000 | F8: 47300 | G8: 50600 | H8: 53900
B9: 12x | C9: 40800 | D9: 44400 | E9: 48000 | F9: 51600 | G9: 55200 | H9: 58800
B11: BẢNG 2: ĐỊNH GIÁ THEO EV/EBITDA × EBITDA 2026E
B12: EV/EBITDA \ EBITDA (tỷ) | C12: 550 | D12: 580 | E12: 610 | F12: 640 | G12: 670 | H12: 700 | I12: 730
B13: 5x | C13: 31090 | D13: 32643 | E13: 34196 | F13: 35749 | G13: 37302 | H13: 38855 | I13: 40408
B14: 6x | C14: 36784 | D14: 38648 | E14: 40511 | F14: 42375 | G14: 44239 | H14: 46102 | I14: 47966
B15: 7x | C15: 42479 | D15: 44653 | E15: 46827 | F15: 49001 | G15: 51175 | H15: 53349 | I15: 55523
B16: 8x | C16: 48173 | D16: 50657 | E16: 53142 | F16: 55627 | G16: 58112 | H16: 60596 | I16: 63081
B17: 9x | C17: 53867 | D17: 56662 | E17: 59458 | F17: 62253 | G17: 65048 | H17: 67843 | I17: 70639
B18: 10x | C18: 59561 | D18: 62667 | E18: 65773 | F18: 68879 | G18: 71985 | H18: 75091 | I18: 78197

Sheet 10_Peers
B1: SO SÁNH CÔNG TY CÙNG NGÀNH
B2: Công ty | C2: Sàn | D2: Vốn hóa (tỷ) | E2: P/E | F2: EV/EBITDA | G2: Biên GP (%) | H2: ROE (%) | I2: Ghi chú
B3: DHC — Đông Hải BT | C3: HOSE | D3: 3535 | E3: 8.3 | F3: 5.2 | G3: 16.2% | H3: 20.6% | I3: Tiêu điểm phân tích
B4: SVI | C4: HOSE | D4: 1850 | E4: 10.5 | F4: 6.8 | G4: 14.5% | H4: 15.2% | I4: Bao bì sóng, cạnh tranh trực tiếp
B5: Saigon Paper (SAP) | C5: HOSE | D5: 950 | E5: 12 | F5: 7.5 | G5: 12.8% | H5: 11.5% | I5: Giấy tissue & offset
B6: SCG Packaging | C6: SET | D6: 18000 | E6: 14 | F6: 9.2 | G6: 18.5% | H6: 16.8% | I6: Tập đoàn bao bì Thái Lan
B7: Smurfit WestRock | C7: NYSE | D7: 250000 | E7: 15 | F7: 10.5 | G7: 20.0% | H7: 18.5% | I7: Global leader giấy bao bì
B8: Rengo Co. | C8: TSE | D8: 35000 | E8: 12.5 | F8: 8 | G8: 17.5% | H8: 14.0% | I8: Nhật Bản — tương đồng model
B9: Trung bình peers VN | C9: — | D9: 1400 | E9: 11.3 | F9: 7.2 | G9: 13.7% | H9: 13.4% | I9: Bình quân đơn giản DHC/SVI/SAP
B10: Định giá DHC vs peers: P/E & EV/EBITDA thấp hơn trung bình ngành → Còn dư địa nâng hệ số định giá

Sheet 11_PESTLE
B1: PHÂN TÍCH PESTLE — BỐI CẢNH VĨ MÔ
B2: Nhân tố | C2: Tích cực / Cơ hội | D2: Rủi ro / Thách thức | E2: Đánh giá net
B3: Chính trị (Political) | C3: Việt Nam ổn định chính trị; chính sách ủng hộ công nghiệp hóa, khu công nghiệp phát triển mạnh | D3: Căng thẳng thương mại Mỹ-Trung; rủi ro thuế quan với hàng XK sang Mỹ | E3: TÍCH CỰC
B4: Kinh tế (Economic) | C4: GDP VN tăng 6–7%/năm; TMĐT tăng trưởng 25%+/năm thúc đẩy nhu cầu bao bì | D4: Lạm phát chi phí giấy OCC; biến động tỷ giá ảnh hưởng nhập khẩu nguyên liệu | E4: TÍCH CỰC
B5: Xã hội (Social) | C5: Xu hướng tiêu dùng online bùng nổ; dân số trung lưu tăng → nhu cầu đóng gói cao | D5: Áp lực chuyển đổi xanh; người tiêu dùng kỳ vọng bao bì thân thiện môi trường | E5: TRUNG LẬP
B6: Công nghệ (Technology) | C6: Tự động hóa sản xuất nâng cao năng suất; Giao Long 3 ứng dụng công nghệ mới | D6: Đầu tư CAPEX lớn cho R&D; rủi ro lỗi thời máy móc nếu không đổi mới kịp | E6: TÍCH CỰC
B7: Pháp lý (Legal) | C7: EPR 2025 → cơ hội mở rộng mảng tái chế; quy định bao bì tạo rào cản gia nhập ngành | D7: Chi phí tuân thủ EPR tăng; yêu cầu tái chế ≥50% có thể ảnh hưởng biên lợi nhuận | E7: TRUNG LẬP
B8: Môi trường (Environment) | C8: DHC dùng giấy tái chế OCC → lợi thế xanh; chứng chỉ FSC/ISO nâng cao uy tín | D8: Biến đổi khí hậu; quy định phát thải CO₂ ngày càng chặt chẽ hơn | E8: TRUNG LẬP
B9: NET PESTLE | C9: 4/6 nhân tố Tích cực; Kinh tế & Công nghệ là 2 động lực chính | D9: Rủi ro kiểm soát được; chủ yếu từ thuế quan & chi phí nguyên liệu | E9: TÍCH CỰC

Sheet 12_Chỉ số
B1: CÁC CHỈ SỐ TÀI CHÍNH
B2: Chỉ số | C2: 2021A | D2: 2022A | E2: 2023A | F2: 2024A | G2: 2025A | H2: 2026E
B3: A. CHỈ SỐ TĂNG TRƯỞNG (YoY%)
B4: Tăng trưởng DT | C4: — | D4: -0.054995197 | E4: -0.17179161 | F4: 0.1037128 | G4: 0.0094523214 | H4: =('04_KQKD'!H16-'04_KQKD'!G16)/'04_KQKD'!G16 -> 0.11731298
B5: Tăng trưởng GP | C5: — | D5: -0.09077381 | E5: -0.17512275 | F5: -0.1547619 | G5: 0.37793427 | H5: =('04_KQKD'!H17-'04_KQKD'!G17)/'04_KQKD'!G17 -> -0.033826287
B6: Tăng trưởng EBITDA | C6: — | D6: -0.096247961 | E6: -0.16967509 | F6: -0.17608696 | G6: 0.4116095 | H6: =('04_KQKD'!H18-'04_KQKD'!G18)/'04_KQKD'!G18 -> -0.81198847
B7: Tăng trưởng LNST | C7: — | D7: -0.21205821 | E7: -0.18469657 | F7: -0.21682848 | G7: 0.62396694 | H7: =('04_KQKD'!H19-'04_KQKD'!G19)/'04_KQKD'!G19 -> 0
B8: B. CHỈ SỐ SINH LỜI (%)
B9: Biên lợi nhuận gộp | C9: 0.16138329 | D9: 0.15527319 | E9: 0.15464867 | F9: 0.11843203 | G9: 0.16166345 | H9: ='04_KQKD'!H6 -> 0.165
B10: Biên EBITDA | C10: 0.14721422 | D10: 0.1407878 | E10: 0.14114759 | F10: 0.10536558 | G10: 0.14734233 | H10: ='04_KQKD'!H12 -> 0.14738747
B11: Biên lợi nhuận ròng | C11: 0.11551393 | D11: 0.096315121 | E11: 0.09481436 | F11: 0.067278287 | G11: 0.10823465 | H11: ='04_KQKD'!H17 -> 0.10457347
B12: ROE (%) | C12: 0.300625 | D12: 0.22294118 | E12: 0.16711736 | F12: 0.12093953 | G12: 0.17774763 | H12: ='04_KQKD'!H16/'05_CĐKT'!E22 -> 0.19859973
B13: ROIC (%) | C13: 0.19202422 | D13: 0.15756522 | E13: 0.10634648 | F13: 0.073239779 | G13: 0.10187802 | H13: ='04_KQKD'!H8*(1-'02_Giả định'!E12)/'05_CĐKT'!F13 -> 0.10223411
B14: C. ĐÒN BẨY TÀI CHÍNH
B15: D/E (Tổng nợ / VCSH) | C15: — | D15: — | E15: 0.57490535 | F15: 0.62068966 | G15: 0.61872456 | H15: ='05_CĐKT'!F18/'05_CĐKT'!F22 -> 0.53169234
B16: Net Debt/EBITDA | C16: — | D16: — | E16: 0.76956522 | F16: -0.3878628 | G16: -0.4728972 | H16: =('05_CĐKT'!F15-'05_CĐKT'!F4-'05_CĐKT'!F5)/'04_KQKD'!H11 -> -0.45890964
B17: D. THANH KHOẢN
B18: Current Ratio (TSngắn hạn / Nợ NH) | C18: — | D18: — | E18: 1.4844779 | F18: 1.8043478 | G18: 1.8852339 | H18: ='05_CĐKT'!F9/'05_CĐKT'!F18 -> 1.9218404
B19: Quick Ratio ((Tiền+ĐTTC+AR) / Nợ NH) | C19: — | D19: — | E19: 0.91627469 | F19: 1.2914654 | G19: 1.4049708 | H19: =('05_CĐKT'!F4+'05_CĐKT'!F5+'05_CĐKT'!F6)/'05_CĐKT'!F18 -> 1.4322517
B20: E. CHỈ SỐ ĐỊNH GIÁ (dùng giá 36,600 VNĐ)
B21: P/E trailing | C21: 7.4938575 | D21: 9.5064935 | E21: 11.779852 | F21: 14.878049 | G21: 9.1775326 | H21: =C3/'04_KQKD'!H20 -> 0
B22: P/B (Price/Book Value) | C22: 1.9639967 | D22: 1.9639967 | E22: 1.9119492 | F22: 1.7667136 | G22: 1.5989118 | H22: =36600/'05_CĐKT'!F25 -> 1.3339831
B23: EV/EBITDA | C23: 5.7670375 | D23: 6.3812166 | E23: 8.4547696 | F23: 8.9398259 | G23: 6.1349421 | H23: =(C3*96.59/1000-'05_CĐKT'!F24)/'04_KQKD'!H11 -> -0.45890964
B24: Dividend Yield (%) | C24: 0.054644809 | D24: 0.054644809 | E24: 0.054644809 | F24: 0.054644809 | G24: 0.054644809 | H24: 0.054644809

Sheet 13_Theo dõi
B1: THEO DÕI ĐẦU TƯ — DHC (CÁC YẾU TỐ CẦN CẬP NHẬT ĐỊNH KỲ)
B2: Màu ngưỡng: 🟢 Tốt = giữ thesis | 🟡 Trung lập = theo dõi sát | 🔴 Xấu = xem xét lại khuyến nghị
B4: A. CHỈ SỐ VĨ MÔ & NGÀNH
B5: Chỉ số / Yếu tố | C5: Giá trị hiện tại | D5: Ngưỡng tốt 🟢 | E5: Ngưỡng trung lập 🟡 | F5: Ngưỡng xấu 🔴 | G5: Ý nghĩa / Hành động | H5: Tần suất
B6: Giá giấy OCC (USD/tấn) | C6: ~120–140 | D6: ≥ 120 & ≤ 140 | E6: 100–120 hoặc 140–160 | F6: < 100 hoặc > 160 | G6: Chi phí nguyên liệu chính (~60% COGS) | H6: Hàng tháng
B7: ASP giấy cuộn VN (tr VNĐ/tấn) | C7: ~9.3 | D7: ≥ 10.0 | E7: 9.0–10.0 | F7: < 9.0 | G7: Doanh thu giảm nếu ASP xuống dưới 9.0 | H7: Hàng quý
B8: XNK hàng hóa VN (tỷ USD) | C8: ~380 | D8: ≥ 380 | E8: 350–380 | F8: < 350 | G8: Nhu cầu bao bì xuất khẩu | H8: Hàng tháng
B9: GDP Việt Nam (YoY%) | C9: ~6.5% | D9: ≥ 6.5% | E9: 5.0–6.5% | F9: < 5.0% | G9: Tiêu dùng nội địa & TMĐT giảm | H9: Hàng quý
B10: Tỷ giá USD/VNĐ | C10: ~25,500 | D10: 23,000–26,000 | E10: 26,000–27,000 | F10: > 27,000 | G10: Chi phí NK máy móc, nguyên liệu tăng | H10: Hàng ngày
B12: B. BCTC DOANH NGHIỆP (cập nhật sau mỗi quý)
B13: Chỉ số / Yếu tố | C13: Giá trị hiện tại | D13: Ngưỡng tốt 🟢 | E13: Ngưỡng trung lập 🟡 | F13: Ngưỡng xấu 🔴 | G13: Ý nghĩa / Hành động | H13: Tần suất
B14: Doanh thu YoY% | C14: [quý gần nhất] | D14: > +10% | E14: 0% → +10% | F14: < 0% | G14: Tín hiệu tăng trưởng volume + giá | H14: Hàng quý
B15: LNST YoY% | C15: [quý gần nhất] | D15: > +15% | E15: 0% → +15% | F15: < 0% | G15: Sức khỏe lợi nhuận cốt lõi | H15: Hàng quý
B16: Biên lợi nhuận gộp (%) | C16: ~16% | D16: > 15% | E16: 12–15% | F16: < 12% | G16: Kiểm soát COGS & định giá đầu ra | H16: Hàng quý
B17: Net Debt/EBITDA | C17: ~1.3x | D17: < 1.0x | E17: 1.0–2.0x | F17: > 2.0x | G17: Rủi ro đòn bẩy tài chính | H17: Hàng quý
B18: Doanh thu mảng bao bì (tỷ) | C18: ~726 | D18: ≥ 726 | E18: 600–726 | F18: < 600 | G18: Động lực tăng trưởng chính 2026 | H18: Hàng quý
B19: CAPEX thực tế (tỷ/năm) | C19: [năm hiện tại] | D19: < 400 | E19: 400–500 | F19: > 500 | G19: Giao Long 3 — rủi ro overrun vốn | H19: Hàng năm
B21: C. CATALYST THEO DÕI
B22: Sự kiện / Catalyst | C22: Thời điểm | D22: Xác suất | E22: Tác động | F22: Loại | G22: Ghi chú
B23: Giao Long 3 phase 1 khởi công | C23: Q2/2028 | D23: Trung bình | E23: Nâng công suất 50% | F23: Tích cực | G23: Catalyst dài hạn lớn nhất
B24: KQKD Q2/2026 công bố | C24: T8/2026 | D24: Cao | E24: Xác nhận luận điểm đầu tư | F24: Tích cực | G24: Theo dõi biên GP & tăng trưởng bao bì
B25: Chi trả cổ tức 2025 (2,000 VNĐ) | C25: Q3/2026 | D25: Cao | E25: Yield 5.5% tại giá 36,600 | F25: Tích cực | G25: Đã được ĐHCĐ thông qua
B26: Diễn biến thuế quan Mỹ (tariff) | C26: 2026–2027 | D26: Trung bình | E26: Giảm XK → cầu bao bì giảm | F26: Tiêu cực | G26: Rủi ro gián tiếp qua khách hàng xuất khẩu
B27: EPR 2025 triển khai | C27: 2026 | D27: Trung bình | E27: Chi phí tuân thủ tăng; rào cản gia nhập tốt | F27: Trung lập | G27: Tác động hai chiều
B29: D. ĐIỀU KIỆN ĐÁNH GIÁ LẠI KHUYẾN NGHỊ
B30: HẠ XUỐNG TRUNG LẬP / BÁN NẾU:
B31: • LNST 2 quý liên tiếp thấp hơn kịch bản Bear > 20%
B32: • Biên LN gộp giảm dưới 12% và duy trì > 2 quý
B33: • ASP giấy cuộn xuống dưới 9.0 tr/tấn và giá OCC > 160 USD/tấn đồng thời
B34: • CAPEX Giao Long 3 vượt 600 tỷ/năm (overrun > 20% kế hoạch)
B35: • Catalyst chính (Giao Long 3) bị hoãn hơn 12 tháng so với kế hoạch
B37: NÂNG LÊN MUA MẠNH NẾU:
B38: • LNST 2026E vượt kịch bản Bull (>500 tỷ) nhờ ASP phục hồi + bao bì tăng mạnh
B39: • Biên LN gộp duy trì trên 17% trong 2 quý liên tiếp
B40: • Doanh thu bao bì đạt > 1,000 tỷ trước Q4/2026
B41: • Thông báo Giao Long 3 khởi công sớm hơn kế hoạch > 6 tháng
B42: • Giá CP giảm về vùng 28,000–30,000 VNĐ (P/E < 8x trailing)
