Workbook

Sheet 00_Beta
A1: BẢNG TÍNH HỆ SỐ BETA LỊCH SỬ | B1: Beta thô (raw): | C1: =COVAR(C6:C505, E6:E505)/VAR(E6:E505) | D1: Beta Blume (đã điều chỉnh): | E1: =0.67*C1+0.33
B2: Số phiên giao dịch: | C2: =COUNT(C6:C505)
A4: Ngày | B4: Giá VPB | C4: Tỷ suất sinh lời VPB | D4: Giá VNINDEX | E4: Tỷ suất sinh lời VNINDEX
A5: 2024-08-30 | B5: 18125 | D5: 1283.87
A6: 2024-09-04 | B6: 17695 | C6: =(B6-B5)/B5 | D6: 1275.8 | E6: =(D6-D5)/D5
A7: 2024-09-05 | B7: 17503 | C7: =(B7-B6)/B6 | D7: 1268.21 | E7: =(D7-D6)/D6
A8: 2024-09-06 | B8: 17647 | C8: =(B8-B7)/B7 | D8: 1273.96 | E8: =(D8-D7)/D7
A9: 2024-09-09 | B9: 17551 | C9: =(B9-B8)/B8 | D9: 1267.73 | E9: =(D9-D8)/D8
A10: 2024-09-10 | B10: 17360 | C10: =(B10-B9)/B9 | D10: 1255.23 | E10: =(D10-D9)/D9
A11: 2024-09-11 | B11: 17455 | C11: =(B11-B10)/B10 | D11: 1253.27 | E11: =(D11-D10)/D10
A12: 2024-09-12 | B12: 17695 | C12: =(B12-B11)/B11 | D12: 1256.35 | E12: =(D12-D11)/D11
A13: 2024-09-13 | B13: 17647 | C13: =(B13-B12)/B12 | D13: 1251.71 | E13: =(D13-D12)/D12
A14: 2024-09-16 | B14: 17551 | C14: =(B14-B13)/B13 | D14: 1239.26 | E14: =(D14-D13)/D13
A15: 2024-09-17 | B15: 17838 | C15: =(B15-B14)/B14 | D15: 1258.95 | E15: =(D15-D14)/D14
A16: 2024-09-18 | B16: 17838 | C16: =(B16-B15)/B15 | D16: 1264.9 | E16: =(D16-D15)/D15
A17: 2024-09-19 | B17: 17934 | C17: =(B17-B16)/B16 | D17: 1271.27 | E17: =(D17-D16)/D16
... A505: 2026-09-08 | B505: 27400 | C505: =(B505-B504)/B504 | D505: 1830.44 | E505: =(D505-D504)/D504

Sheet 00_COE
A1: CHI PHÍ VỐN CSH (COE) — MÔ HÌNH CAPM
A3: Tham số | B3: Giá trị | C3: Ghi chú / Tra cứu
A4: Rf — Lãi suất phi rủi ro | B4: 0.045
A5: β — Hệ số Beta (Blume adjusted) | B5: ='00_Beta'!E1 | C5: =HYPERLINK("https://finance.vietstock.vn/search?query=VPB", "Tra cứu Beta trên Vietstock (tham khảo)")
A6: ERP — Phần bù rủi ro vốn | B6: 0.07
A7: α — Phần bù rủi ro đặc thù (Frontier/Bank) | B7: 0.02
A9: COE = Rf + β × ERP + α | B9: =B4+B5*B6+B7

Sheet 01_Cover
B2: PHÂN TÍCH CỔ PHIẾU NGÂN HÀNG: VPB
B3: Ngân hàng Thương mại Cổ phần Việt Nam Thịnh Vượng
B4: Ngày lập: 08/09/2026 22:58
B5: Giá hiện tại (VND): | C5: ='02_Assumptions'!B2
B6: Giá mục tiêu (VND): | C6: ='07_Valuation'!B21
B7: Upside: | C7: ='07_Valuation'!B23
B8: Khuyến nghị: | C8: =IF('07_Valuation'!B23>0.15,"MUA",IF('07_Valuation'!B23<-0.05,"BÁN","THEO DÕI"))

Sheet 02_Assumptions
A1: Chỉ tiêu | B1: 2021 | C1: 2022 | D1: 2023 | E1: 2024 | F1: 2025 | G1: 2026F | H1: 2027F | I1: 2028F
A2: Giá cổ phiếu (VND) | B2: 27300
A3: Số lượng CP lưu hành | B3: 4505693000 | C3: 6743423600 | D3: 7933923600 | E3: 7933923600 | F3: 7933923600 | G3: 7933923600 | H3: 7933923600 | I3: 7933923600
A4: Tín dụng tăng trưởng (%) | C4: =(SUM('05_Balance_Sheet'!C3:C4)-SUM('05_Balance_Sheet'!B3:B4))/SUM('05_Balance_Sheet'!B3:B4) | D4: =(SUM('05_Balance_Sheet'!D3:D4)-SUM('05_Balance_Sheet'!C3:C4))/SUM('05_Balance_Sheet'!C3:C4) | E4: =(SUM('05_Balance_Sheet'!E3:E4)-SUM('05_Balance_Sheet'!D3:D4))/SUM('05_Balance_Sheet'!D3:D4) | F4: =(SUM('05_Balance_Sheet'!F3:F4)-SUM('05_Balance_Sheet'!E3:E4))/SUM('05_Balance_Sheet'!E3:E4) | G4: =AVERAGE(D4:F4)*0.9 | H4: =MAX(G4-0.01,0.05) | I4: =MAX(H4-0.01,0.05)
A5: Huy động tăng trưởng (%) | C5: =((SUM('05_Balance_Sheet'!C5:C6)+'05_Balance_Sheet'!C7*0.0-'05_Balance_Sheet'!C8-'05_Balance_Sheet'!C9)-(SUM('05_Balance_Sheet'!B5:B6)+'05_Balance_Sheet'!B7*0.0-'05_Balance_Sheet'!B8-'05_Balance_Sheet'!B9))/(SUM('05_Balance_Sheet'!B5:B6)+'05_Balance_Sheet'!B7*0.0-'05_Balance_Sheet'!B8-'05_Balance_Sheet'!B9) | D5: =((SUM('05_Balance_Sheet'!D5:D6)+'05_Balance_Sheet'!D7*0.5-'05_Balance_Sheet'!D8-'05_Balance_Sheet'!D9)-(SUM('05_Balance_Sheet'!C5:C6)+'05_Balance_Sheet'!C7*0.0-'05_Balance_Sheet'!C8-'05_Balance_Sheet'!C9))/(SUM('05_Balance_Sheet'!C5:C6)+'05_Balance_Sheet'!C7*0.0-'05_Balance_Sheet'!C8-'05_Balance_Sheet'!C9) | E5: =((SUM('05_Balance_Sheet'!E5:E6)+'05_Balance_Sheet'!E7*0.4-'05_Balance_Sheet'!E8-'05_Balance_Sheet'!E9)-(SUM('05_Balance_Sheet'!D5:D6)+'05_Balance_Sheet'!D7*0.5-'05_Balance_Sheet'!D8-'05_Balance_Sheet'!D9))/(SUM('05_Balance_Sheet'!D5:D6)+'05_Balance_Sheet'!D7*0.5-'05_Balance_Sheet'!D8-'05_Balance_Sheet'!D9) | F5: =((SUM('05_Balance_Sheet'!F5:F6)+'05_Balance_Sheet'!F7*0.2-'05_Balance_Sheet'!F8-'05_Balance_Sheet'!F9)-(SUM('05_Balance_Sheet'!E5:E6)+'05_Balance_Sheet'!E7*0.4-'05_Balance_Sheet'!E8-'05_Balance_Sheet'!E9))/(SUM('05_Balance_Sheet'!E5:E6)+'05_Balance_Sheet'!E7*0.4-'05_Balance_Sheet'!E8-'05_Balance_Sheet'!E9) | G5: 0.2551 | H5: 0.2451 | I5: 0.2351
A6: NIM (%) | B6: ='06_Ratios'!B2 | C6: ='06_Ratios'!C2 | D6: ='06_Ratios'!D2 | E6: ='06_Ratios'!E2 | F6: ='06_Ratios'!F2 | G6: 0.0548 | H6: 0.0548 | I6: 0.0548 | J6: Năm 1 (2026E) cơ học (YOEA/COF): YOEA=9.60% (gốc 9.74% x hệ số 0.985), COF=6.42% (gốc 6.62% x hệ số 0.97) → NIM cơ học=5.68%. Đã có Q2 thực tế = 5.29% → NIM năm 1 = 50% cơ học + 50% Q2 thực tế = 5.48%. Năm 2/3 GIỮ NGUYÊN bằng năm 1 (không giả định NIM tăng, để định giá an toàn hơn).
A7: CIR (%) | B7: 0.242 | C7: 0.2442 | D7: 0.2803 | E7: 0.2303 | F7: 0.2496 | G7: 0.33 | H7: 0.32 | I7: 0.32
A8: CoC — Credit Cost (%) | B8: ='06_Ratios'!B8 | C8: ='06_Ratios'!C8 | D8: ='06_Ratios'!D8 | E8: ='06_Ratios'!E8 | F8: ='06_Ratios'!F8 | G8: =B29*B30 | H8: =B29*B31 | I8: =B29*B32
A9: NPL ratio (%) | B9: ='06_Ratios'!B7 | C9: ='06_Ratios'!C7 | D9: ='06_Ratios'!D7 | E9: ='06_Ratios'!E7 | F9: ='06_Ratios'!F7 | G9: =B33*B34 | H9: =B33*B35 | I9: =B33*B36
A10: CASA ratio (%) | B10: ='06_Ratios'!B9 | C10: ='06_Ratios'!C9 | D10: ='06_Ratios'!D9 | E10: ='06_Ratios'!E9 | F10: ='06_Ratios'!F9 | G10: =B37+B38 | H10: =B37+B39 | I10: =B37+B40
A11: Tăng trưởng non-TOI (%) | G11: 0.15 | H11: 0.15 | I11: 0.14
A12: Chi phí vốn CSH (COE) | G12: 0.144331 | H12: 0.144331 | I12: 0.144331
A13: Tăng trưởng dài hạn (g) | I13: 0.03
A14: Thuế suất (%) | G14: 0.2 | H14: 0.2 | I14: 0.2
A15: P/B Over (x) | G15: 1.5280941 | H15: 1.5280941 | I15: 1.5280941
A17: ——— THAM SỐ TÍNH TOÁN (có thể sửa trực tiếp) ———
A18: YOEA gốc (2025A) | B18: ='06_Ratios'!F10
A19: YOEA hệ số 2026F | B19: 0.985
A20: YOEA hệ số 2027F | B20: 0.985
A21: YOEA hệ số 2028F | B21: 0.985
A22: COF gốc (2025A) | B22: ='06_Ratios'!F11
A23: COF hệ số 2026F | B23: 0.97
A24: COF hệ số 2027F | B24: 0.97
A25: COF hệ số 2028F | B25: 0.97
A26: IEA_end gốc (2025A) | B26: ='05_Balance_Sheet'!F2
A27: DepBonds gốc (2025A) | B27: =SUM('05_Balance_Sheet'!F5:F6)
A28: --- Các tham số khác ---
A29: CoC gốc (2025A) | B29: ='06_Ratios'!F8
A30: CoC giảm còn 2026F | B30: 0.95
A31: CoC giảm còn 2027F | B31: 0.9
A32: CoC giảm còn 2028F | B32: 0.85
A33: NPL gốc (2025A) | B33: ='06_Ratios'!F7
A34: NPL giảm còn 2026F | B34: 0.95
A35: NPL giảm còn 2027F | B35: 0.9
A36: NPL giảm còn 2028F | B36: 0.85
A37: CASA gốc (2025A) | B37: ='06_Ratios'!F9
A38: CASA tăng thêm 2026F | B38: 0.01
A39: CASA tăng thêm 2027F | B39: 0.02
A40: CASA tăng thêm 2028F | B40: 0.03

Sheet 03_Income_Model
A1: Chỉ tiêu | B1: 2021 | C1: 2022 | D1: 2023 | E1: 2024 | F1: 2025 | G1: 2026F | H1: 2027F | I1: 2028F
A2: IEA bình quân (tỷ) | B2: 491499.8 | C2: 529898.72 | D2: 659579.23 | E2: 818083.6 | F2: 1039393.4 | G2: =(F18+G18)/2 | H2: =(G18+H18)/2 | I2: =(H18+I18)/2
A3: IEA tăng trưởng (%) | C3: =(C2-B2)/B2 | D3: =(D2-C2)/C2 | E3: =(E2-D2)/D2 | F3: =(F2-E2)/E2 | G3: ='02_Assumptions'!G4 | H3: ='02_Assumptions'!H4 | I3: ='02_Assumptions'!I4
A4: NIM (%) | B4: 0.0699 | C4: 0.0774 | D4: 0.0579 | E4: 0.0611 | F4: 0.0564 | G4: 0.0548 | H4: 0.0548 | I4: 0.0548
A5: NII (tỷ) | B5: 34348.829 | C5: 41021.058 | D5: 38174.676 | E5: 50002.402 | F5: 58662.713 | G5: =G2*'02_Assumptions'!G6 | H5: =H2*'02_Assumptions'!H6 | I5: =I2*'02_Assumptions'!I6
A6: Thu nhập dịch vụ | B6: 4059.031 | C6: 6437.752 | D6: 7211.882 | E6: 5204.328 | F6: 7381.663
A7: Thu nhập ngoại hối | B7: -76.394 | C7: -618.05 | D7: -805.973 | E7: 827.24 | F7: 297.016
A8: Thu nhập CK đầu tư | B8: 3159.745 | C8: 359.561 | D8: 630.205 | E8: 830.623 | F8: 1571.104
A9: Thu nhập khác | B9: 2807.788 | C9: 10583.967 | D9: 4525.551 | E9: 5377.662 | F9: 6706.16
A10: Tổng thu nhập ngoài lãi | B10: 9952.646 | C10: 16776.031 | D10: 11564.812 | E10: 12252.654 | F10: 15991.104 | G10: 18389.77 | H10: 21148.235 | I10: 24108.988
A11: Tổng thu nhập HĐ - TOI | B11: 44301.475 | C11: 57797.089 | D11: 49739.488 | E11: 62255.056 | F11: 74653.817 | G11: =G5+G10 | H11: =H5+H10 | I11: =I5+I10
A12: NII/TOI (%) | B12: 77.53 | C12: 70.97 | D12: 76.75 | E12: 80.32 | F12: 78.58
A13: Chi phí HĐ - OPEX | B13: 10718.937 | C13: 14115.731 | D13: 13941.218 | E13: 14339.732 | F13: 18630.319 | G13: =G11*'02_Assumptions'!G7 | H13: =H11*'02_Assumptions'!H7 | I13: =I11*'02_Assumptions'!I7
A14: PPOP - LN trước dự phòng | B14: 33582.538 | C14: 43681.358 | D14: 35798.27 | E14: 47915.324 | F14: 56023.498 | G14: =G11-G13 | H14: =H11-H13 | I14: =I11-I13
A15: PPOP/TOI (%) | B15: 75.8 | C15: 75.58 | D15: 71.97 | E15: 76.97 | F15: 75.04
A16: Dự phòng tín dụng | B16: 19218.768 | C16: 22461.226 | D16: 24994.374 | E16: 27902.624 | F16: 25398.549 | G16: =(('05_Balance_Sheet'!F3+'05_Balance_Sheet'!G3)/2)*'02_Assumptions'!G8 | H16: =(('05_Balance_Sheet'!G3+'05_Balance_Sheet'!H3)/2)*'02_Assumptions'!H8 | I16: =(('05_Balance_Sheet'!H3+'05_Balance_Sheet'!I3)/2)*'02_Assumptions'!I8
A17: LN trước thuế - PBT | B17: 14363.77 | C17: 21220.132 | D17: 10803.896 | E17: 20012.7 | F17: 30624.949 | G17: =G14-G16 | H17: =H14-H16 | I17: =I14-I16
A18: IEA cuối kỳ (tỷ) | B18: 491499.8 | C18: 568297.6 | D18: 750860.8 | E18: 885306.4 | F18: 1193480.3 | G18: =F18*(1+G3) | H18: =G18*(1+H3) | I18: =H18*(1+I3)

Sheet 04_PnL_Quarterly
A1: Chỉ tiêu | B1: Q1/2022 | C1: Q2/2022 | D1: Q3/2022 | E1: Q4/2022 | F1: Q1/2023 | G1: Q2/2023 | H1: Q3/2023 | I1: Q4/2023 | J1: Q1/2024 | K1: Q2/2024 | L1: Q3/2024 | M1: Q4/2024 | N1: Q1/2025 | O1: Q2/2025 | P1: Q3/2025 | Q1: Q4/2025 | R1: Q1/2026 | S1: Q2/2026
A2: Thu nhập lãi thuần - NII | B2: 9887.714 | C2: 10465.653 | D2: 10384.901 | E2: 10282.653 | F2: 9533.939 | G2: 8762.153 | H2: 8836.748 | I2: 11041.836 | J2: 11323.398 | K2: 12408.24 | L2: 12155.772 | M2: 14114.992 | N2: 13355.764 | O2: 13478.566 | P2: 15061.208 | Q2: 16767.175 | R2: 16960.628 | S2: 17973.498
A3: Thu nhập ngoài lãi | B3: 8381.881 | C3: 2820.836 | D3: 3088.237 | E3: 2485.155 | F3: 2824.814 | G3: 4019.353 | H3: 2425.283 | I3: 2299.304 | J3: 2087.214 | K3: 3728.792 | L3: 2907.235 | M3: 3529.413 | N3: 2210.324 | O3: 3056.065 | P3: 5076.348 | Q3: 5648.367 | R3: 2947.579 | S3: 5510.136
A4: Tổng thu nhập HĐ - TOI | B4: 18269.595 | C4: 13286.489 | D4: 13473.138 | E4: 12767.808 | F4: 12358.753 | G4: 12781.506 | H4: 11262.031 | I4: 13341.14 | J4: 13410.612 | K4: 16137.032 | L4: 15063.007 | M4: 17644.405 | N4: 15566.088 | O4: 16534.631 | P4: 20137.556 | Q4: 22415.542 | R4: 19908.207 | S4: 23483.634
A5: Chi phí hoạt động - OPEX | B5: 2990.976 | C5: 3524.036 | D5: 3536.223 | E5: 4064.846 | F5: 3422.919 | G5: 3678.666 | H5: 3194.749 | I5: 3615.483 | J5: 3466.567 | K5: 3331.107 | L5: 3750.96 | M5: 3791.098 | N5: 3873.901 | O5: 4404.427 | P5: 4427.75 | Q5: 5924.241 | R5: 4318.327 | S5: 4614.08
A6: LN trước dự phòng - PPOP | B6: 15278.619 | C6: 9762.453 | D6: 9936.915 | E6: 8702.962 | F6: 8935.834 | G6: 9102.84 | H6: 8067.282 | I6: 9725.657 | J6: 9944.045 | K6: 12805.925 | L6: 11312.047 | M6: 13853.307 | N6: 11692.187 | O6: 12130.204 | P6: 15709.806 | Q6: 16491.301 | R6: 15589.88 | S6: 18869.554
A7: Dự phòng tín dụng | B7: 4132.443 | C7: 5585.723 | D7: 5422.915 | E7: 7320.145 | F7: 6386.179 | G7: 6490.301 | H7: 4950.15 | I7: 7017.806 | J7: 5762.193 | K7: 8313.437 | L7: 6125.121 | M7: 7701.873 | N7: 6677.305 | O7: 5915.679 | P7: 6543.509 | Q7: 6262.056 | R7: 7669.094 | S7: 7910.375
A8: LN trước thuế - PBT | B8: 11146.176 | C8: 4176.73 | D8: 4514 | E8: 1382.817 | F8: 2549.655 | G8: 2612.539 | H8: 3117.132 | I8: 2707.851 | J8: 4181.852 | K8: 4492.488 | L8: 5186.926 | M8: 6151.434 | N8: 5014.882 | O8: 6214.525 | P8: 9166.297 | Q8: 10229.245 | R8: 7920.786 | S8: 10959.179
A9: LN sau thuế - NPAT | B9: 8916.823 | C9: 3324.075 | D9: 3542.43 | E9: 1140.448 | F9: 1649.719 | G9: 2452.231 | H9: 2427.678 | I9: 2111.161 | J9: 3141.883 | K9: 3641.161 | L9: 4164.26 | M9: 5039.522 | N9: 3934.954 | O9: 4937.496 | P9: 7363.737 | Q9: 8118.409 | R9: 6329.468 | S9: 8775.909
A10: Chi phí lãi (Int Exp) | B10: 1249.219 | C10: 1538.007 | D10: 1769.456 | E10: 1881.147 | F10: 1668.354 | G10: 1657.042 | H10: 1889.361 | I10: 1881.068 | J10: 1553.831 | K10: 1883.037 | L10: 1147.565 | M10: 619.895 | N10: 1168.799 | O10: 1343.252 | P10: 2392.034 | Q10: 2477.578 | R10: 2064.523 | S10: 3490.13

Sheet 04_PnL
A1: Chỉ tiêu | B1: 2021 | C1: 2022 | D1: 2023 | E1: 2024 | F1: 2025 | G1: 2026F | H1: 2027F | I1: 2028F
A2: Thu nhập lãi thuần (NII) | B2: 34348.829 | C2: 41021.058 | D2: 38174.676 | E2: 50002.402 | F2: 58662.713 | G2: ='03_Income_Model'!G5 | H2: ='03_Income_Model'!H5 | I2: ='03_Income_Model'!I5
A3: Tổng thu nhập hoạt động (TOI) | B3: 44301.475 | C3: 57797.089 | D3: 49739.488 | E3: 62255.056 | F3: 74653.817 | G3: =SUM(G2+'03_Income_Model'!G10) | H3: =SUM(H2+'03_Income_Model'!H10) | I3: =SUM(I2+'03_Income_Model'!I10)
A4: Lợi nhuận trước dự phòng (PPOP) | B4: 33582.538 | C4: 43681.358 | D4: 35798.27 | E4: 47915.324 | F4: 56023.498 | G4: ='03_Income_Model'!G14 | H4: ='03_Income_Model'!H14 | I4: ='03_Income_Model'!I14
A5: LNST (NPAT) | B5: 11477.17 | C5: 16908.807 | D5: 8494.171 | E5: 15986.826 | F5: 24354.596 | G5: =('03_Income_Model'!G17)-MAX(('03_Income_Model'!G17)*'02_Assumptions'!G14,0) | H5: =('03_Income_Model'!H17)-MAX(('03_Income_Model'!H17)*'02_Assumptions'!H14,0) | I5: =('03_Income_Model'!I17)-MAX(('03_Income_Model'!I17)*'02_Assumptions'!I14,0)
A6: EPS (VND) | B6: 2547.2597 | C6: 2507.4514 | D6: 1070.6142 | E6: 2014.9962 | F6: 3069.6787 | G6: =G5*1000000000/'02_Assumptions'!G3 | H6: =H5*1000000000/'02_Assumptions'!H3 | I6: =I5*1000000000/'02_Assumptions'!I3

Sheet 05_Balance_Sheet_Quarterly
A1: Chỉ tiêu | B1: Q1/2022 | C1: Q2/2022 | D1: Q3/2022 | E1: Q4/2022 | F1: Q1/2023 | G1: Q2/2023 | H1: Q3/2023 | I1: Q4/2023 | J1: Q1/2024 | K1: Q2/2024 | L1: Q3/2024 | M1: Q4/2024 | N1: Q1/2025 | O1: Q2/2025 | P1: Q3/2025 | Q1: Q4/2025 | R1: Q1/2026 | S1: Q2/2026
A2: Tổng tài sản | B2: 563923.69 | C2: 608275.14 | D2: 595901.87 | E2: 631073.66 | F2: 677623.73 | G2: 739761.99 | H2: 780212.73 | I2: 817699.54 | J2: 822366.98 | K2: 864392.98 | L2: 858884.59 | M2: 923847.64 | N2: 994036.65 | O2: 1104718.5 | P2: 1178298.6 | Q2: 1260149.6 | R2: 1372010 | S2: 1502526.4
A3: Tiền mặt & NHNN | B3: 6934.643 | C3: 7285.128 | D3: 6782.508 | E3: 12593.872 | F3: 11812.899 | G3: 12387.336 | H3: 11848.889 | I3: 10707.501 | J3: 10191.747 | K3: 17572.826 | L3: 16228.366 | M3: 16475.504 | N3: 9863.195 | O3: 19724.318 | P3: 17183.555 | Q3: 16344.658 | R3: 18882.481 | S3: 15976.632
A4: TG các TCTD khác | B4: 51850.561 | C4: 62025.635 | D4: 47833.645 | E4: 47965.493 | F4: 69935.068 | G4: 105026.76 | H4: 98886.732 | I4: 94093.778 | J4: 98545.79 | K4: 115858.61 | L4: 119231.09 | M4: 134643.66 | N4: 142751.03 | O4: 154342.4 | P4: 166685.54 | Q4: 186228.94 | R4: 195016.58 | S4: 199197.88
A5: Cho vay khách hàng | B5: 362946.44 | C5: 379718.35 | D5: 390122.81 | E5: 424662.38 | F5: 450145.68 | G5: 474940.43 | H5: 508798.76 | I5: 551622 | J5: 567636.43 | K5: 609030.87 | L5: 619865.9 | M5: 681404.17 | N5: 713554.85 | O5: 811930.92 | P5: 879072.2 | Q5: 926472.66 | R5: 1021232.1 | S5: 1140006.7
A6: CK đầu tư | B6: 92350.151 | C6: 101733.42 | D6: 87756.862 | E6: 83075.897 | F6: 78811.465 | G6: 80047.557 | H6: 87404.082 | I6: 94587.476 | J6: 82798.265 | K6: 59429.591 | L6: 58056.373 | M6: 52783.054 | N6: 57972.59 | O6: 73755.887 | P6: 57363.954 | Q6: 64434.066 | R6: 65833.137 | S6: 62911.491
A7: Tiền gửi khách hàng | B7: 274148.7 | C7: 295419.57 | D7: 277422.33 | E7: 303151.42 | F7: 331184.43 | G7: 387611.14 | H7: 421471.75 | I7: 442368.38 | J7: 455817.48 | K7: 471348.62 | L7: 475782.34 | M7: 485666.55 | N7: 552373.98 | O7: 600774.16 | P7: 585833.05 | Q7: 628044.62 | R7: 682719.37 | S7: 732887.44
A8: Vốn chủ sở hữu | B8: 95202.019 | C8: 98523.824 | D8: 102366.25 | E8: 103516.89 | F8: 105097.64 | G8: 107563.87 | H8: 109991.55 | I8: 139946.57 | J8: 142937.41 | K8: 138075.61 | L8: 142239.87 | M8: 147275.26 | N8: 151213.36 | O8: 152182.68 | P8: 159545.29 | Q8: 180275.63 | R8: 186604.8 | S8: 191215.34
A9: TPDN (trái phiếu TCKT) | B9: 41593.119 | C9: 37190.838 | D9: 33013.8 | E9: 32891.899 | F9: 28197.933 | G9: 28331.744 | H9: 28167.762 | I9: 23605.716 | J9: 21286.878 | K9: 12547.387 | L9: 10569.188 | M9: 7966.743 | N9: 7247.394 | O9: 4446.615 | P9: 4087.215 | Q9: 2804.914 | R9: 2564.724 | S9: 2627.237
A10: Giấy tờ có giá (Bonds) | B10: 76781.597 | C10: 76025.392 | D10: 72872.562 | E10: 63699.974 | F10: 82485.019 | G10: 73281.087 | H10: 64999.327 | I10: 47787.312 | J10: 46344.356 | K10: 54199.709 | L10: 50941.501 | M10: 66975.704 | N10: 78788.99 | O10: 83140.558 | P10: 106091.09 | Q10: 107120.65 | R10: 138840.02 | S10: 168943.54
A11: Tiền gửi Kho bạc NN | B11: 44268.757 | C11: 48463.587 | D11: 53781.235 | E11: 53971.282 | F11: 54192.123 | G11: 51897.373 | H11: 57191.12 | I11: 55546.509 | J11: 48493.251 | K11: 48450.43 | L11: 32087.374 | M11: 22423.057 | N11: 51273.416 | O11: 31960.914 | P11: 35871.116 | Q11: 39152.252 | R11: 44144.605 | S11: 53234.839
A12: Tiền gửi ký quỹ (trừ đi) | B12: 3784.293 | C12: 4360.848 | D12: 3853.934 | E12: 6028.739 | F12: 4709.645 | G12: 3088.177 | H12: 3660.48 | I12: 3219.23 | J12: 2650.132 | K12: 3936.333 | L12: 3879.633 | M12: 3626.525 | N12: 3768.819 | O12: 4392.017 | P12: 5031.665 | Q12: 6012.259 | R12: 9089.926 | S12: 13913.52
A13: Vốn chuyên dùng (trừ đi) | B13: 86.864 | C13: 71.739 | D13: 57.983 | E13: 47.05 | F13: 39 | G13: 32.433 | H13: 26.538 | I13: 22.045 | J13: 18.39 | K13: 15.529 | L13: 13.025 | M13: 10.894 | N13: 9.192 | O13: 7.497 | P13: 10.814 | Q13: 16.394 | R13: 38.296 | S13: 69.858
A14: Tài sản sinh lãi (IEA) | B14: 514081.8 | C14: 550762.53 | D14: 532495.82 | E14: 568297.64 | F14: 610705.11 | G14: 672402.08 | H14: 706938.46 | I14: 751010.76 | J14: 759172.23 | K14: 801891.9 | L14: 813381.73 | M14: 885306.39 | N14: 924141.67 | O14: 1059753.5 | P14: 1120305.2 | Q14: 1193480.3 | R14: 1300964.3 | S14: 1418092.7
A15: Tổng tín dụng (tỷ) | B15: =B5+B9 | C15: =C5+C9 | D15: =D5+D9 | E15: =E5+E9 | F15: =F5+F9 | G15: =G5+G9 | H15: =H5+H9 | I15: =I5+I9 | ... S15: =S5+S9
A16: Tổng huy động (tỷ) | B16: =B7+B10+B17+B11*0.0-B12-B13 | C16: =C7+C10+C17+C11*0.0-C12-C13 | D16: =D7+D10+D17+D11*0.0-D12-D13 | E16: =E7+E10+E17+E11*0.0-E12-E13 | F16: =F7+F10+F17+F11*0.5-F12-F13 | G16: =G7+G10+G17+G11*0.5-G12-G13 | H16: =H7+H10+H17+H11*0.5-H12-H13 | I16: =I7+I10+I17+I11*0.5-I12-I13 | J16: =J7+J10+J17+J11*0.4-J12-J13 | K16: =K7+K10+K17+K11*0.4-K12-K13 | L16: =L7+L10+L17+L11*0.4-L12-L13 | M16: =M7+M10+M17+M11*0.4-M12-M13 | N16: =N7+N10+N17+N11*0.2-N12-N13 | O16: =O7+O10+O17+O11*0.2-O12-O13 | P16: =P7+P10+P17+P11*0.2-P12-P13 | Q16: =Q7+Q10+Q17+Q11*0.2-Q12-Q13 | R16: =R7+R10+R17+R11*0.2-R12-R13 | S16: =S7+S10+S17+S11*0.2-S12-S13
A17: Tiền gửi của TCTD khác | B17: 38726.286 | C17: 43005.291 | D17: 46545.936 | E17: 51325.927 | F17: 60937.487 | G17: 79426.408 | H17: 80100.321 | I17: 83234.756 | J17: 77529.895 | K17: 81845.87 | L17: 80189.046 | M17: 111863.21 | N17: 89678.391 | O17: 118204.79 | P17: 134763.01 | Q17: 140778.78 | R17: 149661.01 | S17: 149580.46

Sheet 05_Balance_Sheet
A1: Chỉ tiêu | B1: 2021 | C1: 2022 | D1: 2023 | E1: 2024 | F1: 2025 | G1: 2026F | H1: 2027F | I1: 2028F
A2: Tổng tài sản | B2: 547409.44 | C2: 631012.89 | D2: 817566.92 | E2: 923847.64 | F2: 1260149.6 | G2: =SUM(G3:G6)+G7-G8-G9+G10 | H2: =SUM(H3:H6)+H7-H8-H9+H10 | I2: =SUM(I3:I6)+I7-I8-I9+I10
A3: Cho vay khách hàng (Gross) | B3: 345390.28 | C3: 424662.38 | D3: 551472.07 | E3: 681404.17 | F3: 926472.66 | G3: =F3*(1+'02_Assumptions'!G4) | H3: =G3*(1+'02_Assumptions'!H4) | I3: =H3*(1+'02_Assumptions'!I4)
A4: Trái phiếu doanh nghiệp | B4: 27782.414 | C4: 32891.899 | D4: 23605.716 | E4: 7966.743 | F4: 2804.914 | G4: =F4*(1+'02_Assumptions'!G4) | H4: =G4*(1+'02_Assumptions'!H4) | I4: =H4*(1+'02_Assumptions'!I4)
A5: Tiền gửi khách hàng | B5: 241837.03 | C5: 303151.42 | D5: 442368.38 | E5: 485666.55 | F5: 628044.62 | G5: =F5*(1+'02_Assumptions'!G5) | H5: =G5*(1+'02_Assumptions'!H5) | I5: =H5*(1+'02_Assumptions'!I5)
A6: Giấy tờ có giá phát hành (Bonds) | B6: 81295.633 | C6: 63699.974 | D6: 47787.312 | E6: 66975.704 | F6: 107120.65 | G6: =F6*1.02 | H6: =G6*1.02 | I6: =H6*1.02
A7: Tiền gửi Kho bạc Nhà nước | B7: 54208.397 | C7: 53910.506 | D7: 55563.831 | E7: 22423.057 | F7: 39152.252 | G7: =F7*(1+'02_Assumptions'!G5) | H7: =G7*(1+'02_Assumptions'!H5) | I7: =H7*(1+'02_Assumptions'!I5)
A8: Tiền gửi ký quỹ (trừ đi) | B8: 3530.268 | C8: 6028.739 | D8: 3219.23 | E8: 3626.525 | F8: 6012.259 | G8: =F8*(1+'02_Assumptions'!G5) | H8: =G8*(1+'02_Assumptions'!H5) | I8: =H8*(1+'02_Assumptions'!I5)
A9: Vốn chuyên dùng (trừ đi) | B9: 103.93 | C9: 47.05 | D9: 22.045 | E9: 10.894 | F9: 16.394 | G9: =F9*1.02 | H9: =G9*1.02 | I9: =H9*1.02
A10: Vốn chủ sở hữu (VCSH) | B10: 86278.147 | C10: 103501.92 | D10: 139795.53 | E10: 147275.26 | F10: 180275.63 | G10: =F10+'04_PnL'!G5*0.7 | H10: =G10+'04_PnL'!H5*0.7 | I10: =H10+'04_PnL'!I5*0.7
A11: Tổng tín dụng (tỷ) | B11: =B3+B4 | C11: =C3+C4 | D11: =D3+D4 | E11: =E3+E4 | F11: =F3+F4 | G11: =G3+G4 | H11: =H3+H4 | I11: =I3+I4
A12: Tổng huy động (tỷ) | B12: =B5+B6+B13+B7*0.0-B8-B9 | C12: =C5+C6+C13+C7*0.0-C8-C9 | D12: =D5+D6+D13+D7*0.5-D8-D9 | E12: =E5+E6+E13+E7*0.4-E8-E9 | F12: =F5+F6+F13+F7*0.2-F8-F9 | G12: =G5+G6+G13+G7*0.2-G8-G9 | H12: =H5+H6+H13+H7*0.2-H8-H9 | I12: =I5+I6+I13+I7*0.2-I8-I9
A13: Tiền gửi của TCTD khác | B13: 47106.801 | C13: 51325.927 | D13: 83234.756 | E13: 111863.21 | F13: 140778.78 | G13: =F13*(1+'02_Assumptions'!G5) | H13: =G13*(1+'02_Assumptions'!H5) | I13: =H13*(1+'02_Assumptions'!I5)

Sheet 06_Ratios_Quarterly
A1: Chỉ tiêu | B1: Q1/2022 | C1: Q2/2022 | D1: Q3/2022 | E1: Q4/2022 | F1: Q1/2023 | G1: Q2/2023 | H1: Q3/2023 | I1: Q4/2023 | J1: Q1/2024 | K1: Q2/2024 | L1: Q3/2024 | M1: Q4/2024 | N1: Q1/2025 | O1: Q2/2025 | P1: Q3/2025 | Q1: Q4/2025 | R1: Q1/2026 | S1: Q2/2026
A2: NIM — năm hóa (%) | B2: =('04_PnL_Quarterly'!B2*4/(('05_Balance_Sheet_Quarterly'!B14+'05_Balance_Sheet_Quarterly'!B14)/2))*100 | C2: =('04_PnL_Quarterly'!C2*4/(('05_Balance_Sheet_Quarterly'!B14+'05_Balance_Sheet_Quarterly'!C14)/2))*100 | D2: =('04_PnL_Quarterly'!D2*4/(('05_Balance_Sheet_Quarterly'!C14+'05_Balance_Sheet_Quarterly'!D14)/2))*100 | E2: =('04_PnL_Quarterly'!E2*4/(('05_Balance_Sheet_Quarterly'!D14+'05_Balance_Sheet_Quarterly'!E14)/2))*100 | F2: =('04_PnL_Quarterly'!F2*4/(('05_Balance_Sheet_Quarterly'!E14+'05_Balance_Sheet_Quarterly'!F14)/2))*100 | G2: =('04_PnL_Quarterly'!G2*4/(('05_Balance_Sheet_Quarterly'!F14+'05_Balance_Sheet_Quarterly'!G14)/2))*100 | H2: =('04_PnL_Quarterly'!H2*4/(('05_Balance_Sheet_Quarterly'!G14+'05_Balance_Sheet_Quarterly'!H14)/2))*100 | I2: =('04_PnL_Quarterly'!I2*4/(('05_Balance_Sheet_Quarterly'!H14+'05_Balance_Sheet_Quarterly'!I14)/2))*100 | J2: =('04_PnL_Quarterly'!J2*4/(('05_Balance_Sheet_Quarterly'!I14+'05_Balance_Sheet_Quarterly'!J14)/2))*100 | ... S2: =('04_PnL_Quarterly'!S2*4/(('05_Balance_Sheet_Quarterly'!R14+'05_Balance_Sheet_Quarterly'!S14)/2))*100
A3: ROE — năm hóa (%) | B3: =('04_PnL_Quarterly'!B8*4/'05_Balance_Sheet_Quarterly'!B8)*100 | C3: =('04_PnL_Quarterly'!C8*4/'05_Balance_Sheet_Quarterly'!C8)*100 | D3: =('04_PnL_Quarterly'!D8*4/'05_Balance_Sheet_Quarterly'!D8)*100 | E3: =('04_PnL_Quarterly'!E8*4/'05_Balance_Sheet_Quarterly'!E8)*100 | F3: =('04_PnL_Quarterly'!F8*4/'05_Balance_Sheet_Quarterly'!F8)*100 | G3: =('04_PnL_Quarterly'!G8*4/'05_Balance_Sheet_Quarterly'!G8)*100 | H3: =('04_PnL_Quarterly'!H8*4/'05_Balance_Sheet_Quarterly'!H8)*100 | I3: =('04_PnL_Quarterly'!I8*4/'05_Balance_Sheet_Quarterly'!I8)*100 | ... S3: =('04_PnL_Quarterly'!S8*4/'05_Balance_Sheet_Quarterly'!S8)*100
A4: LDR (%) | B4: =('05_Balance_Sheet_Quarterly'!B15/'05_Balance_Sheet_Quarterly'!B16)*100 | C4: =('05_Balance_Sheet_Quarterly'!C15/'05_Balance_Sheet_Quarterly'!C16)*100 | D4: =('05_Balance_Sheet_Quarterly'!D15/'05_Balance_Sheet_Quarterly'!D16)*100 | E4: =('05_Balance_Sheet_Quarterly'!E15/'05_Balance_Sheet_Quarterly'!E16)*100 | F4: =('05_Balance_Sheet_Quarterly'!F15/'05_Balance_Sheet_Quarterly'!F16)*100 | G4: =('05_Balance_Sheet_Quarterly'!G15/'05_Balance_Sheet_Quarterly'!G16)*100 | H4: =('05_Balance_Sheet_Quarterly'!H15/'05_Balance_Sheet_Quarterly'!H16)*100 | I4: =('05_Balance_Sheet_Quarterly'!I15/'05_Balance_Sheet_Quarterly'!I16)*100 | ... S4: =('05_Balance_Sheet_Quarterly'!S15/'05_Balance_Sheet_Quarterly'!S16)*100
A5: COF — năm hóa (%) | B5: =('04_PnL_Quarterly'!B10*4/'05_Balance_Sheet_Quarterly'!B7)*100 | C5: =('04_PnL_Quarterly'!C10*4/'05_Balance_Sheet_Quarterly'!C7)*100 | D5: =('04_PnL_Quarterly'!D10*4/'05_Balance_Sheet_Quarterly'!D7)*100 | E5: =('04_PnL_Quarterly'!E10*4/'05_Balance_Sheet_Quarterly'!E7)*100 | F5: =('04_PnL_Quarterly'!F10*4/'05_Balance_Sheet_Quarterly'!F7)*100 | G5: =('04_PnL_Quarterly'!G10*4/'05_Balance_Sheet_Quarterly'!G7)*100 | H5: =('04_PnL_Quarterly'!H10*4/'05_Balance_Sheet_Quarterly'!H7)*100 | I5: =('04_PnL_Quarterly'!I10*4/'05_Balance_Sheet_Quarterly'!I7)*100 | ... S5: =('04_PnL_Quarterly'!S10*4/'05_Balance_Sheet_Quarterly'!S7)*100

Sheet 06_Ratios
A1: Chỉ tiêu | B1: 2021 | C1: 2022 | D1: 2023 | E1: 2024 | F1: 2025 | G1: 2026F | H1: 2027F | I1: 2028F
A2: NIM (%) | B2: 0.0699 | C2: 0.0774 | D2: 0.0579 | E2: 0.0611 | F2: 0.0564 | G2: ='02_Assumptions'!G6 | H2: ='02_Assumptions'!H6 | I2: ='02_Assumptions'!I6
A3: CIR (%) | B3: ='02_Assumptions'!B7 | C3: ='02_Assumptions'!C7 | D3: ='02_Assumptions'!D7 | E3: ='02_Assumptions'!E7 | F3: ='02_Assumptions'!F7 | G3: ='02_Assumptions'!G7 | H3: ='02_Assumptions'!H7 | I3: ='02_Assumptions'!I7
A4: ROE (%) | B4: 0.133 | C4: 0.1782 | D4: 0.0698 | E4: 0.1114 | F4: 0.1487 | G4: ='04_PnL'!G5/AVERAGE('05_Balance_Sheet'!F10,'05_Balance_Sheet'!G10) | H4: ='04_PnL'!H5/AVERAGE('05_Balance_Sheet'!G10,'05_Balance_Sheet'!H10) | I4: ='04_PnL'!I5/AVERAGE('05_Balance_Sheet'!H10,'05_Balance_Sheet'!I10)
A5: ROA (%) | B5: 0.021 | C5: 0.0268 | D5: 0.0104 | E5: 0.0173 | F5: 0.0193 | G5: ='04_PnL'!G5/AVERAGE('05_Balance_Sheet'!F2,'05_Balance_Sheet'!G2) | H5: ='04_PnL'!H5/AVERAGE('05_Balance_Sheet'!G2,'05_Balance_Sheet'!H2) | I5: ='04_PnL'!I5/AVERAGE('05_Balance_Sheet'!H2,'05_Balance_Sheet'!I2)
A6: LDR — điều chỉnh (%) | B6: ='05_Balance_Sheet'!B11/'05_Balance_Sheet'!B12 | C6: ='05_Balance_Sheet'!C11/'05_Balance_Sheet'!C12 | D6: ='05_Balance_Sheet'!D11/'05_Balance_Sheet'!D12 | E6: ='05_Balance_Sheet'!E11/'05_Balance_Sheet'!E12 | F6: ='05_Balance_Sheet'!F11/'05_Balance_Sheet'!F12 | G6: ='05_Balance_Sheet'!G11/'05_Balance_Sheet'!G12 | H6: ='05_Balance_Sheet'!H11/'05_Balance_Sheet'!H12 | I6: ='05_Balance_Sheet'!I11/'05_Balance_Sheet'!I12
A7: NPL (%) | B7: 0.047 | C7: 0.0592 | D7: 0.0515 | E7: 0.0427 | F7: 0.034 | G7: =F7*'02_Assumptions'!B34 | H7: =F7*'02_Assumptions'!B35 | I7: =F7*'02_Assumptions'!B36
A8: CoC — Credit Cost (%) | B8: 0.0556 | C8: 0.0583 | D8: 0.0512 | E8: 0.0453 | F8: 0.0316 | G8: =F8*'02_Assumptions'!B30 | H8: =F8*'02_Assumptions'!B31 | I8: =F8*'02_Assumptions'!B32
A9: CASA ratio (%) | B9: 0.2192 | C9: 0.1654 | D9: 0.1703 | E9: 0.1371 | F9: 0.1365 | G9: =F9+'02_Assumptions'!B38 | H9: =F9+'02_Assumptions'!B39 | I9: =F9+'02_Assumptions'!B40
A10: YOEA — Lợi suất TSSL (%) | B10: 0.1034 | C10: 0.1174 | D10: 0.1161 | E10: 0.0991 | F10: 0.0974
A11: COF — Chi phí vốn (%) | B11: 0.051 | C11: 0.0614 | D11: 0.0896 | E11: 0.0595 | F11: 0.0662

Sheet 07_Valuation
A1: PHƯƠNG PHÁP ĐỊNH GIÁ
A2: Chi phí vốn CSH (COE) | B2: ='00_COE'!B9
A3: Tăng trưởng dài hạn (g) | B3: 0.03
A5: RESIDUAL INCOME MODEL
A6: BV/share hiện tại (VND) | B6: ='05_Balance_Sheet'!F10*1000000000/'02_Assumptions'!$F$3
A7: PV của RI 3 năm (VND) | B7: =SUM(B31:D31)
A8: PV của Continuing Value (VND) | B8: =(D29*(1+B3)/(B2-B3))*D30
A9: GIÁ TRỊ RI (VND) | B9: =B6+B7+B8
A11: P/B MULTIPLE — 3 mức phân phối lịch sử
A12: P/B hiện tại (x) | B12: ='02_Assumptions'!B2/B6
A13: P/B hấp dẫn (x) — MUA | B13: {=MEDIAN(SMALL('13_PE_PB_History'!C2:C33, ROW(INDIRECT("1:"&CEILING(COUNT('13_PE_PB_History'!C2:C33)/2,1)))))} | C13: Median P/B nửa dưới (vùng mua hấp dẫn)
A14: P/B median all-time (x) — FAIR VALUE | B14: =MEDIAN('13_PE_PB_History'!C2:C33) | C14: Median PB toàn bộ lịch sử
A15: P/B Over (x) — BÁN / CHỐT LỜI | B15: {=MEDIAN(LARGE('13_PE_PB_History'!C2:C33, ROW(INDIRECT("1:"&CEILING(COUNT('13_PE_PB_History'!C2:C33)/2,1)))))} | C15: Median P/B nửa trên (vùng chốt lời)
A16: BV/share tương lai (2026F) | B16: =B6+B26
A17: GIÁ TRỊ P/B (VND) | B17: =B14*B16
A19: WEIGHTED TARGET PRICE
A20: Trong số: 40% RI + 60% P/B
A21: Target Price (VND) | B21: =B9*0.4+B17*0.6
A22: Giá hiện tại (VND) | B22: ='02_Assumptions'!B2
A23: UPSIDE (%) | B23: =B21/B22-1
A25: --- RI DETAIL ---
A26: EPS (VND) | B26: ='04_PnL'!G6 | C26: ='04_PnL'!H6 | D26: ='04_PnL'!I6
A27: BVPS đầu kỳ (VND) | B27: =B6 | C27: =B27+B26 | D27: =C27+C26
A28: Capital Charge (VND) | B28: =B27*'07_Valuation'!$B$2 | C28: =C27*'07_Valuation'!$B$2 | D28: =D27*'07_Valuation'!$B$2
A29: Residual Income (VND) | B29: =B26-B28 | C29: =C26-C28 | D29: =D26-D28
A30: Discount Factor | B30: =1/(1+'07_Valuation'!$B$2)^1 | C30: =1/(1+'07_Valuation'!$B$2)^2 | D30: =1/(1+'07_Valuation'!$B$2)^3
A31: PV of RI | B31: =B29*B30 | C31: =C29*C30 | D31: =D29*D30

Sheet 08_Sensitivity
A1: Độ nhạy: Giá trị RI theo COE × g (5×5)
A2: COE \ g | B2: 0.01 | C2: 0.02 | D2: 0.03 | E2: 0.04 | F2: 0.05
A3: 0.08 | B3: 31228.868 | C3: 32629.964 | D3: 34591.5 | E3: 37533.803 | F3: 42437.642
A4: 0.1 | B4: 29122.522 | C4: 29910.378 | D4: 30923.337 | E4: 32273.947 | F4: 34164.803
A5: 0.12 | B5: 27791.524 | C5: 28288.959 | D5: 28896.935 | E5: 29656.905 | F5: 30634.009
A6: 0.14 | B6: 26877.467 | C6: 27216.023 | D6: 27616.135 | E6: 28096.269 | F6: 28683.1
A7: 0.16 | B7: 26213.136 | C7: 26456.037 | D7: 26736.307 | E7: 27063.29 | F7: 27449.724

Sheet 09_PESTLE
A1: Nhân tố | B1: Nội dung | C1: Tác động | D1: Mức độ
A2: Chính trị (Political) | B2: Môi trường chính trị ổn định, NHNN điều hành linh hoạt hỗ trợ tăng trưởng tín dụng. | C2: Tích cực | D2: Cao
A3: Kinh tế (Economic) | B3: GDP tăng trưởng 6–7%, nhu cầu vốn sản xuất–tiêu dùng cao, lãi suất huy động giảm dần. | C3: Tích cực | D3: Cao
A4: Xã hội (Social) | B4: Tầng lớp trung lưu mở rộng, thanh toán không tiền mặt tăng mạnh thúc đẩy CASA và phí dịch vụ. | C4: Tích cực | D4: Trung bình
A5: Công nghệ (Technological) | B5: Chuyển đổi số banking (mobile/open banking) giảm CIR, tăng CASA và cross-sell sản phẩm. | C5: Tích cực | D5: Cao
A6: Pháp lý (Legal) | B6: Thông tư 06/2024 siết TPDN, Basel II/III nâng chuẩn CAR — cần theo dõi áp lực pháp lý. | C6: Trung tính | D6: Trung bình
A7: Môi trường (Environmental) | B7: ESG lending ngày càng được yêu cầu; rủi ro tín dụng BĐS liên quan biến đổi khí hậu tăng. | C7: Tiêu cực | D7: Thấp

Sheet 10_Leading_Indicators
A1: Chỉ số | B1: Ngưỡng tích cực | C1: Giá trị hiện tại | D1: Trạng thái
A2: NPL ratio (%) | B2: < 1.5% | C2: 3.40% | D2: Đạt
A3: CASA ratio (%) | B3: > 20% | C3: 13.65% | D3: Tốt
A4: NIM (%) | B4: > 3.0% | C4: 5.64% | D4: Tốt

Sheet 11_Investment_Thesis
A1: Luận điểm chính | B1: Chi tiết nhận định
A2: Lợi thế CASA vượt trội | B2: Hệ sinh thái số hóa giúp huy động dòng vốn rẻ dồi dào, ổn định biên lãi NIM.
A3: Hiệu quả sinh lời cao | B3: Chỉ số ROE và ROA luôn nằm trong nhóm dẫn đầu hệ thống ngân hàng TMCP.

Sheet 12_Summary_Snapshot
A1: Chỉ tiêu | B1: 2021 | C1: 2022 | D1: 2023 | E1: 2024 | F1: 2025 | G1: 2026F | H1: 2027F | I1: 2028F
A2: Thu nhập lãi thuần (NII) | B2: ='04_PnL'!B2 | C2: ='04_PnL'!C2 | D2: ='04_PnL'!D2 | E2: ='04_PnL'!E2 | F2: ='04_PnL'!F2 | G2: ='04_PnL'!G2 | H2: ='04_PnL'!H2 | I2: ='04_PnL'!I2
A3: Tổng thu nhập HĐ (TOI) | B3: ='04_PnL'!B3 | C3: ='04_PnL'!C3 | D3: ='04_PnL'!D3 | E3: ='04_PnL'!E3 | F3: ='04_PnL'!F3 | G3: ='04_PnL'!G3 | H3: ='04_PnL'!H3 | I3: ='04_PnL'!I3
A4: LN trước dự phòng (PPOP) | B4: ='04_PnL'!B4 | C4: ='04_PnL'!C4 | D4: ='04_PnL'!D4 | E4: ='04_PnL'!E4 | F4: ='04_PnL'!F4 | G4: ='04_PnL'!G4 | H4: ='04_PnL'!H4 | I4: ='04_PnL'!I4
A5: LNST (NPAT) | B5: ='04_PnL'!B5 | C5: ='04_PnL'!C5 | D5: ='04_PnL'!D5 | E5: ='04_PnL'!E5 | F5: ='04_PnL'!F5 | G5: ='04_PnL'!G5 | H5: ='04_PnL'!H5 | I5: ='04_PnL'!I5
A6: EPS (VND) | B6: ='04_PnL'!B6 | C6: ='04_PnL'!C6 | D6: ='04_PnL'!D6 | E6: ='04_PnL'!E6 | F6: ='04_PnL'!F6 | G6: ='04_PnL'!G6 | H6: ='04_PnL'!H6 | I6: ='04_PnL'!I6
A7: Tổng tài sản | B7: ='05_Balance_Sheet'!B2 | C7: ='05_Balance_Sheet'!C2 | D7: ='05_Balance_Sheet'!D2 | E7: ='05_Balance_Sheet'!E2 | F7: ='05_Balance_Sheet'!F2 | G7: ='05_Balance_Sheet'!G2 | H7: ='05_Balance_Sheet'!H2 | I7: ='05_Balance_Sheet'!I2
A8: Cho vay khách hàng (Gross) | B8: ='05_Balance_Sheet'!B3 | C8: ='05_Balance_Sheet'!C3 | D8: ='05_Balance_Sheet'!D3 | E8: ='05_Balance_Sheet'!E3 | F8: ='05_Balance_Sheet'!F3 | G8: ='05_Balance_Sheet'!G3 | H8: ='05_Balance_Sheet'!H3 | I8: ='05_Balance_Sheet'!I3
A9: Trái phiếu doanh nghiệp | B9: ='05_Balance_Sheet'!B4 | C9: ='05_Balance_Sheet'!C4 | D9: ='05_Balance_Sheet'!D4 | E9: ='05_Balance_Sheet'!E4 | F9: ='05_Balance_Sheet'!F4 | G9: ='05_Balance_Sheet'!G4 | H9: ='05_Balance_Sheet'!H4 | I9: ='05_Balance_Sheet'!I4
A10: Tiền gửi khách hàng | B10: ='05_Balance_Sheet'!B5 | C10: ='05_Balance_Sheet'!C5 | D10: ='05_Balance_Sheet'!D5 | E10: ='05_Balance_Sheet'!E5 | F10: ='05_Balance_Sheet'!F5 | G10: ='05_Balance_Sheet'!G5 | H10: ='05_Balance_Sheet'!H5 | I10: ='05_Balance_Sheet'!I5
A11: Giấy tờ có giá (Bonds) | B11: ='05_Balance_Sheet'!B6 | C11: ='05_Balance_Sheet'!C6 | D11: ='05_Balance_Sheet'!D6 | E11: ='05_Balance_Sheet'!E6 | F11: ='05_Balance_Sheet'!F6 | G11: ='05_Balance_Sheet'!G6 | H11: ='05_Balance_Sheet'!H6 | I11: ='05_Balance_Sheet'!I6
A12: Tiền gửi Kho bạc NN | B12: ='05_Balance_Sheet'!B7 | C12: ='05_Balance_Sheet'!C7 | D12: ='05_Balance_Sheet'!D7 | E12: ='05_Balance_Sheet'!E7 | F12: ='05_Balance_Sheet'!F7 | G12: ='05_Balance_Sheet'!G7 | H12: ='05_Balance_Sheet'!H7 | I12: ='05_Balance_Sheet'!I7
A13: Tiền gửi ký quỹ (trừ đi) | B13: ='05_Balance_Sheet'!B8 | C13: ='05_Balance_Sheet'!C8 | D13: ='05_Balance_Sheet'!D8 | E13: ='05_Balance_Sheet'!E8 | F13: ='05_Balance_Sheet'!F8 | G13: ='05_Balance_Sheet'!G8 | H13: ='05_Balance_Sheet'!H8 | I13: ='05_Balance_Sheet'!I8
A14: Vốn chuyên dùng (trừ đi) | B14: ='05_Balance_Sheet'!B9 | C14: ='05_Balance_Sheet'!C9 | D14: ='05_Balance_Sheet'!D9 | E14: ='05_Balance_Sheet'!E9 | F14: ='05_Balance_Sheet'!F9 | G14: ='05_Balance_Sheet'!G9 | H14: ='05_Balance_Sheet'!H9 | I14: ='05_Balance_Sheet'!I9
A15: Vốn chủ sở hữu (VCSH) | B15: ='05_Balance_Sheet'!B10 | C15: ='05_Balance_Sheet'!C10 | D15: ='05_Balance_Sheet'!D10 | E15: ='05_Balance_Sheet'!E10 | F15: ='05_Balance_Sheet'!F10 | G15: ='05_Balance_Sheet'!G10 | H15: ='05_Balance_Sheet'!H10 | I15: ='05_Balance_Sheet'!I10

Sheet 13_PE_PB_History
A1: Quỳ | B1: P/E (x) | C1: P/B (x) | D1: EV/EBITDA (x) | E1: Giá
A2: Q3/18 | B2: 7.5885769 | C2: 1.7314874
A3: Q4/18 | B3: 7.255118 | C3: 1.5360935
A4: Q1/19 | B4: 6.6726838 | C4: 1.3715345
A5: Q2/19 | B5: 6.8610047 | C5: 1.2664035
A6: Q3/19 | B6: 7.4928275 | C6: 1.44029
A7: Q4/19 | B7: 6.6045249 | C7: 1.3545975
A8: Q1/20 | B8: 5.9878087 | C8: 1.1290754
A9: Q2/20 | B9: 6.1488397 | C9: 1.2620257
A10: Q3/20 | B10: 6.0109327 | C10: 1.2734379
A11: Q4/20 | B11: 8.2308791 | C11: 1.6734809
A12: Q1/21 | B12: 12.025764 | C12: 2.3016098
A13: Q2/21 | B13: 13.832604 | C13: 2.8056616
... A35: MEDIAN ALL-TIME | B35: 8.3642846 | C35: 1.3412089

Sheet 14_Credit_Funding_Growth
A1: Quý | B1: Tổng Tín dụng (tỷ VND) | C1: Tổng Huy động (tỷ VND) | D1: Tăng trưởng TD so cuối năm trước (%) | E1: Tăng trưởng HĐ so cuối năm trước (%)
A2: Q1/22 | B2: ='05_Balance_Sheet_Quarterly'!B5+'05_Balance_Sheet_Quarterly'!B9 | C2: ='05_Balance_Sheet_Quarterly'!B7+'05_Balance_Sheet_Quarterly'!B10+'05_Balance_Sheet_Quarterly'!B11*0.0-'05_Balance_Sheet_Quarterly'!B12-'05_Balance_Sheet_Quarterly'!B13
A3: Q2/22 | B3: ='05_Balance_Sheet_Quarterly'!C5+'05_Balance_Sheet_Quarterly'!C9 | C3: ='05_Balance_Sheet_Quarterly'!C7+'05_Balance_Sheet_Quarterly'!C10+'05_Balance_Sheet_Quarterly'!C11*0.0-'05_Balance_Sheet_Quarterly'!C12-'05_Balance_Sheet_Quarterly'!C13
A4: Q3/22 | B4: ='05_Balance_Sheet_Quarterly'!D5+'05_Balance_Sheet_Quarterly'!D9 | C4: ='05_Balance_Sheet_Quarterly'!D7+'05_Balance_Sheet_Quarterly'!D10+'05_Balance_Sheet_Quarterly'!D11*0.0-'05_Balance_Sheet_Quarterly'!D12-'05_Balance_Sheet_Quarterly'!D13
A5: Q4/22 | B5: ='05_Balance_Sheet_Quarterly'!E5+'05_Balance_Sheet_Quarterly'!E9 | C5: ='05_Balance_Sheet_Quarterly'!E7+'05_Balance_Sheet_Quarterly'!E10+'05_Balance_Sheet_Quarterly'!E11*0.0-'05_Balance_Sheet_Quarterly'!E12-'05_Balance_Sheet_Quarterly'!E13
A6: Q1/23 | B6: ='05_Balance_Sheet_Quarterly'!F5+'05_Balance_Sheet_Quarterly'!F9 | C6: ='05_Balance_Sheet_Quarterly'!F7+'05_Balance_Sheet_Quarterly'!F10+'05_Balance_Sheet_Quarterly'!F11*0.5-'05_Balance_Sheet_Quarterly'!F12-'05_Balance_Sheet_Quarterly'!F13 | D6: =(B6-B5)/B5 | E6: =(C6-C5)/C5
A7: Q2/23 | B7: ='05_Balance_Sheet_Quarterly'!G5+'05_Balance_Sheet_Quarterly'!G9 | C7: ='05_Balance_Sheet_Quarterly'!G7+'05_Balance_Sheet_Quarterly'!G10+'05_Balance_Sheet_Quarterly'!G11*0.5-'05_Balance_Sheet_Quarterly'!G12-'05_Balance_Sheet_Quarterly'!G13 | D7: =(B7-B5)/B5 | E7: =(C7-C5)/C5
A8: Q3/23 | B8: ='05_Balance_Sheet_Quarterly'!H5+'05_Balance_Sheet_Quarterly'!H9 | C8: ='05_Balance_Sheet_Quarterly'!H7+'05_Balance_Sheet_Quarterly'!H10+'05_Balance_Sheet_Quarterly'!H11*0.5-'05_Balance_Sheet_Quarterly'!H12-'05_Balance_Sheet_Quarterly'!H13 | D8: =(B8-B5)/B5 | E8: =(C8-C5)/C5
A9: Q4/23 | B9: ='05_Balance_Sheet_Quarterly'!I5+'05_Balance_Sheet_Quarterly'!I9 | C9: ='05_Balance_Sheet_Quarterly'!I7+'05_Balance_Sheet_Quarterly'!I10+'05_Balance_Sheet_Quarterly'!I11*0.5-'05_Balance_Sheet_Quarterly'!I12-'05_Balance_Sheet_Quarterly'!I13 | D9: =(B9-B5)/B5 | E9: =(C9-C5)/C5
A10: Q1/24 | B10: ='05_Balance_Sheet_Quarterly'!J5+'05_Balance_Sheet_Quarterly'!J9 | C10: ='05_Balance_Sheet_Quarterly'!J7+'05_Balance_Sheet_Quarterly'!J10+'05_Balance_Sheet_Quarterly'!J11*0.4-'05_Balance_Sheet_Quarterly'!J12-'05_Balance_Sheet_Quarterly'!J13 | D10: =(B10-B9)/B9 | E10: =(C10-C9)/C9
A11: Q2/24 | B11: ='05_Balance_Sheet_Quarterly'!K5+'05_Balance_Sheet_Quarterly'!K9 | C11: ='05_Balance_Sheet_Quarterly'!K7+'05_Balance_Sheet_Quarterly'!K10+'05_Balance_Sheet_Quarterly'!K11*0.4-'05_Balance_Sheet_Quarterly'!K12-'05_Balance_Sheet_Quarterly'!K13 | D11: =(B11-B9)/B9 | E11: =(C11-C9)/C9
A12: Q3/24 | B12: ='05_Balance_Sheet_Quarterly'!L5+'05_Balance_Sheet_Quarterly'!L9 | C12: ='05_Balance_Sheet_Quarterly'!L7+'05_Balance_Sheet_Quarterly'!L10+'05_Balance_Sheet_Quarterly'!L11*0.4-'05_Balance_Sheet_Quarterly'!L12-'05_Balance_Sheet_Quarterly'!L13 | D12: =(B12-B9)/B9 | E12: =(C12-C9)/C9
A13: Q4/24 | B13: ='05_Balance_Sheet_Quarterly'!M5+'05_Balance_Sheet_Quarterly'!M9 | C13: ='05_Balance_Sheet_Quarterly'!M7+'05_Balance_Sheet_Quarterly'!M10+'05_Balance_Sheet_Quarterly'!M11*0.4-'05_Balance_Sheet_Quarterly'!M12-'05_Balance_Sheet_Quarterly'!M13 | D13: =(B13-B9)/B9 | E13: =(C13-C9)/C9
A14: Q1/25 | B14: ='05_Balance_Sheet_Quarterly'!N5+'05_Balance_Sheet_Quarterly'!N9 | C14: ='05_Balance_Sheet_Quarterly'!N7+'05_Balance_Sheet_Quarterly'!N10+'05_Balance_Sheet_Quarterly'!N11*0.2-'05_Balance_Sheet_Quarterly'!N12-'05_Balance_Sheet_Quarterly'!N13 | D14: =(B14-B13)/B13 | E14: =(C14-C13)/C13
A15: Q2/25 | B15: ='05_Balance_Sheet_Quarterly'!O5+'05_Balance_Sheet_Quarterly'!O9 | C15: ='05_Balance_Sheet_Quarterly'!O7+'05_Balance_Sheet_Quarterly'!O10+'05_Balance_Sheet_Quarterly'!O11*0.2-'05_Balance_Sheet_Quarterly'!O12-'05_Balance_Sheet_Quarterly'!O13 | D15: =(B15-B13)/B13 | E15: =(C15-C13)/C13
A16: Q3/25 | B16: ='05_Balance_Sheet_Quarterly'!P5+'05_Balance_Sheet_Quarterly'!P9 | C16: ='05_Balance_Sheet_Quarterly'!P7+'05_Balance_Sheet_Quarterly'!P10+'05_Balance_Sheet_Quarterly'!P11*0.2-'05_Balance_Sheet_Quarterly'!P12-'05_Balance_Sheet_Quarterly'!P13 | D16: =(B16-B13)/B13 | E16: =(C16-C13)/C13
A17: Q4/25 | B17: ='05_Balance_Sheet_Quarterly'!Q5+'05_Balance_Sheet_Quarterly'!Q9 | C17: ='05_Balance_Sheet_Quarterly'!Q7+'05_Balance_Sheet_Quarterly'!Q10+'05_Balance_Sheet_Quarterly'!Q11*0.2-'05_Balance_Sheet_Quarterly'!Q12-'05_Balance_Sheet_Quarterly'!Q13 | D17: =(B17-B13)/B13 | E17: =(C17-C13)/C13
A18: Q1/26 | B18: ='05_Balance_Sheet_Quarterly'!R5+'05_Balance_Sheet_Quarterly'!R9 | C18: ='05_Balance_Sheet_Quarterly'!R7+'05_Balance_Sheet_Quarterly'!R10+'05_Balance_Sheet_Quarterly'!R11*0.2-'05_Balance_Sheet_Quarterly'!R12-'05_Balance_Sheet_Quarterly'!R13 | D18: =(B18-B17)/B17 | E18: =(C18-C17)/C17
A19: Q2/26 | B19: ='05_Balance_Sheet_Quarterly'!S5+'05_Balance_Sheet_Quarterly'!S9 | C19: ='05_Balance_Sheet_Quarterly'!S7+'05_Balance_Sheet_Quarterly'!S10+'05_Balance_Sheet_Quarterly'!S11*0.2-'05_Balance_Sheet_Quarterly'!S12-'05_Balance_Sheet_Quarterly'!S13 | D19: =(B19-B17)/B17 | E19: =(C19-C17)/C17

Sheet 15_Peer_Benchmark
A1: Ngân hàng | B1: NPL (%) | C1: NIM (%) | D1: CASA (%) | E1: ROE (%) | F1: CIR (%) | G1: P/B (x) | H1: Tăng trưởng tín dụng (%) | I1: Vốn hóa (tỷ VND)
A2: Trung bình ngành | B2: 2.3422222 | C2: 4.4505556 | D2: 16.706111 | E2: 16.482778 | F2: 32.677778 | G2: 1.3588889 | H2: 5.5066667 | I2: -
A3: VCB — Vietcombank | B3: 0.0062 | C3: 0.0443 | D3: 0.3235 | E3: 0.2342 | F3: 0.3204 | G3: 1.95 | H3: 0.0005 | I3: 484629.16
A4: BID — BIDV | B4: 0.0185 | C4: 0.0289 | D4: 0.2012 | E4: 0.1669 | F4: 0.3166 | G4: 1.41 | H4: 0.0312 | I4: 280016.26
A5: CTG — VietinBank | B5: 0.0122 | C5: 0.0403 | D5: 0.2272 | E5: 0.2354 | F5: 0.2409 | G5: 1.19 | H5: 0.0326 | I5: 239221.89
A6: TCB — Techcombank | B6: 0.011 | C6: 0.0515 | D6: 0.3381 | E6: 0.1635 | F6: 0.3092 | G6: 1.2 | H6: 0.0639 | I6: 226051.07
A7: MBB — MBBank | B7: 0.0147 | C7: 0.0558 | D7: 0.3362 | E7: 0.2155 | F7: 0.2754 | G7: 1.3 | H7: 0.095 | I7: 203388.75
A8: ACB — ACB | B8: 0.0104 | C8: 0.0422 | D8: 0.2003 | E8: 0.1729 | F8: 0.297 | G8: 1.3 | H8: 0.052 | I8: 129148.39
A9: VIB — VIB | B9: 0.0296 | C9: 0.0446 | D9: 0.1176 | E9: 0.1593 | F9: 0.3174 | G9: 1.06 | H9: 0.0279 | I9: 50719.685
A10: HDB — HDBank | B10: 0.0283 | C10: 0.0599 | D10: 0.1081 | E10: 0.2569 | F10: 0.2411 | G10: 1.52 | H10: 0.0952 | I10: 136894.31
A11: STB — Sacombank | B11: 0.0788 | C11: 0.041 | D11: 0.1643 | E11: 0.0858 | F11: 0.2839 | G11: 2.3 | H11: 0.0066 | I11: 144407.52
A12: VPB — VPBank | B12: 0.0334 | C12: 0.0631 | D12: 0.1149 | E12: 0.1836 | F12: 0.1965 | G12: 1.13 | H12: 0.1163 | I12: 216596.11
A13: TPB — TPBank | B13: 0.0188 | C13: 0.0435 | D13: 0.1832 | E13: 0.1526 | F13: 0.3933 | G13: 0.81 | H13: 0.0703 | I13: 40362.382
A14: MSB — MSB | B14: 0.0256 | C14: 0.0528 | D14: 0.2191 | E14: 0.1106 | F14: 0.3902 | G14: 1.09 | H14: 0.074 | I14: 49233.6
... A20: NAB — NamABank | B20: 0.0149 | C20: 0.0411 | D20: 0.0527 | E20: 0.1869 | F20: 0.4166 | G20: 0.94 | H20: 0.088 | I20: 24394.692

Sheet 16_ALM_LaiSuat_ThanhKhoan
A1: PHÂN TÍCH RỦI RO LÃI SUẤT & THANH KHOẢN (ALM)
A2: Chưa đọc được 2 bảng khe hở lãi suất/thanh khoản từ BCTC kỳ này (thiếu OCR hoặc BCTC quý không soát xét, rút gọn thuyết minh) — chỉ có cơ cấu bảng cân đối bên dưới, tính thẳng từ số liệu Vietcap, không cần OCR.
A4: A. RỦI RO LÃI SUẤT — Khe hở nhạy cảm lãi suất theo kỳ hạn
