Workbook

Sheet 00_COE
A1: CHI PHÍ VỐN CSH (COE) — MÔ HÌNH CAPM
A3: Tham số | B3: Giá trị
A4: Rf — Lãi suất phi rủi ro | B4: 0.045
A5: β — Hệ số Beta | B5: 0.88
A6: ERP — Phần bù rủi ro vốn | B6: 0.07
A7: α — Phần bù rủi ro đặc thù (Frontier/Bank) | B7: 0.02
A9: COE = Rf + β × ERP + α | B9: =B4+B5*B6+B7

Sheet 01_Cover
B2: PHÂN TÍCH CỔ PHIẾU NGÂN HÀNG: HDB
B3: Ngân hàng Thương mại Cổ phần Phát Triển Thành phố Hồ Chí Minh
B5: Giá hiện tại (VND): | C5: ='02_Assumptions'!B2
B6: Giá mục tiêu (VND): | C6: ='07_Valuation'!B21
B7: Upside: | C7: ='07_Valuation'!B23
B8: Khuyến nghị: | C8: =IF('07_Valuation'!B23>0.15,"MUA",IF('07_Valuation'!B23<-0.05,"BÁN","THEO DÕI"))

Sheet 02_Assumptions
A1: Chỉ tiêu | B1: 2021 | C1: 2022 | D1: 2023 | E1: 2024 | F1: 2025 | G1: 2026F | H1: 2027F | I1: 2028F
A2: Giá cổ phiếu (VND) | B2: 25400
A3: Số lượng CP lưu hành | B3: 5132772600
A4: Tín dụng tăng trưởng (%) | G4: 0.14 | H4: 0.13 | I4: 0.12
A5: Huy động tăng trưởng (%) | G5: 0.12 | H5: 0.11 | I5: 0.1
A6: NIM (%) | B6: 0.0413 | C6: 0.0508 | D6: 0.0495 | E6: 0.0541 | F6: 0.0469 | G6: 0.0492 | H6: 0.0507 | I6: 0.0516
A7: CIR (%) | B7: 0.3809 | C7: 0.3929 | D7: 0.3456 | E7: 0.352 | F7: 0.2717 | G7: 0.33 | H7: 0.32 | I7: 0.32
A8: CoC - Credit Cost (%) | B8: 0.0115 | C8: 0.0133 | D8: 0.0142 | E8: 0.0137 | F8: 0.02 | G8: 0.019 | H8: 0.018 | I8: 0.017
A9: NPL ratio (%) | B9: 0.0167 | C9: 0.0169 | D9: 0.0182 | E9: 0.0196 | F9: 0.0247 | G9: 0.0235 | H9: 0.0222 | I9: 0.021
A10: CASA ratio (%) | B10: 0.1305 | C10: 0.103 | D10: 0.1088 | E10: 0.1177 | F10: 0.121 | G10: 0.131 | H10: 0.141 | I10: 0.151
A11: Tăng trưởng non-TOI (%) | G11: 0.15 | H11: 0.15 | I11: 0.14
A12: Chi phí vốn CSH (COE) | G12: 0.1266 | H12: 0.1266 | I12: 0.1266
A13: Tăng trưởng dài hạn (g) | I13: 0.03
A14: Thuế suất (%) | G14: 0.2 | H14: 0.2 | I14: 0.2
A15: P/B mục tiêu (x) | G15: 1.6648451 | H15: 1.6648451 | I15: 1.6648451

Sheet 03_Income_Model
A1: Chỉ tiêu | B1: 2021 | C1: 2022 | D1: 2023 | E1: 2024 | F1: 2025 | G1: 2026F | H1: 2027F | I1: 2028F
A2: IEA bình quân (tỷ) | B2: 336508.49 | C2: 354698.07 | D2: 448568.16 | E2: 570496.04 | F2: 740461.2 | G2: 920350.64 | H2: 1035113.6 | I2: 1153858.7
A3: IEA tăng trưởng (%) | C3: 0.1081 | D3: 0.4059 | E3: 0.1764 | F3: 0.4012 | G3: 0.13 | H3: 0.12 | I3: 0.11
A4: NIM (%) | B4: 0.0413 | C4: 0.0508 | D4: 0.0495 | E4: 0.0541 | F4: 0.0469 | G4: 0.0492 | H4: 0.0507 | I4: 0.0516
A5: NII (tỷ) | B5: 13890.777 | C5: 18011.568 | D5: 22183.974 | E5: 30857.076 | F5: 34746.19 | G5: =G2*'02_Assumptions'!G6 | H5: =H2*'02_Assumptions'!H6 | I5: =I2*'02_Assumptions'!I6
A6: Thu nhập dịch vụ | B6: 1927.438 | C6: 2956.818 | D6: 2187.802 | E6: 1416.578 | F6: 4126.04
A7: Thu nhập ngoại hối | B7: 179.248 | C7: 134.237 | D7: 564.703 | E7: 843.813 | F7: 1272.182
A8: Thu nhập CK đầu tư | B8: 578.145 | C8: 329.606 | D8: 1208.728 | E8: 137.182 | F8: 1495.37
A9: Thu nhập khác | B9: 182.637 | C9: 528.09 | D9: 259.153 | E9: 705.871 | F9: 736.618
A10: Tổng thu nhập ngoài lãi | B10: 2867.468 | C10: 3955.536 | D10: 4229.711 | E10: 3175.108 | F10: 7949.682 | G10: 9142.1343 | H10: 10513.454 | I10: 11985.338
A11: Tổng thu nhập HĐ - TOI | B11: 16758.245 | C11: 21967.104 | D11: 26413.685 | E11: 34032.184 | F11: 42695.872 | G11: =G5+G10 | H11: =H5+H10 | I11: =I5+I10
A12: NII/TOI (%) | B12: 82.89 | C12: 81.99 | D12: 83.99 | E12: 90.67 | F12: 81.38
A13: Chi phí HĐ - OPEX | B13: 6382.768 | C13: 8630.709 | D13: 9129.202 | E13: 11980.755 | F13: 11600.987 | G13: =G11*'02_Assumptions'!G7 | H13: =H11*'02_Assumptions'!H7 | I13: =I11*'02_Assumptions'!I7
A14: PPOP - LN trước dự phòng | B14: 10375.477 | C14: 13336.395 | D14: 17284.483 | E14: 22051.429 | F14: 31094.885 | G14: =G11-G13 | H14: =H11-H13 | I14: =I11-I13
A15: PPOP/TOI (%) | B15: 61.91 | C15: 60.71 | D15: 65.44 | E15: 64.8 | F15: 72.83
A16: Dự phòng tín dụng | B16: 2305.86 | C16: 3068.339 | D16: 4267.751 | E16: 5321.434 | F16: 9748.394 | G16: =(('05_Balance_Sheet'!F3+'05_Balance_Sheet'!G3)/2)*'02_Assumptions'!G8 | H16: =(('05_Balance_Sheet'!G3+'05_Balance_Sheet'!H3)/2)*'02_Assumptions'!H8 | I16: =(('05_Balance_Sheet'!H3+'05_Balance_Sheet'!I3)/2)*'02_Assumptions'!I8
A17: LN trước thuế - PBT | B17: 8069.617 | C17: 10268.056 | D17: 13016.732 | E17: 16729.995 | F17: 21346.491 | G17: =G14-G16 | H17: =H14-H16 | I17: =I14-I16

Sheet 04_PnL_Quarterly
A1: Chỉ tiêu | B1: Q2/2023 | C1: Q3/2023 | D1: Q4/2023 | E1: Q1/2024 | F1: Q2/2024 | G1: Q3/2024 | H1: Q4/2024 | I1: Q1/2025 | J1: Q2/2025 | K1: Q3/2025 | L1: Q4/2025 | M1: Q1/2026
A2: Thu nhập lãi thuần - NII | B2: 4954.515 | C2: 4916.148 | D2: 7472.503 | E2: 7160.35 | F2: 7719.878 | G2: 7773.445 | H2: 8203.403 | I2: 7408.1 | J2: 9819.158 | K2: 7763.322 | L2: 9755.61 | M2: 8483.022
A3: Thu nhập ngoài lãi | B3: 1458.876 | C3: 1169.08 | D3: 785.156 | E3: 591.715 | F3: 573.138 | G3: 761.527 | H3: 1248.728 | I3: 1796.453 | J3: 1816.729 | K3: 1753.16 | L3: 2583.34 | M3: 1469.82
A4: Tổng thu nhập HĐ - TOI | B4: 6413.391 | C4: 6085.228 | D4: 8257.659 | E4: 7752.065 | F4: 8293.016 | G4: 8534.972 | H4: 9452.131 | I4: 9204.553 | J4: 11635.887 | K4: 9516.482 | L4: 12338.95 | M4: 9952.842
A5: Chi phí hoạt động - OPEX | B5: 2238.587 | C5: 2301.873 | D5: 2630.124 | E5: 2454.639 | F5: 3029.78 | G5: 2951.077 | H5: 3545.259 | I5: 2524.523 | J5: 2782.029 | K5: 2487.98 | L5: 3806.455 | M5: 2587.015
A6: LN trước dự phòng - PPOP | B6: 4174.804 | C6: 3783.355 | D6: 5627.535 | E6: 5297.426 | F6: 5263.236 | G6: 5583.895 | H6: 5906.872 | I6: 6680.03 | J6: 8853.858 | K6: 7028.502 | L6: 8532.495 | M6: 7365.827
A7: Dự phòng tín dụng | B7: 1433.167 | C7: 636.089 | D7: 1242.405 | E7: 1269.851 | F7: 1126.231 | G7: 1093.488 | H7: 1831.864 | I7: 1324.795 | J7: 4141.072 | K7: 2294.002 | L7: 1988.525 | M7: 1258.493
A8: LN trước thuế - PBT | B8: 2741.637 | C8: 3147.266 | D8: 4385.13 | E8: 4027.575 | F8: 4137.005 | G8: 4490.407 | H8: 4075.008 | I8: 5355.235 | J8: 4712.786 | K8: 4734.5 | L8: 6543.97 | M8: 6107.334
A9: LN sau thuế - NPAT | B9: 2179.528 | C9: 2515.158 | D9: 3447.615 | E9: 3213.172 | F9: 3251.852 | G9: 3545.636 | H9: 3236.988 | I9: 4357.672 | J9: 3676.059 | K9: 3798.817 | L9: 5241.074 | M9: 4902.14

Sheet 04_PnL
A1: Chỉ tiêu | B1: 2021 | C1: 2022 | D1: 2023 | E1: 2024 | F1: 2025 | G1: 2026F | H1: 2027F | I1: 2028F
A2: Thu nhập lãi thuần (NII) | B2: 13890.777 | C2: 18011.568 | D2: 22183.974 | E2: 30857.076 | F2: 34746.19 | G2: ='03_Income_Model'!G5 | H2: ='03_Income_Model'!H5 | I2: ='03_Income_Model'!I5
A3: Tổng thu nhập hoạt động (TOI) | B3: 16758.245 | C3: 21967.104 | D3: 26413.685 | E3: 34032.184 | F3: 42695.872 | G3: =SUM(G2+'03_Income_Model'!G10) | H3: =SUM(H2+'03_Income_Model'!H10) | I3: =SUM(I2+'03_Income_Model'!I10)
A4: Lợi nhuận trước dự phòng (PPOP) | B4: 10375.477 | C4: 13336.395 | D4: 17284.483 | E4: 22051.429 | F4: 31094.885 | G4: ='03_Income_Model'!G14 | H4: ='03_Income_Model'!H14 | I4: ='03_Income_Model'!I14
A5: LNST (NPAT) | B5: 6453.499 | C5: 8209.47 | D5: 10336.013 | E5: 13247.648 | F5: 17073.622 | G5: =('03_Income_Model'!G17)-MAX(('03_Income_Model'!G17)*'02_Assumptions'!G14,0) | H5: =('03_Income_Model'!H17)-MAX(('03_Income_Model'!H17)*'02_Assumptions'!H14,0) | I5: =('03_Income_Model'!I17)-MAX(('03_Income_Model'!I17)*'02_Assumptions'!I14,0)
A6: EPS (VND) | B6: 1257.3125 | C6: 1599.4221 | D6: 2013.729 | E6: 2580.9926 | F6: 3326.3936 | G6: =G5*1000000000/'02_Assumptions'!$B$3 | H6: =H5*1000000000/'02_Assumptions'!$B$3 | I6: =I5*1000000000/'02_Assumptions'!$B$3

Sheet 05_Balance_Sheet_Quarterly
A1: Chỉ tiêu | B1: Q2/2023 | C1: Q3/2023 | D1: Q4/2023 | E1: Q1/2024 | F1: Q2/2024 | G1: Q3/2024 | H1: Q4/2024 | I1: Q1/2025 | J1: Q2/2025 | K1: Q3/2025 | L1: Q4/2025 | M1: Q1/2026
A2: Tổng tài sản | B2: 483935.82 | C2: 508263.25 | D2: 602314.86 | E2: 602551.57 | F2: 624443.5 | G2: 629569.11 | H2: 697366.46 | I2: 711310.76 | J2: 784096.29 | K2: 781937.37 | L2: 931103.94 | M2: 984216.21
A3: Tiền mặt & NHNN | B3: 2902.517 | C3: 2765.559 | D3: 2810.044 | E3: 2891.213 | F3: 3102.598 | G3: 3127.639 | H3: 3105.355 | I3: 3597.997 | J3: 3944.656 | K3: 3679.667 | L3: 4126.643 | M3: 4870.562
A4: TG các TCTD khác | B4: 87190.858 | C4: 55427.3 | D4: 96514.863 | E4: 87659.83 | F4: 83923.363 | G4: 98656.083 | H4: 101600.25 | I4: 126666.26 | J4: 132104.67 | K4: 153845.28 | L4: 184262.21 | M4: 203790.57
A5: Cho vay khách hàng | B5: 283565.06 | C5: 288136.81 | D5: 339349.84 | E5: 358835.15 | F5: 381419.72 | G5: 393739.71 | H5: 436606.24 | I5: 440468.26 | J5: 502451.96 | K5: 482446.82 | L5: 539071.33 | M5: 593322.8
A6: CK đầu tư | B6: 44652.422 | C6: 51041.447 | D6: 44092.289 | E6: 55248.147 | F6: 60762.059 | G6: 34611.149 | H6: 48751.284 | I6: 49726.466 | J6: 71362.33 | K6: 63385.953 | L6: 76811.704 | M6: 88955.221
A7: Tiền gửi khách hàng | B7: 309645.14 | C7: 341712.98 | D7: 370777.89 | E7: 378789.08 | F7: 386573.34 | G7: 397018.67 | H7: 437505.16 | I7: 465321.21 | J7: 478700.23 | K7: 487862.98 | L7: 560714.28 | M7: 621548.94
A8: Vốn chủ sở hữu | B8: 40476.748 | C8: 43025.581 | D8: 46400.322 | E8: 49700.25 | F8: 52825.71 | G8: 53583.975 | H8: 56657.261 | I8: 61032.537 | J8: 64626.363 | K8: 68407.053 | L8: 78285.522 | M8: 83186.008

Sheet 05_Balance_Sheet
A1: Chỉ tiêu | B1: 2021 | C1: 2022 | D1: 2023 | E1: 2024 | F1: 2025 | G1: 2026F | H1: 2027F | I1: 2028F
A2: Tổng tài sản | B2: 374611.57 | C2: 416273.02 | D2: 602314.86 | E2: 697366.46 | F2: 931103.94 | G2: =SUM(G3:G6)+G7-G8-G9+G10 | H2: =SUM(H3:H6)+H7-H8-H9+H10 | I2: =SUM(I3:I6)+I7-I8-I9+I10
A3: Cho vay khách hàng (Gross) | B3: 200758.83 | C3: 260754.81 | D3: 339349.84 | E3: 436606.24 | F3: 539071.33 | G3: =F3*(1+'02_Assumptions'!G4) | H3: =G3*(1+'02_Assumptions'!H4) | I3: =H3*(1+'02_Assumptions'!I4)
A4: Trái phiếu doanh nghiệp | B4: 24879.776 | C4: 25793.635 | D4: 93389.645 | E4: 138247.9 | F4: 175459.66 | G4: =F4*(1+'02_Assumptions'!G4) | H4: =G4*(1+'02_Assumptions'!H4) | I4: =H4*(1+'02_Assumptions'!I4)
A5: Tiền gửi khách hàng | B5: 183283.12 | C5: 215797.17 | D5: 370777.89 | E5: 437505.16 | F5: 560714.28 | G5: =F5*(1+'02_Assumptions'!G5) | H5: =G5*(1+'02_Assumptions'!H5) | I5: =H5*(1+'02_Assumptions'!I5)
A6: Giấy tờ có giá phát hành (Bonds) | B6: 42756.113 | C6: 44161.64 | D6: 50938.148 | E6: 81349.744 | F6: 87434.265 | G6: =F6*1.02 | H6: =G6*1.02 | I6: =H6*1.02
A7: Tiền gửi Kho bạc Nhà nước | B7: 25507.511 | C7: 50949.728 | D7: 57835.226 | E7: 56059.007 | F7: 51095.331 | G7: =F7*(1+'02_Assumptions'!G5) | H7: =G7*(1+'02_Assumptions'!H5) | I7: =H7*(1+'02_Assumptions'!I5)
A8: Tiền gửi ký quỹ (trừ đi) | B8: 3306.15 | C8: 23377.548 | D8: 2444.773 | E8: 3798.848 | F8: 12520.928 | G8: =F8*(1+'02_Assumptions'!G5) | H8: =G8*(1+'02_Assumptions'!H5) | I8: =H8*(1+'02_Assumptions'!I5)
A9: Vốn chuyên dùng (trừ đi) | B9: 2936.864 | C9: 2860.155 | D9: 2811.129 | E9: 2788.443 | F9: 2721.952 | G9: =F9*1.02 | H9: =G9*1.02 | I9: =H9*1.02
A10: Vốn chủ sở hữu (VCSH) | B10: 30790.113 | C10: 38994.886 | D10: 46400.322 | E10: 56657.261 | F10: 78285.522 | G10: =F10+'04_PnL'!G5*0.7 | H10: =G10+'04_PnL'!H5*0.7 | I10: =H10+'04_PnL'!I5*0.7

Sheet 06_Ratios_Quarterly
A1: Chỉ tiêu | B1: Q2/2023 | C1: Q3/2023 | D1: Q4/2023 | E1: Q1/2024 | F1: Q2/2024 | G1: Q3/2024 | H1: Q4/2024 | I1: Q1/2025 | J1: Q2/2025 | K1: Q3/2025 | L1: Q4/2025 | M1: Q1/2026
A2: NIM — năm hóa (%) | B2: =('04_PnL_Quarterly'!B2*4/'05_Balance_Sheet_Quarterly'!B4)*100 | C2: =('04_PnL_Quarterly'!C2*4/'05_Balance_Sheet_Quarterly'!C4)*100 | D2: =('04_PnL_Quarterly'!D2*4/'05_Balance_Sheet_Quarterly'!D4)*100 | E2: =('04_PnL_Quarterly'!E2*4/'05_Balance_Sheet_Quarterly'!E4)*100 | F2: =('04_PnL_Quarterly'!F2*4/'05_Balance_Sheet_Quarterly'!F4)*100 | G2: =('04_PnL_Quarterly'!G2*4/'05_Balance_Sheet_Quarterly'!G4)*100 | H2: =('04_PnL_Quarterly'!H2*4/'05_Balance_Sheet_Quarterly'!H4)*100 | I2: =('04_PnL_Quarterly'!I2*4/'05_Balance_Sheet_Quarterly'!I4)*100 | ... M2: =('04_PnL_Quarterly'!M2*4/'05_Balance_Sheet_Quarterly'!M4)*100
A3: ROE — năm hóa (%) | B3: =('04_PnL_Quarterly'!B8*4/'05_Balance_Sheet_Quarterly'!B7)*100 | C3: =('04_PnL_Quarterly'!C8*4/'05_Balance_Sheet_Quarterly'!C7)*100 | D3: =('04_PnL_Quarterly'!D8*4/'05_Balance_Sheet_Quarterly'!D7)*100 | E3: =('04_PnL_Quarterly'!E8*4/'05_Balance_Sheet_Quarterly'!E7)*100 | F3: =('04_PnL_Quarterly'!F8*4/'05_Balance_Sheet_Quarterly'!F7)*100 | G3: =('04_PnL_Quarterly'!G8*4/'05_Balance_Sheet_Quarterly'!G7)*100 | H3: =('04_PnL_Quarterly'!H8*4/'05_Balance_Sheet_Quarterly'!H7)*100 | I3: =('04_PnL_Quarterly'!I8*4/'05_Balance_Sheet_Quarterly'!I7)*100 | ... M3: =('04_PnL_Quarterly'!M8*4/'05_Balance_Sheet_Quarterly'!M7)*100
A4: LDR (%) | B4: =('05_Balance_Sheet_Quarterly'!B4/'05_Balance_Sheet_Quarterly'!B6)*100 | C4: =('05_Balance_Sheet_Quarterly'!C4/'05_Balance_Sheet_Quarterly'!C6)*100 | D4: =('05_Balance_Sheet_Quarterly'!D4/'05_Balance_Sheet_Quarterly'!D6)*100 | E4: =('05_Balance_Sheet_Quarterly'!E4/'05_Balance_Sheet_Quarterly'!E6)*100 | F4: =('05_Balance_Sheet_Quarterly'!F4/'05_Balance_Sheet_Quarterly'!F6)*100 | G4: =('05_Balance_Sheet_Quarterly'!G4/'05_Balance_Sheet_Quarterly'!G6)*100 | H4: =('05_Balance_Sheet_Quarterly'!H4/'05_Balance_Sheet_Quarterly'!H6)*100 | I4: =('05_Balance_Sheet_Quarterly'!I4/'05_Balance_Sheet_Quarterly'!I6)*100 | ... M4: =('05_Balance_Sheet_Quarterly'!M4/'05_Balance_Sheet_Quarterly'!M6)*100

Sheet 06_Ratios
A1: Chỉ tiêu | B1: 2021 | C1: 2022 | D1: 2023 | E1: 2024 | F1: 2025 | G1: 2026F | H1: 2027F | I1: 2028F
A2: NIM (%) | B2: 0.0413 | C2: 0.0508 | D2: 0.0495 | E2: 0.0541 | F2: 0.0469 | G2: 0.0492 | H2: 0.0507 | I2: 0.0516
A3: CIR (%) | B3: 0.3809 | C3: 0.3929 | D3: 0.3456 | E3: 0.352 | F3: 0.2717 | G3: 0.33 | H3: 0.32 | I3: 0.32
A4: ROE (%) | B4: 0.2096 | C4: 0.2353 | D4: 0.2421 | E4: 0.2571 | F4: 0.253 | G4: ='04_PnL'!G5/AVERAGE('05_Balance_Sheet'!F10,'05_Balance_Sheet'!G10) | H4: ='04_PnL'!H5/AVERAGE('05_Balance_Sheet'!G10,'05_Balance_Sheet'!H10) | I4: ='04_PnL'!I5/AVERAGE('05_Balance_Sheet'!H10,'05_Balance_Sheet'!I10)
A5: ROA (%) | B5: 0.0172 | C5: 0.0197 | D5: 0.0172 | E5: 0.019 | F5: 0.0183 | G5: ='04_PnL'!G5/AVERAGE('05_Balance_Sheet'!F2,'05_Balance_Sheet'!G2) | H5: ='04_PnL'!H5/AVERAGE('05_Balance_Sheet'!G2,'05_Balance_Sheet'!H2) | I5: ='04_PnL'!I5/AVERAGE('05_Balance_Sheet'!H2,'05_Balance_Sheet'!I2)
A6: LDR — điều chỉnh (%) | B6: 1.0266 | C6: 1.226 | D6: 0.9909 | E6: 1.064 | F6: 1.0768 | G6: =SUM('05_Balance_Sheet'!G3:G4)/(SUM('05_Balance_Sheet'!G5:G6)+'05_Balance_Sheet'!G7*0.8-'05_Balance_Sheet'!G8-'05_Balance_Sheet'!G9) | H6: =SUM('05_Balance_Sheet'!H3:H4)/(SUM('05_Balance_Sheet'!H5:H6)+'05_Balance_Sheet'!H7*0.8-'05_Balance_Sheet'!H8-'05_Balance_Sheet'!H9) | I6: =SUM('05_Balance_Sheet'!I3:I4)/(SUM('05_Balance_Sheet'!I5:I6)+'05_Balance_Sheet'!I7*0.8-'05_Balance_Sheet'!I8-'05_Balance_Sheet'!I9)
A7: NPL (%) | B7: 0.0167 | C7: 0.0169 | D7: 0.0182 | E7: 0.0196 | F7: 0.0247 | G7: 0.0235 | H7: 0.0222 | I7: 0.021
A8: CoC — Credit Cost (%) | B8: 0.0115 | C8: 0.0133 | D8: 0.0142 | E8: 0.0137 | F8: 0.02 | G8: 0.019 | H8: 0.018 | I8: 0.017
A9: CASA ratio (%) | B9: 0.1305 | C9: 0.103 | D9: 0.1088 | E9: 0.1177 | F9: 0.121 | G9: 0.131 | H9: 0.141 | I9: 0.151

Sheet 07_Valuation
A1: PHƯƠNG PHÁP ĐỊNH GIÁ
A2: Chi phí vốn CSH (COE) | B2: ='00_COE'!B9
A3: Tăng trưởng dài hạn (g) | B3: 0.03
A5: RESIDUAL INCOME MODEL
A6: BV/share hiện tại (VND) | B6: ='05_Balance_Sheet'!F10*1000000000/'02_Assumptions'!$B$3
A7: PV của RI 3 năm (VND) | B7: =SUM(B31:D31)
A8: PV của Continuing Value (VND) | B8: =((D29*(1+B3)/(B2-B3))*D30)*0.5
A9: GIÁ TRỊ RI (VND) | B9: =B6+B7+B8
A11: P/B MULTIPLE — 3 mức phân phối lịch sử
A12: P/B hiện tại (x) | B12: ='02_Assumptions'!B2/B6
A13: P/B hấp dẫn (x) — MUA | B13: =PERCENTILE('13_PE_PB_History'!C6:C17, 0.25) | C13: Median P/B nửa dưới (vùng mua hấp dẫn)
A14: P/B median all-time (x) — FAIR VALUE | B14: =MEDIAN('13_PE_PB_History'!C6:C17) | C14: Median PB toàn bộ lịch sử
A15: P/B chốt lời (x) — BÁN / CHỐT LỜI | B15: =PERCENTILE('13_PE_PB_History'!C6:C17, 0.75) | C15: Median P/B nửa trên (vùng chốt lời)
A16: BV/share tương lai (2026F) | B16: =B6+B26
A17: GIÁ TRỊ P/B (VND) | B17: =B14*B16
A19: WEIGHTED TARGET PRICE
A20: Trong số: 50% RI + 50% P/B
A21: Target Price (VND) | B21: =B9*0.5+B17*0.5
A22: Giá hiện tại (VND) | B22: ='02_Assumptions'!B2
A23: UPSIDE (%) | B23: =B21/B22-1
A25: --- RI DETAIL ---
A26: EPS (VND) | B26: ='04_PnL'!G6 | C26: ='04_PnL'!H6 | D26: ='04_PnL'!I6
A27: BVPS đầu kỳ (VND) | B27: =B6 | C27: =B27+B26 | D27: =C27+C26
A28: Capital Charge (VND) | B28: =B27*'07_Valuation'!$B$2 | C28: =C27*'07_Valuation'!$B$2 | D28: =D27*'07_Valuation'!$B$2
A29: Residual Income (VND) | B29: =B26-B28 | C29: =C26-C28 | D29: =D26-D28
A30: Discount Factor | B30: =1/(1+'07_Valuation'!$B$2)^1 | C30: =1/(1+'07_Valuation'!$B$2)^2 | D30: =1/(1+'07_Valuation'!$B$2)^3
A31: PV of RI | B31: =B29*B30 | C31: =C29*C30 | D31: =D29*D30

Sheet 08_Sensitivity
A1: Độ nhạy: Giá trị RI theo COE × g (5×5)
A2: COE \ g | B2: 0.01 | C2: 0.02 | D2: 0.03 | E2: 0.04 | F2: 0.05
A3: 0.08 | B3: 36052.323 | C3: 38688.868 | D3: 42380.031 | E3: 47916.775 | F3: 57144.681
A4: 0.1 | B4: 31929.923 | C4: 33412.489 | D4: 35318.646 | E4: 37860.188 | F4: 41418.346
A5: 0.12 | B5: 29275.351 | C5: 30211.41 | D5: 31355.482 | E5: 32785.572 | F5: 34624.259
A6: 0.14 | B6: 27413.51 | C6: 28050.595 | D6: 28803.514 | E6: 29707.017 | F6: 30811.298
A7: 0.16 | B7: 26029.142 | C7: 26486.227 | D7: 27013.632 | E7: 27628.938 | F7: 28356.119

Sheet 09_PESTLE
A1: Nhân tố | B1: Nội dung | C1: Tác động | D1: Mức độ
A2: Chính trị (Political) | B2: Môi trường chính trị ổn định, NHNN điều hành linh hoạt hỗ trợ tăng trưởng tín dụng. | C2: Tích cực | D2: Cao
A3: Kinh tế (Economic) | B3: GDP tăng trưởng 6–7%, nhu cầu vốn sản xuất–tiêu dùng cao, lãi suất huy động giảm dần. | C3: Tích cực | D3: Cao
A4: Xã hội (Social) | B4: Tầng lớp trung lưu mở rộng, thanh toán không tiền mặt tăng mạnh thúc đẩy CASA và phí dịch vụ. | C4: Tích cực | D4: Trung bình
A5: Công nghệ (Technological) | B5: Chuyển đổi số banking (mobile/open banking) giảm CIR, tăng CASA và cross-sell sản phẩm. | C5: Tích cực | D5: Cao
A6: Pháp lý (Legal) | B6: Thông tư 06/2024 siết TPDN, Basel II/III nâng chuẩn CAR — cần theo dõi áp lực pháp lý. | C6: Trung tính | D6: Trung bình
A7: Môi trường (Environmental) | B7: ESG lending ngày càng được yêu cầu; rủi ro tín dụng BĐS liên quan biến đổi khí hậu tăng. | C7: Tiêu cực | D7: Thấp

Sheet 10_Leading_Indicators
A1: Chỉ số | B1: Ngưỡng tích cực | C1: Giá trị hiện tại | D1: Trạng thái
A2: NPL ratio (%) | B2: < 1.5% | C2: 2.47% | D2: Đạt
A3: CASA ratio (%) | B3: > 20% | C3: 12.10% | D3: Tốt
A4: NIM (%) | B4: > 3.0% | C4: 4.69% | D4: Tốt

Sheet 11_Investment_Thesis
A1: Luận điểm chính | B1: Chi tiết nhận định
A2: Lợi thế CASA vượt trội | B2: Hệ sinh thái số hóa giúp huy động dòng vốn rẻ dồi dào, ổn định biên lãi NIM.
A3: Hiệu quả sinh lời cao | B3: Chỉ số ROE và ROA luôn nằm trong nhóm dẫn đầu hệ thống ngân hàng TMCP.

Sheet 12_Summary_Snapshot
A1: Chỉ tiêu | B1: 2021 | C1: 2022 | D1: 2023 | E1: 2024 | F1: 2025 | G1: 2026F | H1: 2027F | I1: 2028F
A2: Thu nhập lãi thuần (NII) | B2: 13890.777 | C2: 18011.568 | D2: 22183.974 | E2: 30857.076 | F2: 34746.19 | G2: 45281.251 | H2: 52480.26 | I2: 59539.11
A3: Tổng thu nhập hoạt động (TOI) | B3: 16758.245 | C3: 21967.104 | D3: 26413.685 | E3: 34032.184 | F3: 42695.872 | G3: 54423.386 | H3: 62993.715 | I3: 71524.448
A4: Lợi nhuận trước dự phòng (PPOP) | B4: 10375.477 | C4: 13336.395 | D4: 17284.483 | E4: 22051.429 | F4: 31094.885 | G4: 36463.668 | H4: 42835.726 | I4: 48636.625
A5: LNST (NPAT) | B5: 6453.499 | C5: 8209.47 | D5: 10336.013 | E5: 13247.648 | F5: 17073.622 | G5: 20403.479 | H5: 24843.975 | I5: 28898.372
A6: EPS (VND) | B6: 1257.3125 | C6: 1599.4221 | D6: 2013.729 | E6: 2580.9926 | F6: 3326.3936 | G6: 3975.1378 | H6: 4840.2641 | I6: 5630.1681
A7: Tổng tài sản | B7: 374611.57 | C7: 416273.02 | D7: 602314.86 | E7: 697366.46 | F7: 931103.94
A8: Cho vay khách hàng (Gross) | B8: 200758.83 | C8: 260754.81 | D8: 339349.84 | E8: 436606.24 | F8: 539071.33 | G8: 614541.32 | H8: 694431.69 | I8: 777763.5
A9: Trái phiếu doanh nghiệp | B9: 24879.776 | C9: 25793.635 | D9: 93389.645 | E9: 138247.9 | F9: 175459.66
A10: Tiền gửi khách hàng | B10: 183283.12 | C10: 215797.17 | D10: 370777.89 | E10: 437505.16 | F10: 560714.28 | G10: 628000 | H10: 697080 | I10: 766787.99
A11: Giấy tờ có giá phát hành (Bonds) | B11: 42756.113 | C11: 44161.64 | D11: 50938.148 | E11: 81349.744 | F11: 87434.265
A12: Tiền gửi Kho bạc Nhà nước | B12: 25507.511 | C12: 50949.728 | D12: 57835.226 | E12: 56059.007 | F12: 51095.331
A13: Tiền gửi ký quỹ (trừ đi) | B13: 3306.15 | C13: 23377.548 | D13: 2444.773 | E13: 3798.848 | F13: 12520.928
A14: Vốn chuyên dùng (trừ đi) | B14: 2936.864 | C14: 2860.155 | D14: 2811.129 | E14: 2788.443 | F14: 2721.952
A15: Vốn chủ sở hữu (VCSH) | B15: 30790.113 | C15: 38994.886 | D15: 46400.322 | E15: 56657.261 | F15: 78285.522

Sheet 13_PE_PB_History
A1: Quỳ | B1: P/E (x) | C1: P/B (x) | D1: EV/EBITDA (x) | E1: Giá
A2: Q2/18 | B2: 13.632459 | C2: 2.2035968
A3: Q3/18 | B3: 12.297557 | C3: 2.3584431
A4: Q4/18 | B4: 11.978797 | C4: 1.9786207
A5: Q1/19 | B5: 9.6992525 | C5: 1.7630831
A6: Q2/19 | B6: 8.8450628 | C6: 1.5514332
A7: Q3/19 | B7: 9.6700004 | C7: 1.6463272
A8: Q4/19 | B8: 8.2446558 | C8: 1.4848074
A9: Q1/20 | B9: 5.5924696 | C9: 1.0407449
A10: Q2/20 | B10: 6.3721764 | C10: 1.1836675
A11: Q3/20 | B11: 7.2356119 | C11: 1.4204438
A12: Q4/20 | B12: 8.0379722 | C12: 1.5744158
A13: Q1/21 | B13: 9.9583976 | C13: 1.8226478
... A35: MEDIAN ALL-TIME | B35: 6.7377377 | C35: 1.5109863
