Workbook

Sheet 00_Beta
A1: BẢNG TÍNH HỆ SỐ BETA LỊCH SỬ | B1: Beta thô (raw): | C1: =COVAR(C6:C505,E6:E505)/VAR(E6:E505) | D1: Beta Blume (điều chỉnh): | E1: =0.67*C1+0.33
B2: Số phiên giao dịch: | C2: =COUNT(C6:C505)
A4: Ngày | B4: Giá SIP | C4: Tỷ suất sinh lời SIP | D4: Giá VNINDEX | E4: Tỷ suất sinh lời VNINDEX
A5: 2024-07-04 | B5: 61697 | D5: 1279.89
A6: 2024-07-05 | B6: 61358 | C6: =(B6-B5)/B5 | D6: 1283.04 | E6: =(D6-D5)/D5
A7: 2024-07-08 | B7: 62986 | C7: =(B7-B6)/B6 | D7: 1283.56 | E7: =(D7-D6)/D6
A8: 2024-07-09 | B8: 62511 | C8: =(B8-B7)/B7 | D8: 1293.71 | E8: =(D8-D7)/D7
A9: 2024-07-10 | B9: 64166 | C9: =(B9-B8)/B8 | D9: 1285.94 | E9: =(D9-D8)/D8
A10: 2024-07-11 | B10: 63465 | C10: =(B10-B9)/B9 | D10: 1283.8 | E10: =(D10-D9)/D9
A11: 2024-07-12 | B11: 63465 | C11: =(B11-B10)/B10 | D11: 1280.75 | E11: =(D11-D10)/D10
A12: 2024-07-15 | B12: 64556 | C12: =(B12-B11)/B11 | D12: 1279.82 | E12: =(D12-D11)/D11
A13: 2024-07-16 | B13: 67753 | C13: =(B13-B12)/B12 | D13: 1281.18 | E13: =(D13-D12)/D12
A14: 2024-07-17 | B14: 64634 | C14: =(B14-B13)/B13 | D14: 1268.66 | E14: =(D14-D13)/D13
A15: 2024-07-18 | B15: 64868 | C15: =(B15-B14)/B14 | D15: 1274.44 | E15: =(D15-D14)/D14
A16: 2024-07-19 | B16: 63932 | C16: =(B16-B15)/B15 | D16: 1264.78 | E16: =(D16-D15)/D15
A17: 2024-07-22 | B17: 61593 | C17: =(B17-B16)/B16 | D17: 1254.64 | E17: =(D17-D16)/D16
... A505: 2026-07-08 | B505: 49900 | C505: =(B505-B504)/B504 | D505: 1853.7 | E505: =(D505-D504)/D504

Sheet 00_COE
A1: CHI PHÍ VỐN CHỦ SỞ HỮU (COE) - MÔ HÌNH CAPM
A3: Tham số | B3: Giá trị | C3: Ghi chú / Nguồn
A4: Rf - Lãi suất phi rủi ro (TPCP 10 năm) | B4: 0.045 | C4: TPCP 10Y VN
A5: Hệ số Beta (Blume-adjusted) | B5: ='00_Beta'!E1 | C5: Tự tính toán (1619 phiên)
A6: ERP - Phần bù rủi ro vốn (Damodaran) | B6: 0.07 | C6: Damodaran ERP cho Việt Nam
A7: Phần bù rủi ro đặc thù (Quốc gia/Ngành) | B7: 0.02 | C7: Phần bù rủi ro quốc gia/KCN đặc thù
A9: COE = Rf + β × ERP + PBĐT | B9: =B4+B5*B6+B7 | C9: Chi phí vốn chủ sở hữu (CAPM điều chỉnh)

Sheet 01_Cover
B2: MÔ HÌNH PHÂN TÍCH TÀI CHÍNH & ĐỊNH GIÁ — SIP
B3: Công ty Cổ phần Đầu tư Sài Gòn VRG
B4: Ngày lập: 09/07/2026 00:01
B6: Giá thị trường (VND) | C6: 49750
B7: Số CP lưu hành | C7: 242112943
B8: Vốn hóa (tỷ VND) | C8: =B6*B7/1000000000
B9: Beta (CAPM) | C9: ='00_COE'!B5
B10: Rf (%/năm) | C10: ='00_COE'!B4
B11: COE (%/năm) | C11: ='00_COE'!B9
B12: Nguồn Beta | C12: Tự tính toán (1619 phiên)
B15: ─── ĐỊNH GIÁ TỔNG HỢP ───
B16: Giá hợp lý P/E (40%) | C16: ='08_Valuation'!B11
B17: Giá hợp lý P/B (40%) | C17: ='08_Valuation'!B15
B18: Giá hợp lý RI (20%) | C18: ='08_Valuation'!B23
B19: Giá mục tiêu blend | C19: ='08_Valuation'!B26
B20: Upside/Downside | C20: ='08_Valuation'!B27
B22: Nhận định AI:
B23: Công ty Cổ phần Đầu tư Sài Gòn VRG (SIP) là doanh nghiệp bất động sản khu công nghiệp với mô hình đa mảng (cho thuê đất, tiện ích, điện, BOT…). Doanh thu mảng hạ tầng KCN mang tính chu kỳ nhưng ổn định nhờ hợp đồng thuê dài hạn; mảng điện và tiện ích tạo dòng tiền đều đặn hàng quý.

Sheet 02_Assumptions
A1: Tham số giả định | B1: Giá trị | C1: Ghi chú
A2: Rf (lãi TPCP 10Y, %/năm) | B2: ='00_COE'!B4 | C2: TPCP 10Y VN
A3: Beta (CAPM) | B3: ='00_COE'!B5 | C3: Tự tính toán (1619 phiên)
A4: ERP (phần bù rủi ro thị trường) | B4: ='00_COE'!B6 | C4: Damodaran ERP cho VN (7%)
A5: Phần bù rủi ro đặc thù KCN | B5: ='00_COE'!B7 | C5: Thanh khoản thấp, phụ thuộc FDI (+2%)
A6: COE = Rf + β × ERP + PBĐT | B6: ='00_COE'!B9 | C6: Cost of Equity (CAPM điều chỉnh)
A7: EPS lịch sử gần nhất (VND) | B7: ='A4_EPS_Bridge'!F4 | C7: isa22 / CP lưu hành năm tương ứng
A8: BVPS mẹ lịch sử gần nhất (VND) | B8: ='A4_EPS_Bridge'!F5 | C8: (bsa78 − bsa210) / CP lưu hành
A9: Payout ratio trung bình | B9: 0.34306959 | C9: Trung bình lịch sử |cfa32| / isa22
A10: CAGR EPS dự phóng | B10: ='A1_CAGR_Analysis'!G8 | C10: CAGR EPS 3Y — từ A1_CAGR_Analysis
A11: ROE ước tính (EPS/BVPS đầu kỳ) | B11: =B7/B8 | C11: =EPS_last / BVPS_đầu kỳ cuối
A12: P/E mục tiêu | B12: =MAX(8, MIN(25, '03_PE_PB_History'!B27)) | C12: Median P/E lịch sử, kẹp [8, 25]
A13: P/B mục tiêu | B13: =MAX(0.6, MIN(4, '03_PE_PB_History'!C27)) | C13: Median P/B lịch sử, kẹp [0.6, 4]
A14: Số năm RI dự phóng (n) | B14: 3 | C14: PV RI 3 năm + terminal value
A15: g terminal RI | B15: =MAX(0, MIN(0.04, B10*0.5)) | C15: min(CAGR_EPS × 0.5, 4%)
A16: Số CP lưu hành | B16: 242112943 | C16: VĐL / 10,000 (mệnh giá 10k) — năm mới nhất
A17: Giá thị trường (VND) | B17: 49750 | C17: Giá cuối phiên gần nhất

Sheet 03_PE_PB_History
A1: Quý | B1: P/E (x) | C1: P/B (x)
A2: 2019-Q4 | B2: 9.25 | C2: 3.35
A3: 2020-Q1 | B3: 12.52 | C3: 3.41
A4: 2020-Q2 | B4: 11.2 | C4: 3.94
A5: 2020-Q3 | B5: 23.97 | C5: 8.3
A6: 2020-Q4 | B6: 13.35 | C6: 5.89
A7: 2021-Q1 | B7: 11.12 | C7: 5.18
A8: 2021-Q3 | B8: 11.73 | C8: 4.53
A9: 2021-Q4 | B9: 12.81 | C9: 3.65
A10: 2022-Q1 | B10: 10.52 | C10: 2.9
A11: 2022-Q2 | B11: 12.79 | C11: 3.08
A12: 2022-Q3 | B12: 7.66 | C12: 1.89
A13: 2022-Q4 | B13: 8.17 | C13: 2.41
... A26: 2026-Q1 | B26: 9.22 | C26: 2.19
A27: MEDIAN | B27: =MEDIAN(B2:B26) | C27: =MEDIAN(C2:C26)

Sheet 03_PnL
A1: Chỉ tiêu P&L (tỷ VND) | B1: 2021A | C1: 2022A | D1: 2023A | E1: 2024A | F1: 2025A | G1: 2026E | H1: 2027E | I1: 2028E
A2: Doanh thu thuần | B2: 5577.56 | C2: 6034.52 | D2: 6676.52 | E2: 7801.16 | F2: 8596.23 | G2: 9606.36 | H2: 10328.29 | I2: 11111.37
A3: Giá vốn hàng bán | B3: -4804.7 | C3: -5133.39 | D3: -5746.07 | E3: -6706.01 | F3: -7252.79 | G3: -8181.43 | H3: -8796.27 | I3: -9463.2
A4: Lợi nhuận gộp | B4: 10382.26 | C4: 11167.91 | D4: 12422.59 | E4: 14507.17 | F4: 15849.02 | G4: 17787.79 | H4: 19124.56 | I4: 20574.57
A5: Lợi nhuận trước thuế | B5: 1110.8 | C5: 1245.54 | D5: 1274.29 | E5: 1571.74 | F5: 1838.52 | G5: 1995.3 | H5: 2145.25 | I5: 2307.9
A6: LNST (hợp nhất) | B6: 908.54 | C6: 1009.9 | D6: 1003.66 | E6: 1278.83 | F6: 1467.09 | G6: 1607.12 | H6: 1727.9 | I6: 1858.91
A7: LNST cổ đông mẹ | B7: 835.41 | C7: 977.16 | D7: 926.9 | E7: 1170.16 | F7: 1322.87 | G7: 1459.85 | H7: 1569.56 | I7: 1688.56
A8: Biên lợi nhuận gộp (%) | B8: 1.8614 | C8: 1.8507 | D8: 1.8606 | E8: 1.8596 | F8: 1.8437 | G8: =G4/G2 | H8: =H4/H2 | I8: =I4/I2

Sheet 04_Segments_DT
A1: Mảng kinh doanh | B1: 2021A | C1: 2022A | D1: 2023A | E1: 2024A | F1: 2025A | G1: 2026E | H1: 2027E | I1: 2028E
A2: DV tiện ích điện, nước KCN | B2: 4980.5 | C2: 5340.2 | D2: 5780.4 | E2: 6120.5 | F2: 6580 | G2: =F2 * (1 + 0.0700) | H2: =G2 * (1 + 0.0700) | I2: =H2 * (1 + 0.0700)
A3: Bán hàng hóa, thành phẩm | B3: 120.4 | C3: 145.8 | D3: 168.2 | E3: 180.4 | F3: 195 | G3: =F3 * (1 + 0.2141) | H3: =G3 * (1 + 0.2141) | I3: =H3 * (1 + 0.2141)
A4: DV tiện ích KCN khác | B4: 550.2 | C4: 620.4 | D4: 680.5 | E4: 740.6 | F4: 810 | G4: =F4 * (1 + 0.0700) | H4: =G4 * (1 + 0.0700) | I4: =H4 * (1 + 0.0700)
A5: Cho thuê đất đã phát triển CSHT | B5: 380.6 | C5: 450.9 | D5: 520.4 | E5: 610.2 | F5: 680 | G5: =F5 * (1 + 0.0751) | H5: =G5 * (1 + 0.0751) | I5: =H5 * (1 + 0.0751)
A6: DV xây dựng | B6: 140.8 | C6: 165.2 | D6: 182 | E6: 205.4 | F6: 230 | G6: =F6 * (1 + 0.1305) | H6: =G6 * (1 + 0.1305) | I6: =H6 * (1 + 0.1305)
A7: Bán bất động sản | B7: 85 | C7: 92.4 | D7: 105.8 | E7: 120.5 | F7: 140 | G7: =F7 * (1 + 0.1329) | H7: =G7 * (1 + 0.1329) | I7: =H7 * (1 + 0.1329)
A8: DV khác | B8: 180.2 | C8: 210.5 | D8: 242 | E8: 275.2 | F8: 305 | G8: =F8 * (1 + 0.0250) | H8: =G8 * (1 + 0.0250) | I8: =H8 * (1 + 0.0250)
A9: TỔNG DOANH THU | B9: =SUM(B2:B8) | C9: =SUM(C2:C8) | D9: =SUM(D2:D8) | E9: =SUM(E2:E8) | F9: =SUM(F2:F8) | G9: =SUM(G2:G8) | H9: =SUM(H2:H8) | I9: =SUM(I2:I8)
A10: Giả định g (CAGR/YTD blend) | G10: 0.025 | H10: 0.025 | I10: 0.025
A11: YTD run-rate (tỷ, annualised) | G11: 228.8

Sheet 05_Segments_GV
A1: Mảng kinh doanh (Giá vốn) | B1: 2021A | C1: 2022A | D1: 2023A | E1: 2024A | F1: 2025A | G1: 2026E | H1: 2027E | I1: 2028E
A2: DV tiện ích điện, nước KCN | B2: 4620.2 | C2: 4980.5 | D2: 5350.2 | E2: 5680.4 | F2: 6050.2 | G2: ='04_Segments_DT'!G2 * (1 - '06_Segments_GM'!G2) | H2: ='04_Segments_DT'!H2 * (1 - '06_Segments_GM'!H2) | I2: ='04_Segments_DT'!I2 * (1 - '06_Segments_GM'!I2)
A3: Bán hàng hóa, thành phẩm | B3: 105.3 | C3: 128 | D3: 145.4 | E3: 156.2 | F3: 168.4 | G3: ='04_Segments_DT'!G3 * (1 - '06_Segments_GM'!G3) | H3: ='04_Segments_DT'!H3 * (1 - '06_Segments_GM'!H3) | I3: ='04_Segments_DT'!I3 * (1 - '06_Segments_GM'!I3)
A4: DV tiện ích KCN khác | B4: 310.4 | C4: 340.2 | D4: 365.2 | E4: 395 | F4: 420.5 | G4: ='04_Segments_DT'!G4 * (1 - '06_Segments_GM'!G4) | H4: ='04_Segments_DT'!H4 * (1 - '06_Segments_GM'!H4) | I4: ='04_Segments_DT'!I4 * (1 - '06_Segments_GM'!I4)
A5: Cho thuê đất đã phát triển CSHT | B5: 110.2 | C5: 125.8 | D5: 148.6 | E5: 172.5 | F5: 190.2 | G5: ='04_Segments_DT'!G5 * (1 - '06_Segments_GM'!G5) | H5: ='04_Segments_DT'!H5 * (1 - '06_Segments_GM'!H5) | I5: ='04_Segments_DT'!I5 * (1 - '06_Segments_GM'!I5)
A6: DV xây dựng | B6: 125.4 | C6: 148 | D6: 162.5 | E6: 182 | F6: 198.5 | G6: ='04_Segments_DT'!G6 * (1 - '06_Segments_GM'!G6) | H6: ='04_Segments_DT'!H6 * (1 - '06_Segments_GM'!H6) | I6: ='04_Segments_DT'!I6 * (1 - '06_Segments_GM'!I6)
A7: Bán bất động sản | B7: 35.2 | C7: 38 | D7: 42 | E7: 48.4 | F7: 55 | G7: ='04_Segments_DT'!G7 * (1 - '06_Segments_GM'!G7) | H7: ='04_Segments_DT'!H7 * (1 - '06_Segments_GM'!H7) | I7: ='04_Segments_DT'!I7 * (1 - '06_Segments_GM'!I7)
A8: DV khác | B8: 145.1 | C8: 172.4 | D8: 195.8 | E8: 218 | F8: 242 | G8: ='04_Segments_DT'!G8 * (1 - '06_Segments_GM'!G8) | H8: ='04_Segments_DT'!H8 * (1 - '06_Segments_GM'!H8) | I8: ='04_Segments_DT'!I8 * (1 - '06_Segments_GM'!I8)
A9: TỔNG GIÁ VỐN | B9: =SUM(B2:B8) | C9: =SUM(C2:C8) | D9: =SUM(D2:D8) | E9: =SUM(E2:E8) | F9: =SUM(F2:F8) | G9: =SUM(G2:G8) | H9: =SUM(H2:H8) | I9: =SUM(I2:I8)

Sheet 06_Segments_GM
A1: Mảng kinh doanh (Biên LNG %) | B1: 2021A | C1: 2022A | D1: 2023A | E1: 2024A | F1: 2025A | G1: 2026E | H1: 2027E | I1: 2028E
A2: DV tiện ích điện, nước KCN | B2: =IF('04_Segments_DT'!B2=0, 0, ('04_Segments_DT'!B2 - '05_Segments_GV'!B2) / '04_Segments_DT'!B2) | C2: =IF('04_Segments_DT'!C2=0, 0, ('04_Segments_DT'!C2 - '05_Segments_GV'!C2) / '04_Segments_DT'!C2) | D2: =IF('04_Segments_DT'!D2=0, 0, ('04_Segments_DT'!D2 - '05_Segments_GV'!D2) / '04_Segments_DT'!D2) | E2: =IF('04_Segments_DT'!E2=0, 0, ('04_Segments_DT'!E2 - '05_Segments_GV'!E2) / '04_Segments_DT'!E2) | F2: =IF('04_Segments_DT'!F2=0, 0, ('04_Segments_DT'!F2 - '05_Segments_GV'!F2) / '04_Segments_DT'!F2) | G2: 0.0762 | H2: 0.0762 | I2: 0.0762
A3: Bán hàng hóa, thành phẩm | B3: =IF('04_Segments_DT'!B3=0, 0, ('04_Segments_DT'!B3 - '05_Segments_GV'!B3) / '04_Segments_DT'!B3) | C3: =IF('04_Segments_DT'!C3=0, 0, ('04_Segments_DT'!C3 - '05_Segments_GV'!C3) / '04_Segments_DT'!C3) | D3: =IF('04_Segments_DT'!D3=0, 0, ('04_Segments_DT'!D3 - '05_Segments_GV'!D3) / '04_Segments_DT'!D3) | E3: =IF('04_Segments_DT'!E3=0, 0, ('04_Segments_DT'!E3 - '05_Segments_GV'!E3) / '04_Segments_DT'!E3) | F3: =IF('04_Segments_DT'!F3=0, 0, ('04_Segments_DT'!F3 - '05_Segments_GV'!F3) / '04_Segments_DT'!F3) | G3: 0.1353 | H3: 0.1353 | I3: 0.1353
A4: DV tiện ích KCN khác | B4: =IF('04_Segments_DT'!B4=0, 0, ('04_Segments_DT'!B4 - '05_Segments_GV'!B4) / '04_Segments_DT'!B4) | C4: =IF('04_Segments_DT'!C4=0, 0, ('04_Segments_DT'!C4 - '05_Segments_GV'!C4) / '04_Segments_DT'!C4) | D4: =IF('04_Segments_DT'!D4=0, 0, ('04_Segments_DT'!D4 - '05_Segments_GV'!D4) / '04_Segments_DT'!D4) | E4: =IF('04_Segments_DT'!E4=0, 0, ('04_Segments_DT'!E4 - '05_Segments_GV'!E4) / '04_Segments_DT'!E4) | F4: =IF('04_Segments_DT'!F4=0, 0, ('04_Segments_DT'!F4 - '05_Segments_GV'!F4) / '04_Segments_DT'!F4) | G4: 0.4738 | H4: 0.4738 | I4: 0.4738
A5: Cho thuê đất đã phát triển CSHT | B5: =IF('04_Segments_DT'!B5=0, 0, ('04_Segments_DT'!B5 - '05_Segments_GV'!B5) / '04_Segments_DT'!B5) | C5: =IF('04_Segments_DT'!C5=0, 0, ('04_Segments_DT'!C5 - '05_Segments_GV'!C5) / '04_Segments_DT'!C5) | D5: =IF('04_Segments_DT'!D5=0, 0, ('04_Segments_DT'!D5 - '05_Segments_GV'!D5) / '04_Segments_DT'!D5) | E5: =IF('04_Segments_DT'!E5=0, 0, ('04_Segments_DT'!E5 - '05_Segments_GV'!E5) / '04_Segments_DT'!E5) | F5: =IF('04_Segments_DT'!F5=0, 0, ('04_Segments_DT'!F5 - '05_Segments_GV'!F5) / '04_Segments_DT'!F5) | G5: 0.7188 | H5: 0.7188 | I5: 0.7188
A6: DV xây dựng | B6: =IF('04_Segments_DT'!B6=0, 0, ('04_Segments_DT'!B6 - '05_Segments_GV'!B6) / '04_Segments_DT'!B6) | C6: =IF('04_Segments_DT'!C6=0, 0, ('04_Segments_DT'!C6 - '05_Segments_GV'!C6) / '04_Segments_DT'!C6) | D6: =IF('04_Segments_DT'!D6=0, 0, ('04_Segments_DT'!D6 - '05_Segments_GV'!D6) / '04_Segments_DT'!D6) | E6: =IF('04_Segments_DT'!E6=0, 0, ('04_Segments_DT'!E6 - '05_Segments_GV'!E6) / '04_Segments_DT'!E6) | F6: =IF('04_Segments_DT'!F6=0, 0, ('04_Segments_DT'!F6 - '05_Segments_GV'!F6) / '04_Segments_DT'!F6) | G6: 0.1254 | H6: 0.1254 | I6: 0.1254
A7: Bán bất động sản | B7: =IF('04_Segments_DT'!B7=0, 0, ('04_Segments_DT'!B7 - '05_Segments_GV'!B7) / '04_Segments_DT'!B7) | C7: =IF('04_Segments_DT'!C7=0, 0, ('04_Segments_DT'!C7 - '05_Segments_GV'!C7) / '04_Segments_DT'!C7) | D7: =IF('04_Segments_DT'!D7=0, 0, ('04_Segments_DT'!D7 - '05_Segments_GV'!D7) / '04_Segments_DT'!D7) | E7: =IF('04_Segments_DT'!E7=0, 0, ('04_Segments_DT'!E7 - '05_Segments_GV'!E7) / '04_Segments_DT'!E7) | F7: =IF('04_Segments_DT'!F7=0, 0, ('04_Segments_DT'!F7 - '05_Segments_GV'!F7) / '04_Segments_DT'!F7) | G7: 0.6027 | H7: 0.6027 | I7: 0.6027
A8: DV khác | B8: =IF('04_Segments_DT'!B8=0, 0, ('04_Segments_DT'!B8 - '05_Segments_GV'!B8) / '04_Segments_DT'!B8) | C8: =IF('04_Segments_DT'!C8=0, 0, ('04_Segments_DT'!C8 - '05_Segments_GV'!C8) / '04_Segments_DT'!C8) | D8: =IF('04_Segments_DT'!D8=0, 0, ('04_Segments_DT'!D8 - '05_Segments_GV'!D8) / '04_Segments_DT'!D8) | E8: =IF('04_Segments_DT'!E8=0, 0, ('04_Segments_DT'!E8 - '05_Segments_GV'!E8) / '04_Segments_DT'!E8) | F8: =IF('04_Segments_DT'!F8=0, 0, ('04_Segments_DT'!F8 - '05_Segments_GV'!F8) / '04_Segments_DT'!F8) | G8: 0.2072 | H8: 0.2072 | I8: 0.2072

Sheet 07_BalanceSheet
A1: Chỉ tiêu BS (tỷ VND) | B1: 2021A | C1: 2022A | D1: 2023A | E1: 2024A | F1: 2025A
A2: Tiền & tương đương | B2: 774.4 | C2: 439.73 | D2: 829.3 | E2: 645.6 | F2: 844.6
A3: Tổng tài sản | B3: 17817.26 | C3: 19003.42 | D3: 21060.43 | E3: 25052.88 | F3: 28670.19
A4: Vay ngắn hạn | B4: 450.41 | C4: 688.95 | D4: 1595.16 | E4: 2465.71 | F4: 3748.42
A5: Vay dài hạn | B5: 6.36 | C5: 1.51 | D5: 90.69 | E5: 1132.07 | F5: 1069.11
A6: Tổng nợ phải trả | B6: 14519.38 | C6: 15342.59 | D6: 17032.38 | E6: 20185.06 | F6: 22856.2
A7: VCSH (bao gồm NCI) | B7: 3297.88 | C7: 3660.83 | D7: 4028.05 | E7: 4867.82 | F7: 5813.98
A8: Vốn góp (charter capital) | B8: 929.04 | C8: 909.04 | D8: 1818.08 | E8: 2105.33 | F8: 2421.13
A9: NCI (cổ đông thiểu số) | B9: 320.67 | C9: 415.98 | D9: 461.25 | E9: 528.14 | F9: 661.34
A10: VCSH cổ đông mẹ (= VCSH − NCI) | B10: 2977.21 | C10: 3244.85 | D10: 3566.8 | E10: 4339.68 | F10: 5152.64
A12: BVPS mẹ (VND/cp) | B12: 12297 | C12: 13402 | D12: 14732 | E12: 17924 | F12: 21282
A13: EPS cơ bản (VND/cp) | B13: 8992 | C13: 4697 | D13: 3992 | E13: 4379 | F13: 4972
A14: Payout ratio lịch sử | B14: 0.3083 | C14: 0.2056 | D14: 0.5672 | E14: 0.3067 | F14: 0.3276

Sheet 08_Valuation
A1: Định giá KCN (40%P/E + 40%P/B + 20%RI) | B1: Giá trị | C1: Ghi chú
A2: ─ COE & CAPM ─
A3: Rf (lãi suất phi rủi ro) | B3: ='00_COE'!B4 | C3: TPCP 10Y VN
A4: Beta | B4: ='00_COE'!B5 | C4: Tự tính toán (1619 phiên)
A5: ERP | B5: ='00_COE'!B6 | C5: Phần bù rủi ro TTCK VN
A6: Phần bù rủi ro đặc thù | B6: ='00_COE'!B7 | C6: Phần bù rủi ro quốc gia/ngành đặc thù
A7: COE = Rf + β × ERP + PBĐT | B7: ='00_COE'!B9 | C7: Chi phí vốn chủ sở hữu
A8: ─ P/E ─
A9: EPS forward 1Y (VND) | B9: 5549 | C9: Formula: EPS_last × (1 + CAGR EPS)
A10: P/E mục tiêu | B10: =02_Assumptions!B12 | C10: Median P/E lịch sử, kẹp [8,25]
A11: Giá hợp lý P/E | B11: =B9*B10 | C11: Formula: P/E × EPS_fc1
A12: ─ P/B ─
A13: BVPS forward 1Y (VND) | B13: 24927 | C13: Roll-forward trừ cổ tức
A14: P/B mục tiêu | B14: =02_Assumptions!B13 | C14: Median P/B lịch sử, kẹp [0.6,4]
A15: Giá hợp lý P/B | B15: =B13*B14 | C15: Formula: P/B × BVPS_fc1
A16: ─ Residual Income ─
A17: BVPS hiện tại (VND) | B17: =02_Assumptions!B8 | C17: bsa78 − bsa210 / shares
A18: CAGR EPS | B18: =02_Assumptions!B10 | C18: Kẹp [−10%, +20%]
A19: RI Năm 1 (VND) | B19: 2447.8 | C19: PV EPS1 − COE×BVPS0
A20: RI Năm 2 (VND) | B20: 2295.8 | C20: PV EPS2 − COE×BVPS1
A21: RI Năm 3 (VND) | B21: 2159.7 | C21: PV EPS3 − COE×BVPS2
A22: RI Terminal (PV, VND) | B22: 18629.5 | C22: Formula: TV/(COE-g)
A23: Giá hợp lý RI (VND) | B23: =B17+B19+B20+B21+B22 | C23: Formula: BVPS + ΣRI_PV + Terminal_PV
A24: ─ KẾT QUẢ ─
A25: Giá thị trường (VND) | B25: =02_Assumptions!B17
A26: Giá mục tiêu (40+40+20) | B26: =0.4*B11+0.4*B15+0.2*B23 | C26: Tổng hợp 3 phương pháp
A27: Upside / Downside | B27: =(B26-B25)/B25 | C27: +/- % so với giá thị trường

Sheet 09_Quarterly_DT
A1: Mảng / Quý | B1: 2024Q1 | C1: 2024Q2 | D1: 2024Q3 | E1: 2024Q4 | F1: 2025Q1 | G1: 2025Q2 | H1: 2025Q3 | I1: 2025Q4 | J1: 2026Q1 | K1: Trung bình
A2: DV tiện ích điện, nước KCN | B2: 1407.7 | C2: 1530.1 | D2: 1591.3 | E2: 1591.4 | F2: 1589.9 | G2: 1645 | H2: 1710.8 | I2: 1634.3 | J2: 1687.3 | K2: =AVERAGE(B2:J2)
A3: Bán hàng hóa, thành phẩm | B3: 41.5 | C3: 45.1 | D3: 46.9 | E3: 46.9 | F3: 24.3 | G3: 48.8 | H3: 50.7 | I3: 71.2 | J3: 40.8 | K3: =AVERAGE(B3:J3)
A4: DV tiện ích KCN khác | B4: 170.3 | C4: 185.2 | D4: 192.6 | E4: 192.5 | F4: 146.9 | G4: 202.5 | H4: 210.6 | I4: 250 | J4: 206.1 | K4: =AVERAGE(B4:J4)
A5: Cho thuê đất đã phát triển CSHT | B5: 140.3 | C5: 152.6 | D5: 158.7 | E5: 158.6 | F5: 117.3 | G5: 170 | H5: 176.8 | I5: 215.9 | J5: 116.6 | K5: =AVERAGE(B5:J5)
A6: DV xây dựng | B6: 47.2 | C6: 51.4 | D6: 53.4 | E6: 53.4 | F6: 0 | G6: 57.5 | H6: 59.8 | I6: 112.7 | J6: 17.8 | K6: =AVERAGE(B6:J6)
A7: Bán bất động sản | B7: 27.7 | C7: 30.1 | D7: 31.3 | E7: 31.4 | F7: 0 | G7: 35 | H7: 36.4 | I7: 68.6 | J7: 38.8 | K7: =AVERAGE(B7:J7)
A8: DV khác | B8: 63.3 | C8: 68.8 | D8: 71.6 | E8: 71.5 | F8: 62.9 | G8: 76.2 | H8: 79.3 | I8: 86.6 | J8: 57.2 | K8: =AVERAGE(B8:J8)

Sheet 10_Quarterly_GV
A1: Mảng / Quý | B1: 2024Q1 | C1: 2024Q2 | D1: 2024Q3 | E1: 2024Q4 | F1: 2025Q1 | G1: 2025Q2 | H1: 2025Q3 | I1: 2025Q4 | J1: 2026Q1 | K1: Trung bình
A2: DV tiện ích điện, nước KCN | B2: 1306.5 | C2: 1420.1 | D2: 1476.9 | E2: 1476.9 | F2: 1456.9 | G2: 1512.5 | H2: 1573.1 | I2: 1507.7 | J2: 1562.6 | K2: =AVERAGE(B2:J2)
A3: Bán hàng hóa, thành phẩm | B3: 35.9 | C3: 39 | D3: 40.6 | E3: 40.7 | F3: 21.6 | G3: 42.1 | H3: 43.8 | I3: 60.9 | J3: 34.5 | K3: =AVERAGE(B3:J3)
A4: DV tiện ích KCN khác | B4: 90.9 | C4: 98.8 | D4: 102.7 | E4: 102.6 | F4: 57.4 | G4: 105.1 | H4: 109.3 | I4: 148.7 | J4: 97.7 | K4: =AVERAGE(B4:J4)
A5: Cho thuê đất đã phát triển CSHT | B5: 39.7 | C5: 43.1 | D5: 44.9 | E5: 44.8 | F5: 31.7 | G5: 47.5 | H5: 49.5 | I5: 61.5 | J5: 34.3 | K5: =AVERAGE(B5:J5)
A6: DV xây dựng | B6: 41.9 | C6: 45.5 | D6: 47.3 | E6: 47.3 | F6: 0 | G6: 49.6 | H6: 51.6 | I6: 97.3 | J6: 16.3 | K6: =AVERAGE(B6:J6)
A7: Bán bất động sản | B7: 11.1 | C7: 12.1 | D7: 12.6 | E7: 12.6 | F7: 0 | G7: 13.8 | H7: 14.3 | I7: 26.9 | J7: 13.3 | K7: =AVERAGE(B7:J7)
A8: DV khác | B8: 50.1 | C8: 54.5 | D8: 56.7 | E8: 56.7 | F8: 53.3 | G8: 60.5 | H8: 62.9 | I8: 65.3 | J8: 49 | K8: =AVERAGE(B8:J8)

Sheet 11_Quarterly_GM
A1: Mảng / Quý (Biên LNG %) | B1: 2024Q1 | C1: 2024Q2 | D1: 2024Q3 | E1: 2024Q4 | F1: 2025Q1 | G1: 2025Q2 | H1: 2025Q3 | I1: 2025Q4 | J1: 2026Q1 | K1: Trung bình
A2: DV tiện ích điện, nước KCN | B2: =IF('09_Quarterly_DT'!B2=0, 0, ('09_Quarterly_DT'!B2 - '10_Quarterly_GV'!B2) / '09_Quarterly_DT'!B2) | C2: =IF('09_Quarterly_DT'!C2=0, 0, ('09_Quarterly_DT'!C2 - '10_Quarterly_GV'!C2) / '09_Quarterly_DT'!C2) | D2: =IF('09_Quarterly_DT'!D2=0, 0, ('09_Quarterly_DT'!D2 - '10_Quarterly_GV'!D2) / '09_Quarterly_DT'!D2) | E2: =IF('09_Quarterly_DT'!E2=0, 0, ('09_Quarterly_DT'!E2 - '10_Quarterly_GV'!E2) / '09_Quarterly_DT'!E2) | F2: =IF('09_Quarterly_DT'!F2=0, 0, ('09_Quarterly_DT'!F2 - '10_Quarterly_GV'!F2) / '09_Quarterly_DT'!F2) | G2: =IF('09_Quarterly_DT'!G2=0, 0, ('09_Quarterly_DT'!G2 - '10_Quarterly_GV'!G2) / '09_Quarterly_DT'!G2) | H2: =IF('09_Quarterly_DT'!H2=0, 0, ('09_Quarterly_DT'!H2 - '10_Quarterly_GV'!H2) / '09_Quarterly_DT'!H2) | I2: =IF('09_Quarterly_DT'!I2=0, 0, ('09_Quarterly_DT'!I2 - '10_Quarterly_GV'!I2) / '09_Quarterly_DT'!I2) | J2: =IF('09_Quarterly_DT'!J2=0, 0, ('09_Quarterly_DT'!J2 - '10_Quarterly_GV'!J2) / '09_Quarterly_DT'!J2) | K2: =AVERAGE(B2:J2)
A3: Bán hàng hóa, thành phẩm | B3: =IF('09_Quarterly_DT'!B3=0, 0, ('09_Quarterly_DT'!B3 - '10_Quarterly_GV'!B3) / '09_Quarterly_DT'!B3) | C3: =IF('09_Quarterly_DT'!C3=0, 0, ('09_Quarterly_DT'!C3 - '10_Quarterly_GV'!C3) / '09_Quarterly_DT'!C3) | D3: =IF('09_Quarterly_DT'!D3=0, 0, ('09_Quarterly_DT'!D3 - '10_Quarterly_GV'!D3) / '09_Quarterly_DT'!D3) | E3: =IF('09_Quarterly_DT'!E3=0, 0, ('09_Quarterly_DT'!E3 - '10_Quarterly_GV'!E3) / '09_Quarterly_DT'!E3) | F3: =IF('09_Quarterly_DT'!F3=0, 0, ('09_Quarterly_DT'!F3 - '10_Quarterly_GV'!F3) / '09_Quarterly_DT'!F3) | G3: =IF('09_Quarterly_DT'!G3=0, 0, ('09_Quarterly_DT'!G3 - '10_Quarterly_GV'!G3) / '09_Quarterly_DT'!G3) | H3: =IF('09_Quarterly_DT'!H3=0, 0, ('09_Quarterly_DT'!H3 - '10_Quarterly_GV'!H3) / '09_Quarterly_DT'!H3) | I3: =IF('09_Quarterly_DT'!I3=0, 0, ('09_Quarterly_DT'!I3 - '10_Quarterly_GV'!I3) / '09_Quarterly_DT'!I3) | J3: =IF('09_Quarterly_DT'!J3=0, 0, ('09_Quarterly_DT'!J3 - '10_Quarterly_GV'!J3) / '09_Quarterly_DT'!J3) | K3: =AVERAGE(B3:J3)
A4: DV tiện ích KCN khác | B4: =IF('09_Quarterly_DT'!B4=0, 0, ('09_Quarterly_DT'!B4 - '10_Quarterly_GV'!B4) / '09_Quarterly_DT'!B4) | C4: =IF('09_Quarterly_DT'!C4=0, 0, ('09_Quarterly_DT'!C4 - '10_Quarterly_GV'!C4) / '09_Quarterly_DT'!C4) | D4: =IF('09_Quarterly_DT'!D4=0, 0, ('09_Quarterly_DT'!D4 - '10_Quarterly_GV'!D4) / '09_Quarterly_DT'!D4) | E4: =IF('09_Quarterly_DT'!E4=0, 0, ('09_Quarterly_DT'!E4 - '10_Quarterly_GV'!E4) / '09_Quarterly_DT'!E4) | F4: =IF('09_Quarterly_DT'!F4=0, 0, ('09_Quarterly_DT'!F4 - '10_Quarterly_GV'!F4) / '09_Quarterly_DT'!F4) | G4: =IF('09_Quarterly_DT'!G4=0, 0, ('09_Quarterly_DT'!G4 - '10_Quarterly_GV'!G4) / '09_Quarterly_DT'!G4) | H4: =IF('09_Quarterly_DT'!H4=0, 0, ('09_Quarterly_DT'!H4 - '10_Quarterly_GV'!H4) / '09_Quarterly_DT'!H4) | I4: =IF('09_Quarterly_DT'!I4=0, 0, ('09_Quarterly_DT'!I4 - '10_Quarterly_GV'!I4) / '09_Quarterly_DT'!I4) | J4: =IF('09_Quarterly_DT'!J4=0, 0, ('09_Quarterly_DT'!J4 - '10_Quarterly_GV'!J4) / '09_Quarterly_DT'!J4) | K4: =AVERAGE(B4:J4)
A5: Cho thuê đất đã phát triển CSHT | B5: =IF('09_Quarterly_DT'!B5=0, 0, ('09_Quarterly_DT'!B5 - '10_Quarterly_GV'!B5) / '09_Quarterly_DT'!B5) | C5: =IF('09_Quarterly_DT'!C5=0, 0, ('09_Quarterly_DT'!C5 - '10_Quarterly_GV'!C5) / '09_Quarterly_DT'!C5) | D5: =IF('09_Quarterly_DT'!D5=0, 0, ('09_Quarterly_DT'!D5 - '10_Quarterly_GV'!D5) / '09_Quarterly_DT'!D5) | E5: =IF('09_Quarterly_DT'!E5=0, 0, ('09_Quarterly_DT'!E5 - '10_Quarterly_GV'!E5) / '09_Quarterly_DT'!E5) | F5: =IF('09_Quarterly_DT'!F5=0, 0, ('09_Quarterly_DT'!F5 - '10_Quarterly_GV'!F5) / '09_Quarterly_DT'!F5) | G5: =IF('09_Quarterly_DT'!G5=0, 0, ('09_Quarterly_DT'!G5 - '10_Quarterly_GV'!G5) / '09_Quarterly_DT'!G5) | H5: =IF('09_Quarterly_DT'!H5=0, 0, ('09_Quarterly_DT'!H5 - '10_Quarterly_GV'!H5) / '09_Quarterly_DT'!H5) | I5: =IF('09_Quarterly_DT'!I5=0, 0, ('09_Quarterly_DT'!I5 - '10_Quarterly_GV'!I5) / '09_Quarterly_DT'!I5) | J5: =IF('09_Quarterly_DT'!J5=0, 0, ('09_Quarterly_DT'!J5 - '10_Quarterly_GV'!J5) / '09_Quarterly_DT'!J5) | K5: =AVERAGE(B5:J5)
A6: DV xây dựng | B6: =IF('09_Quarterly_DT'!B6=0, 0, ('09_Quarterly_DT'!B6 - '10_Quarterly_GV'!B6) / '09_Quarterly_DT'!B6) | C6: =IF('09_Quarterly_DT'!C6=0, 0, ('09_Quarterly_DT'!C6 - '10_Quarterly_GV'!C6) / '09_Quarterly_DT'!C6) | D6: =IF('09_Quarterly_DT'!D6=0, 0, ('09_Quarterly_DT'!D6 - '10_Quarterly_GV'!D6) / '09_Quarterly_DT'!D6) | E6: =IF('09_Quarterly_DT'!E6=0, 0, ('09_Quarterly_DT'!E6 - '10_Quarterly_GV'!E6) / '09_Quarterly_DT'!E6) | F6: =IF('09_Quarterly_DT'!F6=0, 0, ('09_Quarterly_DT'!F6 - '10_Quarterly_GV'!F6) / '09_Quarterly_DT'!F6) | G6: =IF('09_Quarterly_DT'!G6=0, 0, ('09_Quarterly_DT'!G6 - '10_Quarterly_GV'!G6) / '09_Quarterly_DT'!G6) | H6: =IF('09_Quarterly_DT'!H6=0, 0, ('09_Quarterly_DT'!H6 - '10_Quarterly_GV'!H6) / '09_Quarterly_DT'!H6) | I6: =IF('09_Quarterly_DT'!I6=0, 0, ('09_Quarterly_DT'!I6 - '10_Quarterly_GV'!I6) / '09_Quarterly_DT'!I6) | J6: =IF('09_Quarterly_DT'!J6=0, 0, ('09_Quarterly_DT'!J6 - '10_Quarterly_GV'!J6) / '09_Quarterly_DT'!J6) | K6: =AVERAGE(B6:J6)
A7: Bán bất động sản | B7: =IF('09_Quarterly_DT'!B7=0, 0, ('09_Quarterly_DT'!B7 - '10_Quarterly_GV'!B7) / '09_Quarterly_DT'!B7) | C7: =IF('09_Quarterly_DT'!C7=0, 0, ('09_Quarterly_DT'!C7 - '10_Quarterly_GV'!C7) / '09_Quarterly_DT'!C7) | D7: =IF('09_Quarterly_DT'!D7=0, 0, ('09_Quarterly_DT'!D7 - '10_Quarterly_GV'!D7) / '09_Quarterly_DT'!D7) | E7: =IF('09_Quarterly_DT'!E7=0, 0, ('09_Quarterly_DT'!E7 - '10_Quarterly_GV'!E7) / '09_Quarterly_DT'!E7) | F7: =IF('09_Quarterly_DT'!F7=0, 0, ('09_Quarterly_DT'!F7 - '10_Quarterly_GV'!F7) / '09_Quarterly_DT'!F7) | G7: =IF('09_Quarterly_DT'!G7=0, 0, ('09_Quarterly_DT'!G7 - '10_Quarterly_GV'!G7) / '09_Quarterly_DT'!G7) | H7: =IF('09_Quarterly_DT'!H7=0, 0, ('09_Quarterly_DT'!H7 - '10_Quarterly_GV'!H7) / '09_Quarterly_DT'!H7) | I7: =IF('09_Quarterly_DT'!I7=0, 0, ('09_Quarterly_DT'!I7 - '10_Quarterly_GV'!I7) / '09_Quarterly_DT'!I7) | J7: =IF('09_Quarterly_DT'!J7=0, 0, ('09_Quarterly_DT'!J7 - '10_Quarterly_GV'!J7) / '09_Quarterly_DT'!J7) | K7: =AVERAGE(B7:J7)
A8: DV khác | B8: =IF('09_Quarterly_DT'!B8=0, 0, ('09_Quarterly_DT'!B8 - '10_Quarterly_GV'!B8) / '09_Quarterly_DT'!B8) | C8: =IF('09_Quarterly_DT'!C8=0, 0, ('09_Quarterly_DT'!C8 - '10_Quarterly_GV'!C8) / '09_Quarterly_DT'!C8) | D8: =IF('09_Quarterly_DT'!D8=0, 0, ('09_Quarterly_DT'!D8 - '10_Quarterly_GV'!D8) / '09_Quarterly_DT'!D8) | E8: =IF('09_Quarterly_DT'!E8=0, 0, ('09_Quarterly_DT'!E8 - '10_Quarterly_GV'!E8) / '09_Quarterly_DT'!E8) | F8: =IF('09_Quarterly_DT'!F8=0, 0, ('09_Quarterly_DT'!F8 - '10_Quarterly_GV'!F8) / '09_Quarterly_DT'!F8) | G8: =IF('09_Quarterly_DT'!G8=0, 0, ('09_Quarterly_DT'!G8 - '10_Quarterly_GV'!G8) / '09_Quarterly_DT'!G8) | H8: =IF('09_Quarterly_DT'!H8=0, 0, ('09_Quarterly_DT'!H8 - '10_Quarterly_GV'!H8) / '09_Quarterly_DT'!H8) | I8: =IF('09_Quarterly_DT'!I8=0, 0, ('09_Quarterly_DT'!I8 - '10_Quarterly_GV'!I8) / '09_Quarterly_DT'!I8) | J8: =IF('09_Quarterly_DT'!J8=0, 0, ('09_Quarterly_DT'!J8 - '10_Quarterly_GV'!J8) / '09_Quarterly_DT'!J8) | K8: =AVERAGE(B8:J8)

Sheet A4_EPS_Bridge
A1: Chỉ tiêu (VND/cp hoặc tỷ VND) | B1: 2021A | C1: 2022A | D1: 2023A | E1: 2024A | F1: 2025A | G1: 2026E | H1: 2027E | I1: 2028E
A2: LNST cổ đông mẹ (tỷ VND) | B2: 835.41 | C2: 977.16 | D2: 926.9 | E2: 1170.16 | F2: 1322.87 | G2: 1459.85 | H2: 1569.56 | I2: 1688.56
A3: Số CP lưu hành (cp) | B3: 242112943 | C3: 242112943 | D3: 242112943 | E3: 242112943 | F3: 242112943 | G3: 242112943 | H3: 242112943 | I3: 242112943
A4: EPS (VND/cp) | B4: 8992 | C4: 4697 | D4: 3992 | E4: 4379 | F4: 4972 | G4: 5115 | H4: 5263 | I4: 5415
A5: BVPS đầu kỳ (VND/cp) | B5: 32046 | C5: 35695 | D5: 19618 | E5: 20613 | F5: 21282 | G5: 24642 | H5: 28099 | I5: 31656
A6: ROE (EPS/BVPS đầu kỳ) | C6: 0.1466 | D6: 0.1118 | E6: 0.2232 | F6: 0.2412 | G6: 0.2403 | H6: 0.2136 | I6: 0.1927
A7: EPS CAGR 3 năm | F7: 0.0289 | G7: 0.0289 | H7: 0.0289 | I7: 0.0289
A9: Căn cứ: EPS CAGR 3 năm = 2.9%; Payout = 34%

Sheet A1_CAGR_Analysis
A1: BẢNG PHÂN TÍCH TĂNG TRƯỞNG — CĂN CỨ GIẢ ĐỊNH DỰ PHÓNG
A2: Chỉ tiêu | B2: 2021 | C2: 2022 | D2: 2023 | E2: 2024 | F2: 2025 | G2: CAGR 3Y | H2: Ghi chú
A3: ── DOANH THU TỔNG CÔNG TY (tỷ VND) ──
A4: Doanh thu thuần | B4: 5577.6 | C4: 6034.5 | D4: 6676.5 | E4: 7801.2 | F4: 8596.2 | G4: 0.1142 | H4: CAGR 5Y lịch sử
A5: YoY DT (%) | C5: 0.0819 | D5: 0.1064 | E5: 0.1684 | F5: 0.1019
A6: ── EPS (VND/cp) ──
A7: EPS lịch sử | B7: 8992 | C7: 4697 | D7: 3992 | E7: 4379 | F7: 4972 | G7: 0.0289 | H7: CAGR EPS dự phóng — dùng cho 02_Assumptions B9
A8: YoY EPS (%) | C8: -0.4776 | D8: -0.1501 | E8: 0.0969 | F8: 0.1354
A9: ── BIÊN LỢI NHUẬN GỘP (%) ──
A10: GM lịch sử | B10: 1.8614 | C10: 1.8507 | D10: 1.8606 | E10: 1.8596 | F10: 1.8437 | G10: 1.8516 | H10: Mean 2Y — giả định cho dự phóng COGS

Sheet A3_KCN_Drivers
A1: BẢNG TƯ DUY ĐẶC THÙ KCN — QUỸ ĐẤT & DOANH THU CHƯA THỰC HIỆN
A2: Căn cứ: T1=PDF CTCK (nếu có) | T2=BCTC thuyết minh | T3=Balance Sheet (bsa58, bsa170, bsa76)
A3: Chỉ tiêu | B3: 2021 | C3: 2022 | D3: 2023 | E3: 2024 | F3: 2025 | G3: 2026E | H3: 2027E | I3: 2028E | J3: Nguồn/Ghi chú
A4: ── QUỸ ĐẤT (từ PDF nếu có) ──
A5: Tổng diện tích KCN (ha) | J5: Nguồn: N/A
A6: Tỷ lệ lấp đầy bình quân (%) | J6: Nguồn: N/A
A7: Giá cho thuê bình quân (USD/m²) | B7: 200 | C7: 200 | D7: 200 | E7: 200 | F7: 200 | G7: 200 | H7: 200 | I7: 200 | J7: T2-BCTC / default 200
A8: Diện tích cho thuê mới (ha/năm) | J8: T2-BCTC markdown
A10: ── PHÂN TÍCH DOANH THU CHƯA THỰC HIỆN & TIỀN NHẬN TRƯỚC ──
A11: Người mua trả tiền trước - ngắn hạn (tỷ) | B11: 281.4 | C11: 26.2 | D11: 54.1 | E11: 9.2 | F11: 25.2 | G11: bsa58 — advance_st
A12: Người mua trả tiền trước - dài hạn (tỷ) | B12: 0 | C12: 0 | D12: 0 | E12: 0 | F12: 0 | G12: bsa170 — advance_lt
A13: Doanh thu chưa thực hiện (tỷ) | B13: 10172.9 | C13: 10720.9 | D13: 10954 | E13: 11729.6 | F13: 12976.4 | G13: bsa76 — deferred_rev
A14: Tổng doanh thu (tỷ) — tham chiếu | B14: 5581.4 | C14: 6037 | D14: 6679.5 | E14: 7804.6 | F14: 8598.3 | G14: isa1
A15: Tỷ lệ advance_st / DT (%) | B15: 0.0504 | C15: 0.0043 | D15: 0.0081 | E15: 0.0012 | F15: 0.0029 | G15: Tỷ lệ đặt cọc so với DT
A16: YoY growth advance_st (%) | C16: -0.9069 | D16: 1.0649 | E16: -0.8301 | F16: 1.7399 | G16: Leading indicator DT năm sau
A18: → g% dự phóng DT cho thuê đất: 17.4% (CAGR advance_st blend) | B18: 0.1741
A19: → Doanh thu ghi nhận từ DTCTH hàng năm ≈ 176 tỷ
A20: → Nguồn tăng trưởng chính: Tiện ích (~80% DT) + Cho thuê đất mới
